Workbook

Sheet 04_09
A1: Tableau des performances hebdomadaires au 04-09-2026
A2: CODE ISIN | B2: Code Maroclear | C2: OPCVM | D2: Société de Gestion | E2: Nature juridique | F2: Classification | G2: Sensibilité | H2: Indice Bentchmark | I2: Périodicité VL | J2: Souscripteurs | K2: Affectation des résultats | L2: Commission de souscription | M2: Commission de rachat | N2: Frais de gestion | O2: Dépositaire | P2: Réseau placeur | Q2: AN | R2: VL | S2: YTD | T2: 1 jour | U2: 1 semaine | V2: 1 mois | W2: 3 mois | X2: 6 mois | Y2: 1 an | Z2: 2 ans | AA2: 3 ans | AB2: 5 ans
A3: MA0000030058 | B3: 3005 | C3: BMCI COSMOS | D3: CIH CAPITAL MANAGEMENT | E3: SICAV | F3: ACTIONS | G3: - | H3: MASI | I3: HEBDOMADAIRE | J3: FGP | K3: CAPITALISANT | L3: 0.02 | M3: 0.0075 | N3: 0.02 | O3: BMCI | P3: CIH CAPITAL MANAGEMENT | Q3: 29912657 | R3: 446 | S3: 0.022818 | T3: - | U3: -0.004886 | V3: -0.000583 | W3: 0.040549 | X3: 0.114109 | Y3: -0.079786 | Z3: 0.361458 | AA3: 0.603451 | AB3: 0.518298
A4: MA0000030066 | B4: 3006 | C4: BMCI EPARGNE OBLIGATIONS | D4: CIH CAPITAL MANAGEMENT | E4: SICAV | F4: OMLT | G4: [3 7[ | H4: MBI MLT | I4: HEBDOMADAIRE | J4: FGP | K4: CAPITALISANT | L4: 0.005 | M4: 0.0025 | N4: 0.0093 | O4: BMCI | P4: CIH CAPITAL MANAGEMENT | Q4: 1.1605659e+08 | R4: 274.32 | S4: -0.008566 | T4: - | U4: -0.001274 | V4: 0.00168 | W4: 0.003218 | X4: 0.000292 | Y4: -0.012029 | Z4: 0.059151 | AA4: 0.158201 | AB4: 0.091083
A5: MA0000030132 | B5: 3013 | C5: BMCI TRESORERIE | D5: CIH CAPITAL MANAGEMENT | E5: SICAV | F5: MONÉTAIRE | G5: [0 0,5[ | H5: TMJ(jj) | I5: QUOTIDIENNE | J5: FGP | K5: CAPITALISANT | L5: 0.0125 | M5: 0.005 | N5: 0.0195 | O5: BMCI | P5: CIH CAPITAL MANAGEMENT | Q5: 1.6391313e+08 | R5: 123521.58 | S5: 0.010523 | T5: - | U5: 0.000191 | V5: 0.00109 | W5: 0.003674 | X5: 0.007571 | Y5: 0.014885 | Z5: 0.032864 | AA5: 0.056679 | AB5: 0.083922
A6: MA0000030215 | B6: 3021 | C6: CDG IZDIHAR | D6: CDG CAPITAL GESTION | E6: SICAV | F6: DIVERSIFIÉ | G6: - | H6: 77% MBI GLOBAL + 23% CFG 25 FLOTTANT | I6: HEBDOMADAIRE | J6: FGP | K6: CAPITALISANT | L6: 0.003 | M6: 0.0025 | N6: 0.02 | O6: CDG CAPITAL | P6: CDG CAPITAL GESTION | Q6: 1.3031416e+09 | R6: 4122.96 | S6: -0.039826 | T6: - | U6: -0.006113 | V6: -0.007599 | W6: 0.010411 | X6: 0.010312 | Y6: -0.101456 | Z6: 0.119001 | AA6: 0.26625 | AB6: 0.176862
A7: MA0000030280 | B7: 3028 | C7: CDG TAWFIR | D7: CDG CAPITAL GESTION | E7: SICAV | F7: OMLT | G7: [3 7[ | H7: MBI GLOBAL | I7: QUOTIDIENNE | J7: FGP | K7: CAPITALISANT | L7: 0.005 | M7: 0 | N7: 0.02 | O7: CDG CAPITAL | P7: CDG CAPITAL GESTION | Q7: 1.7829964e+09 | R7: 3473.73 | S7: -0.001116 | T7: - | U7: -0.001839 | V7: 0.002016 | W7: 0.006455 | X7: 0.007705 | Y7: -0.008234 | Z7: 0.072695 | AA7: 0.16799 | AB7: 0.103816
A8: MA0000030298 | B8: 3029 | C8: SICAV OBLIGATIONS PÉRENNITÉ | D8: CDG CAPITAL GESTION | E8: SICAV | F8: OMLT | G8: [1,1 16[ | H8: MBI MT | I8: QUOTIDIENNE | J8: FNPP | K8: CAPITALISANT | L8: 0.03 | M8: 0.015 | N8: 0.02 | O8: CDG CAPITAL | P8: CDG CAPITAL GESTION | Q8: 6.2754921e+09 | R8: 3297.68 | S8: -0.005453 | T8: - | U8: -0.001729 | V8: 0.00126 | W8: 0.005029 | X8: 0.008388 | Y8: -0.004913 | Z8: 0.048107 | AA8: 0.103918 | AB8: 0.118062
A9: MA0000030306 | B9: 3030 | C9: CDG TRESORERIE | D9: CDG CAPITAL GESTION | E9: SICAV | F9: MONÉTAIRE | G9: [0 0,5[ | H9: 50% MBI CT + 50% TMP | I9: QUOTIDIENNE | J9: FGP | K9: CAPITALISANT | L9: 0 | M9: 0 | N9: 0.02 | O9: CDG CAPITAL | P9: CDG CAPITAL GESTION | Q9: 4.5357895e+09 | R9: 2280.17 | S9: 0.018825 | T9: - | U9: 0.00043 | V9: 0.002066 | W9: 0.006929 | X9: 0.014166 | Y9: 0.026535 | Z9: 0.056671 | AA9: 0.09378 | AB9: 0.138508
A10: MA0000030363 | B10: 3036 | C10: BMCI EPARGNE CROISSANCE | D10: CIH CAPITAL MANAGEMENT | E10: SICAV | F10: DIVERSIFIÉ | G10: - | H10: 60% MASI + 40% MBI MT | I10: HEBDOMADAIRE | J10: FGP | K10: CAPITALISANT | L10: 0.0125 | M10: 0.005 | N10: 0.0195 | O10: BMCI | P10: CIH CAPITAL MANAGEMENT | Q10: 2.6853808e+08 | R10: 165.02 | S10: -0.018556 | T10: - | U10: -0.002539 | V10: 0.000667 | W10: 0.014821 | X10: 0.017951 | Y10: -0.048712 | Z10: 0.128419 | AA10: 0.268799 | AB10: 0.270949
A11: MA0000030371 | B11: 3037 | C11: CIMR TRESO PLUS | D11: SAHAM CAPITAL GESTION | E11: SICAV | F11: OCT | G11: ]0,5 1,1] | H11: MBI CT | I11: QUOTIDIENNE | J11: FNPP | K11: CAPITALISANT | L11: 0 | M11: 0 | N11: 0.02 | O11: SAHAM BANK | P11: SAHAM BANK | Q11: 1.3709135e+08 | R11: 403209.84 | S11: 0.01626 | T11: - | U11: 1.4e-05 | V11: 0.001604 | W11: 0.005912 | X11: 0.012494 | Y11: 0.021415 | Z11: 0.05054 | AA11: 0.08842 | AB11: 0.131864
A12: MA0000030397 | B12: 3039 | C12: CDG BARID | D12: CDG CAPITAL GESTION | E12: SICAV | F12: OMLT | G12: [3 7[ | H12: - | I12: HEBDOMADAIRE | J12: FNPP | K12: CAPITALISANT | L12: 0.005 | M12: 0 | N12: 0.02 | O12: CDG | P12: CDG CAPITAL GESTION | Q12: 3.3974661e+09 | R12: 3728.81 | S12: -0.00703 | T12: - | U12: -0.002015 | V12: 0.001528 | W12: 0.006291 | X12: 0.006008 | Y12: -0.018311 | Z12: 0.070055 | AA12: 0.181589 | AB12: 0.07522
A13: MA0000030405 | B13: 3040 | C13: SICAV MAROC CROISSANCE | D13: MAROGEST | E13: SICAV | F13: DIVERSIFIÉ | G13: - | H13: - | I13: HEBDOMADAIRE | J13: FGP | K13: CAPITALISANT | L13: 0.02 | M13: 0.005 | N13: 0.02 | O13: CIH BANK | P13: MAROGEST | Q13: 3.0421617e+08 | R13: 5184.32 | S13: -0.044115 | T13: - | U13: -0.005624 | V13: -0.007506 | W13: 0.021513 | X13: 0.020266 | Y13: -0.106697 | Z13: 0.140391 | AA13: 0.348819 | AB13: 0.331898
A14: MA0000030413 | B14: 3041 | C14: BMCI CASH | D14: CIH CAPITAL MANAGEMENT | E14: SICAV | F14: OCT | G14: [0,6 1,1[ | H14: MBI CT | I14: QUOTIDIENNE | J14: FGP | K14: CAPITALISANT | L14: 0 | M14: 0 | N14: 0.0067 | O14: BMCI | P14: CIH CAPITAL MANAGEMENT | Q14: 31345674 | R14: 196.49 | S14: 0.021152 | T14: - | U14: -0.000204 | V14: 0.001325 | W14: 0.007744 | X14: 0.018505 | Y14: 0.030308 | Z14: 0.062108 | AA14: 0.093312 | AB14: 0.115596
... A57: MA0000035453 | B57: 3545 | C57: SCR INTEGRALE | D57: CDG CAPITAL GESTION | E57: FCP | F57: ACTIONS | G57: - | H57: CFG 25 FLOTTANT | I57: HEBDOMADAIRE | J57: FNPP | K57: DISTRIBUANT | L57: 0.03 | M57: 0.015 | N57: 0.02 | O57: CDG CAPITAL | P57: CDG CAPITAL GESTION | Q57: 2.2687803e+08 | R57: 6590.11 | S57: -0.052809 | T57: - | U57: -0.00706 | V57: -0.010015 | W57: 0.034424 | X57: 0.072964 | Y57: -0.144061 | Z57: 0.257316 | AA57: 0.504322 | AB57: 0.407589
A58: MA0000035461 | B58: 3546 | C58: SCR OBLIGATIONS | D58: CDG CAPITAL GESTION | E58: FCP | F58: OMLT | G58: ]1,1 9] | H58: MBI GLOBAL | I58: HEBDOMADAIRE | J58: FNPP | K58: CAPITALISANT | L58: 0 | M58: 0 | N58: - | O58: CDG CAPITAL | P58: CDG CAPITAL GESTION | Q58: 2.4192688e+09 | R58: 2729.51 | S58: -0.002011 | T58: - | U58: -0.001697 | V58: 0.001596 | W58: 0.006022 | X58: 0.00625 | Y58: -0.008113 | Z58: 0.071213 | AA58: 0.180613 | AB58: 0.0799
A59: MA0000035487 | B59: 3548 | C59: CDG ACTIONS | D59: CDG CAPITAL GESTION | E59: FCP | F59: ACTIONS | G59: - | H59: CFG 25 FLOTTANT | I59: HEBDOMADAIRE | J59: FNPP | K59: CAPITALISANT | L59: 0.03 | M59: 0.015 | N59: 0.02 | O59: CDG CAPITAL | P59: CDG CAPITAL GESTION | Q59: 1.7631212e+09 | R59: 7646.06 | S59: -0.030572 | T59: - | U59: -0.006923 | V59: -0.005075 | W59: 0.043029 | X59: 0.092167 | Y59: -0.129349 | Z59: 0.233619 | AA59: 0.41789 | AB59: 0.345518
A60: MA0000035495 | B60: 3549 | C60: AL IKRAM | D60: CIH CAPITAL MANAGEMENT | E60: FCP | F60: DIVERSIFIÉ | G60: - | H60: 60% MASI + 40% MBI MT | I60: HEBDOMADAIRE | J60: FNPP | K60: CAPITALISANT | L60: 0.03 | M60: 0.015 | N60: 0.0075 | O60: BMCI | P60: CIH CAPITAL MANAGEMENT | Q60: 34904035 | R60: 36741.09 | S60: -0.003606 | T60: - | U60: -0.003014 | V60: -0.003003 | W60: 0.012287 | X60: 0.028333 | Y60: -0.027695 | Z60: 0.118192 | AA60: 0.230117 | AB60: 0.250894
A61: MA0000035503 | B61: 3550 | C61: CASACTIONS | D61: CIH CAPITAL MANAGEMENT | E61: FCP | F61: DIVERSIFIÉ | G61: - | H61: 80% MBI GLOBAL + 20% MASI | I61: HEBDOMADAIRE | J61: FNPP | K61: DISTRIBUANT | L61: 0.03 | M61: 0.015 | N61: 0.02 | O61: BMCI | P61: CIH CAPITAL MANAGEMENT | Q61: 2469193.4 | R61: 176370.96 | S61: -0.000666 | T61: - | U61: -0.00132 | V61: 9.1e-05 | W61: 0.002939 | X61: 0.003895 | Y61: -0.002508 | Z61: 0.008793 | AA61: 0.030742 | AB61: 0.030856
A62: MA0000035511 | B62: 3551 | C62: AVENIR ACTIONS | D62: CIH CAPITAL MANAGEMENT | E62: FCP | F62: DIVERSIFIÉ | G62: - | H62: 80% MBI GLOBAL + 20% MASI | I62: HEBDOMADAIRE | J62: FNPP | K62: DISTRIBUANT | L62: 0.03 | M62: 0.015 | N62: 0.02 | O62: BMCI | P62: CIH CAPITAL MANAGEMENT | Q62: 2.2489874e+08 | R62: 248781.79 | S62: -0.004295 | T62: - | U62: -0.002795 | V62: -0.001347 | W62: 0.017301 | X62: 0.038092 | Y62: -0.04996 | Z62: 0.123381 | AA62: 0.25473 | AB62: 0.24155
A63: MA0000035529 | B63: 3552 | C63: AXA HORIZON | D63: CIH CAPITAL MANAGEMENT | E63: FCP | F63: DIVERSIFIÉ | G63: - | H63: CFG 25 FLOTTANT | I63: HEBDOMADAIRE | J63: FNPP | K63: MIXTE | L63: 0.03 | M63: 0.015 | N63: 0 | O63: BMCI | P63: CIH CAPITAL MANAGEMENT | Q63: 8.2026232e+08 | R63: 180555.21 | S63: 0.005176 | T63: - | U63: -0.003479 | V63: 0.001572 | W63: 0.016786 | X63: 0.033842 | Y63: -0.028386 | Z63: 0.180174 | AA63: 0.331473 | AB63: 0.287046
A64: MA0000035537 | B64: 3553 | C64: CIMR THARWA | D64: CIH CAPITAL MANAGEMENT | E64: FCP | F64: ACTIONS | G64: - | H64: MASI RN | I64: HEBDOMADAIRE | J64: FNPP | K64: CAPITALISANT | L64: 0 | M64: 0 | N64: 0.02 | O64: BMCI | P64: CIH CAPITAL MANAGEMENT | Q64: 1.1474379e+09 | R64: 516398.69 | S64: 0.023638 | T64: - | U64: -0.005243 | V64: -0.000221 | W64: 0.039627 | X64: 0.119705 | Y64: -0.06798 | Z64: 0.380424 | AA64: 0.652045 | AB64: 0.6405
A65: MA0000035545 | B65: 3554 | C65: BMCI INVEST | D65: CIH CAPITAL MANAGEMENT | E65: FCP | F65: DIVERSIFIÉ | G65: - | H65: 60% MASI + 40% MBI MT | I65: HEBDOMADAIRE | J65: FNPP | K65: CAPITALISANT | L65: 0.03 | M65: 0.015 | N65: 0.006 | O65: BMCI | P65: CIH CAPITAL MANAGEMENT | Q65: 836725.61 | R65: 239.06 | S65: 0.001592 | T65: - | U65: -0.000836 | V65: -0.003335 | W65: -0.006566 | X65: 0.005256 | Y65: -0.015323 | Z65: 0.039889 | AA65: 0.066899 | AB65: 0.056479
A66: MA0000035552 | B66: 3555 | C66: AXA AVENIR | D66: CDG CAPITAL GESTION | E66: FCP | F66: DIVERSIFIÉ | G66: - | H66: 80% MBI GLOBAL + 25% MASI RN | I66: HEBDOMADAIRE | J66: FNPP | K66: MIXTE | L66: 0.03 | M66: 0.015 | N66: 0.02 | O66: CDG CAPITAL | P66: CDG CAPITAL GESTION | Q66: 7.7920621e+08 | R66: 3643.09 | S66: -0.020483 | T66: - | U66: -0.003059 | V66: -0.000373 | W66: 0.016842 | X66: 0.025065 | Y66: -0.06431 | Z66: 0.134575 | AA66: 0.25304 | AB66: 0.194221
A67: MA0000035594 | B67: 3559 | C67: HORIZON BALANCED FUND | D67: SAHAM CAPITAL GESTION | E67: FCP | F67: DIVERSIFIÉ | G67: - | H67: 50% MBI GLOBAL + 50% MASI | I67: QUOTIDIENNE | J67: FGP | K67: DISTRIBUANT | L67: 0.02 | M67: 0.015 | N67: 0.02 | O67: SAHAM BANK | P67: SAHAM BANK | Q67: 1283355 | R67: 106946.25 | S67: -0.009335 | T67: - | U67: -0.003825 | V67: -0.001666 | W67: -0.016707 | X67: 0.027542 | Y67: -0.059033 | Z67: 0.170037 | AA67: 0.356049 | AB67: 0.367711
A68: MA0000035651 | B68: 3565 | C68: ATLAS PREMIUM | D68: ATLAS CAPITAL MANAGEMENT | E68: FCP | F68: ACTIONS | G68: - | H68: MASI | I68: HEBDOMADAIRE | J68: FGP | K68: CAPITALISANT | L68: 0.03 | M68: 0.015 | N68: 0.015 | O68: CIH BANK | P68: ATLAS CAPITAL MANAGEMENT | Q68: 1037503.6 | R68: 756.74 | S68: 0.035949 | T68: - | U68: -0.005493 | V68: -0.001069 | W68: 0.042873 | X68: 0.132912 | Y68: -0.062687 | Z68: 0.416586 | AA68: 0.695814 | AB68: 0.627363
A69: MA0000035677 | B69: 3567 | C69: CDG HORIZONS | D69: CDG CAPITAL GESTION | E69: FCP | F69: OMLT | G69: ]1,1 5,1] | H69: 50% MBI MLT + 50% MBI MT | I69: QUOTIDIENNE | J69: FGP | K69: CAPITALISANT | L69: 0.03 | M69: 0.015 | N69: 0.02 | O69: CDG CAPITAL | P69: CDG CAPITAL GESTION | Q69: 2.3080208e+08 | R69: 2258.44 | S69: 0.00767 | T69: - | U69: -0.000571 | V69: 0.002873 | W69: 0.006695 | X69: 0.010949 | Y69: 0.012976 | Z69: 0.080175 | AA69: 0.142565 | AB69: 0.131069
A70: MA0000035685 | B70: 3568 | C70: AVENIR OBLIGATION | D70: CFG GESTION | E70: FCP | F70: OMLT | G70: [4 8[ | H70: CFG BONDS MT | I70: HEBDOMADAIRE | J70: FNPP | K70: MIXTE | L70: 0 | M70: 0 | N70: 0.01 | O70: ATTIJARIWAFA BANK | P70: CFG GESTION | Q70: 1.4018328e+09 | R70: 26103.92 | S70: -0.00296 | T70: - | U70: -0.000841 | V70: 0.001712 | W70: 0.002787 | X70: 0.000875 | Y70: -0.012978 | Z70: 0.068703 | AA70: 0.178266 | AB70: 0.087156
... A118: MA0000036329 | B118: 3632 | C118: FCP CAPITAL TERME | D118: BMCE CAPITAL GESTION | E118: FCP | F118: DIVERSIFIÉ | G118: - | H118: 80% MBI GLOBAL + 20% MASI | I118: QUOTIDIENNE | J118: FGP | K118: CAPITALISANT | L118: 0.02 | M118: 0.02 | N118: 0.02 | O118: BANK OF AFRICA | P118: BMCE CAPITAL GESTION | Q118: 81016220 | R118: 248.04 | S118: 0.021666 | T118: - | U118: -0.001811 | V118: 0.000161 | W118: 0.028401 | X118: 0.047334 | Y118: -0.007205 | Z118: 0.162651 | AA118: 0.298775 | AB118: 0.251337
A119: MA0000036345 | B119: 3634 | C119: CFG INSTIBONDS | D119: CFG GESTION | E119: FCP | F119: OMLT | G119: ]1,5 5,5] | H119: MBI GLOBAL | I119: QUOTIDIENNE | J119: FGP | K119: CAPITALISANT | L119: 0.03 | M119: 0.015 | N119: 0.02 | O119: CFG BANK | P119: CFG GESTION; CFG BANK | Q119: 5.5279949e+08 | R119: 34.17 | S119: 0.002347 | T119: - | U119: -0.000585 | V119: 0.002641 | W119: 0.005888 | X119: 0.002935 | Y119: -0.780045 | Z119: -0.767741 | AA119: -0.755089 | AB119: -
A120: MA0000036352 | B120: 3635 | C120: FCP CAM TRESO PLUS | D120: MAROGEST | E120: FCP | F120: OCT | G120: ]0,5 1,1] | H120: 85% MBI CT + 15 % MBI MT | I120: QUOTIDIENNE | J120: FGP | K120: CAPITALISANT | L120: 0.03 | M120: 0.015 | N120: 0.02 | O120: CIH BANK | P120: CIH | Q120: 8.7249453e+08 | R120: 174.79 | S120: 0.018887 | T120: - | U120: -0.000172 | V120: 0.001834 | W120: 0.006565 | X120: 0.014275 | Y120: 0.025703 | Z120: 0.061521 | AA120: 0.104448 | AB120: 0.151525
A121: MA0000036378 | B121: 3637 | C121: AVENIR CROISSANCE | D121: CFG GESTION | E121: FCP | F121: ACTIONS | G121: - | H121: CFG 25 FLOTTANT | I121: HEBDOMADAIRE | J121: FNPP | K121: MIXTE | L121: 0.03 | M121: 0.015 | N121: 0.02 | O121: ATTIJARIWAFA BANK | P121: CFG GESTION | Q121: 1297620 | R121: 36045 | S121: -0.038979 | T121: - | U121: -0.003356 | V121: -0.009605 | W121: 0.024839 | X121: 0.051134 | Y121: -0.121713 | Z121: 0.202729 | AA121: 0.458283 | AB121: 0.434454
A122: MA0000036394 | B122: 3639 | C122: FCP CAPITAL TAALIM | D122: BMCE CAPITAL GESTION | E122: FCP | F122: OMLT | G122: [4 8[ | H122: 95% MBI MLT + 5% MASI | I122: HEBDOMADAIRE | J122: FNPP | K122: CAPITALISANT | L122: 0.03 | M122: 0.015 | N122: 0.02 | O122: BANK OF AFRICA | P122: BMCE CAPITAL GESTION | Q122: 3.5469585e+09 | R122: 2369.29 | S122: -0.002476 | T122: - | U122: -0.002194 | V122: 0.001628 | W122: 0.00769 | X122: 0.01154 | Y122: -0.01677 | Z122: 0.095671 | AA122: 0.222922 | AB122: 0.165829
A123: MA0000036402 | B123: 3640 | C123: UPLINE EQUILIBRE | D123: UPLINE CAPITAL MANAGEMENT | E123: FCP | F123: DIVERSIFIÉ | G123: - | H123: 75% MBI GLOBAL + 25% MASI 20 | I123: QUOTIDIENNE | J123: FNPP | K123: MIXTE | L123: 0 | M123: 0 | N123: 0.02 | O123: BCP | P123: UPLINE CAPITAL MANAGEMENT | Q123: 5.6890334e+08 | R123: 124.58 | S123: 0.005423 | T123: - | U123: -0.003758 | V123: -0.002163 | W123: 0.01806 | X123: 0.059711 | Y123: -0.048256 | Z123: 0.190374 | AA123: -0.050326 | AB123: -0.086258
A124: MA0000036436 | B124: 3643 | C124: EMERGENCE CAPITAL | D124: VALORIS MANAGEMENT | E124: FCP | F124: OMLT | G124: [1,1 5,1[ | H124: MBI GLOBAL | I124: HEBDOMADAIRE | J124: FGP | K124: CAPITALISANT | L124: 0.03 | M124: 0.015 | N124: 0.005 | O124: BANK OF AFRICA | P124: VALORIS MANAGEMENT | Q124: 273288824 | R124: 1799.38 | S124: 0.005134 | T124: - | U124: -0.000983 | V124: 0.001737 | W124: 0.005549 | X124: 0.007452 | Y124: 0.0046 | Z124: 0.059269 | AA124: 0.127834 | AB124: 0.110242
A125: MA0000036444 | B125: 3644 | C125: AL IJTIMAI PATRIMOINE | D125: VALORIS MANAGEMENT | E125: FCP | F125: OMLT | G125: [1,1 7,1[ | H125: MBI GLOBAL | I125: HEBDOMADAIRE | J125: FNPP | K125: CAPITALISANT | L125: 0.03 | M125: 0.015 | N125: 0.008 | O125: CDG | P125: VALORIS MANAGEMENT | Q125: 5.0522233e+09 | R125: 214395.21 | S125: 0.005001 | T125: - | U125: 0.002374 | V125: 0.006 | W125: 0.011711 | X125: 0.013192 | Y125: -0.006166 | Z125: 0.093309 | AA125: 0.216864 | AB125: 0.139554
A126: MA0000036485 | B126: 3648 | C126: CAT ACTIONS | D126: CIH CAPITAL MANAGEMENT | E126: FCP | F126: ACTIONS | G126: - | H126: MASI RN | I126: HEBDOMADAIRE | J126: FNPP | K126: DISTRIBUANT | L126: 0 | M126: 0 | N126: 0.02 | O126: BMCI | P126: CIH CAPITAL MANAGEMENT | Q126: 2.8936775e+08 | R126: 505887.68 | S126: 0.029563 | T126: - | U126: 0.013873 | V126: 0.018435 | W126: 0.059921 | X126: 0.123787 | Y126: -0.066276 | Z126: 0.376374 | AA126: 0.6044 | AB126: 0.573048
A127: MA0000036493 | B127: 3649 | C127: FCP CAPITAL MAGHREB | D127: BMCE CAPITAL GESTION | E127: FCP | F127: ACTIONS | G127: - | H127: MASI | I127: QUOTIDIENNE | J127: FGP | K127: CAPITALISANT | L127: 0.02 | M127: 0.02 | N127: 0.02 | O127: BANK OF AFRICA | P127: BMCE CAPITAL GESTION | Q127: 1.4984234e+09 | R127: 1795.48 | S127: 0.009735 | T127: - | U127: -0.00643 | V127: -0.003303 | W127: 0.037232 | X127: 0.117405 | Y127: -0.098682 | Z127: 0.377715 | AA127: 0.725394 | AB127: 0.62907
A128: MA0000036501 | B128: 3650 | C128: FCP CAPITAL MULTI-GESTION | D128: BMCE CAPITAL GESTION | E128: FCP | F128: DIVERSIFIÉ | G128: - | H128: 80% MBI GLOBAL + 20% MASI | I128: QUOTIDIENNE | J128: FGP | K128: CAPITALISANT | L128: 0.02 | M128: 0.02 | N128: 0.02 | O128: BANK OF AFRICA | P128: BMCE CAPITAL GESTION | Q128: 1.7376967e+09 | R128: 544.36 | S128: -0.016211 | T128: - | U128: -0.003077 | V128: -0.001266 | W128: 0.013253 | X128: 0.030224 | Y128: -0.061739 | Z128: 0.130762 | AA128: 0.266101 | AB128: 0.170339
A129: MA0000036519 | B129: 3651 | C129: FCP AL IJTIMAI SECURITE | D129: BMCE CAPITAL GESTION | E129: FCP | F129: OMLT | G129: [1,1 7[ | H129: MBI GLOBAL | I129: HEBDOMADAIRE | J129: FNPP | K129: CAPITALISANT | L129: 0.03 | M129: 0.015 | N129: 0.02 | O129: BANK OF AFRICA | P129: BMCE CAPITAL GESTION | Q129: 3.0176673e+09 | R129: 225047.9 | S129: -0.003419 | T129: - | U129: -0.001662 | V129: 0.001546 | W129: 0.005532 | X129: 0.007169 | Y129: -0.017863 | Z129: 0.084594 | AA129: 0.206594 | AB129: 0.149922
A130: MA0000036527 | B130: 3652 | C130: AL IJTIMAI INMAA | D130: WAFA GESTION | E130: FCP | F130: OMLT | G130: ]1,1 7] | H130: MBI GLOBAL | I130: HEBDOMADAIRE | J130: FNPP | K130: CAPITALISANT | L130: 0.03 | M130: 0.03 | N130: 0.02 | O130: ATTIJARIWAFA BANK | P130: WAFA GESTION | Q130: 5.2342998e+09 | R130: 218450.81 | S130: 0.006006 | T130: - | U130: -0.001448 | V130: 0.002274 | W130: 0.00814 | X130: 0.013458 | Y130: -0.001705 | Z130: 0.098047 | AA130: 0.226024 | AB130: 0.14715
A131: MA0000036535 | B131: 3653 | C131: AL IJTIMAI SOLIDARITE | D131: CFG GESTION | E131: FCP | F131: OMLT | G131: [1,1 7[ | H131: MBI GLOBAL | I131: HEBDOMADAIRE | J131: FNPP | K131: CAPITALISANT | L131: 0 | M131: 0 | N131: 0.02 | O131: CDG | P131: CFG GESTION | Q131: 3.8464538e+09 | R131: 219471.29 | S131: -0.004115 | T131: - | U131: -0.002027 | V131: 0.00113 | W131: 0.005159 | X131: 0.006907 | Y131: -0.015372 | Z131: 0.085751 | AA131: 0.207888 | AB131: 0.127405
... A324: MA0000039034 | B324: 3903 | C324: FH2 ACTIONS | D324: BMCE CAPITAL GESTION | E324: FCP | F324: ACTIONS | G324: - | H324: MASI | I324: QUOTIDIENNE | J324: FNPP | K324: MIXTE | L324: 0 | M324: 0 | N324: 0.02 | O324: BANK OF AFRICA | P324: BMCE CAPITAL GESTION | Q324: 1.4410144e+09 | R324: 1805.08 | S324: 0.01662 | T324: - | U324: -0.00667 | V324: -0.003731 | W324: 0.037671 | X324: 0.120667 | Y324: -0.089617 | Z324: 0.403705 | AA324: 0.764721 | AB324: 0.702456
A325: MA0000039059 | B325: 3905 | C325: WG VALEURS | D325: WAFA GESTION | E325: FCP | F325: ACTIONS | G325: - | H325: MASI RB | I325: QUOTIDIENNE | J325: FGP | K325: MIXTE | L325: 0 | M325: 0 | N325: 0.01 | O325: ATTIJARIWAFA BANK | P325: WAFA GESTION | Q325: 2.1561302e+08 | R325: 1620.36 | S325: 0.111823 | T325: - | U325: -0.001743 | V325: 0.00245 | W325: 0.050981 | X325: 0.161041 | Y325: 0.040841 | Z325: 0.483833 | AA325: 0.722852 | AB325: -
A326: MA0000039067 | B326: 3906 | C326: WG TAYSSIR | D326: WAFA GESTION | E326: FCP | F326: ACTIONS | G326: - | H326: MASI RB | I326: HEBDOMADAIRE | J326: FGP | K326: CAPITALISANT | L326: 0 | M326: 0 | N326: 0.01 | O326: ATTIJARIWAFA BANK | P326: WAFA GESTION | Q326: 2.08029e+08 | R326: 1505.51 | S326: 0.08993 | T326: - | U326: -0.009507 | V326: -0.005108 | W326: 0.033188 | X326: 0.156421 | Y326: -0.013809 | Z326: 0.449599 | AA326: 0.683564 | AB326: -
A327: MA0000039075 | B327: 3907 | C327: FCP OBLIG OPPORTUNITES | D327: IRG ASSET MANAGEMENT | E327: FCP | F327: OMLT | G327: ]1,1 5,1] | H327: MBI MT | I327: QUOTIDIENNE | J327: FGP | K327: CAPITALISANT | L327: 0.03 | M327: 0.015 | N327: 0.02 | O327: CDG | P327: IRG ASSET MANAGEMENT | Q327: 4.4341182e+08 | R327: 104.66 | S327: -0.003618 | T327: - | U327: -0.002002 | V327: 0.000765 | W327: 0.005283 | X327: 0.008771 | Y327: -0.011149 | Z327: 0.04399 | AA327: 0.105291 | AB327: -
A328: MA0000039083 | B328: 3908 | C328: FCP OBLIG LONG TERM | D328: IRG ASSET MANAGEMENT | E328: FCP | F328: OMLT | G328: ]4 8] | H328: 80% MBI MLT+20% MBI LT | I328: HEBDOMADAIRE | J328: FGP | K328: CAPITALISANT | L328: 0.03 | M328: 0.015 | N328: 0.02 | O328: ATTIJARIWAFA BANK | P328: IRG ASSET MANAGEMENT | Q328: 1.283251e+08 | R328: 113.62 | S328: -0.012601 | T328: - | U328: -0.000879 | V328: 0.001057 | W328: -0.000528 | X328: -0.00473 | Y328: -0.01891 | Z328: 0.044301 | AA328: 0.316418 | AB328: -
A329: MA0000039091 | B329: 3909 | C329: CAPITAL TRUST EQUITY | D329: CAPITAL TRUST GESTION | E329: FCP | F329: ACTIONS | G329: - | H329: MASI | I329: QUOTIDIENNE | J329: FGP | K329: CAPITALISANT | L329: 0.03 | M329: 0.015 | N329: 0.02 | O329: BCP | P329: CAPITAL TRUST GESTION | Q329: 9.1462193e+08 | R329: 1454.6 | S329: -0.035366 | T329: - | U329: -0.009054 | V329: -0.007268 | W329: 0.026905 | X329: 0.075705 | Y329: -0.145363 | Z329: 0.265398 | AA329: 0.58709 | AB329: -
A330: MA0000039109 | B330: 3910 | C330: UPLINE PROTECTION DYNAMIQUE | D330: UPLINE CAPITAL MANAGEMENT | E330: FCP | F330: DIVERSIFIÉ | G330: - | H330: - | I330: HEBDOMADAIRE | J330: FGP | K330: CAPITALISANT | L330: 0.002 | M330: 0.002 | N330: 0.02 | O330: BCP | P330: BANQUE POPULAIRE | Q330: 5.6934753e+08 | R330: 1174.8 | S330: 0.006805 | T330: - | U330: -0.001301 | V330: -0.000247 | W330: 0.010963 | X330: 0.032791 | Y330: -0.015033 | Z330: 0.112953 | AA330: 0.181226 | AB330: -
A331: MA0000039117 | B331: 3911 | C331: CAM OBLIBANQUES | D331: MAROGEST | E331: FCP | F331: OCT | G331: ]0,5 1,1] | H331: 85% MBI CT + 15% MBI MT | I331: QUOTIDIENNE | J331: FGP | K331: CAPITALISANT | L331: 0.03 | M331: 0.015 | N331: 0.02 | O331: CIH BANK | P331: CAM; MSIN; CIH; MAROGEST | Q331: 1.8791663e+09 | R331: 1147.38 | S331: 0.018743 | T331: - | U331: -0.000148 | V331: 0.00193 | W331: 0.006509 | X331: 0.014214 | Y331: 0.026747 | Z331: 0.063876 | AA331: 0.107937 | AB331: -
A332: MA0000039125 | B332: 3912 | C332: CAM OBLIRENDEMENT | D332: MAROGEST | E332: FCP | F332: OMLT | G332: ]1,1 5,1] | H332: 100% MBI MT | I332: QUOTIDIENNE | J332: FGP | K332: CAPITALISANT | L332: 0.03 | M332: 0.015 | N332: 0.02 | O332: CIH BANK | P332: CAM; MSIN; CIH; MAROGEST | Q332: 3.9117292e+08 | R332: 1150.96 | S332: -0.005736 | T332: - | U332: -0.002911 | V332: -0.0004 | W332: 0.00474 | X332: 0.005583 | Y332: -0.010778 | Z332: 0.066474 | AA332: 0.13647 | AB332: -
A333: MA0000039133 | B333: 3913 | C333: CKG ISR SELECTION | D333: CDG CAPITAL GESTION | E333: FCP | F333: ACTIONS | G333: - | H333: ESG 10 | I333: HEBDOMADAIRE | J333: FGP | K333: CAPITALISANT | L333: 0.03 | M333: 0.015 | N333: 0.02 | O333: CDG CAPITAL | P333: CDG CAPITAL GESTION | Q333: 2.5011301e+08 | R333: 962.8 | S333: 0.018319 | T333: - | U333: 0.00027 | V333: 0.004748 | W333: 0.040989 | X333: 0.106298 | Y333: -0.084521 | Z333: 0.037612 | AA333: 0.131215 | AB333: -
A334: MA0000039141 | B334: 3914 | C334: AD SELECT BANQUES | D334: AD CAPITAL ASSET MANAGEMENT | E334: FCP | F334: OCT | G334: ]0,5 1,1] | H334: MBI CT | I334: QUOTIDIENNE | J334: FGP | K334: CAPITALISANT | L334: 0.03 | M334: 0.03 | N334: 0.02 | O334: CFG BANK | P334: AD CAPITAL ASSET MANAGEMENT; AD CAPITAL GROUP | Q334: 2.0738869e+09 | R334: 1153.44 | S334: 0.019832 | T334: - | U334: -0.000121 | V334: 0.002033 | W334: 0.007345 | X334: 0.015281 | Y334: 0.027994 | Z334: 0.067664 | AA334: 0.114467 | AB334: -
A335: MA0000039158 | B335: 3915 | C335: AD COMPACT OBLIGATAIRE | D335: AD CAPITAL ASSET MANAGEMENT | E335: FCP | F335: OMLT | G335: [3,5 7,5[ | H335: MBI GLOBAL | I335: HEBDOMADAIRE | J335: FGP | K335: CAPITALISANT | L335: 0.03 | M335: 0.03 | N335: 0.02 | O335: CFG BANK | P335: AD CAPITAL ASSET MANAGEMENT; AD CAPITAL GROUP | Q335: 3.1599779e+09 | R335: 1165.21 | S335: -0.005929 | T335: - | U335: -0.002004 | V335: 0.000816 | W335: 0.005115 | X335: 0.005931 | Y335: -0.019316 | Z335: 0.090837 | AA335: 0.18859 | AB335: -
A336: MA0000039166 | B336: 3916 | C336: CAPITAL TRUST PATRIMOINE | D336: CAPITAL TRUST GESTION | E336: FCP | F336: DIVERSIFIÉ | G336: - | H336: 25% MASI + 30% MBI GLOBAL + 45% MBI MLT | I336: QUOTIDIENNE | J336: FGP | K336: CAPITALISANT | L336: 0.03 | M336: 0.015 | N336: 0.02 | O336: BCP | P336: CAPITAL TRUST GESTION | Q336: 7.2063236e+08 | R336: 1351.03 | S336: -0.022155 | T336: - | U336: -0.005777 | V336: -0.004392 | W336: 0.010297 | X336: 0.033577 | Y336: -0.081476 | Z336: 0.260454 | AA336: 0.40096 | AB336: -
... A340: MA0000039208 | B340: 3920 | C340: TWIN OPPORTUNITY | D340: TWIN CAPITAL GESTION | E340: FCP | F340: DIVERSIFIÉ | G340: - | H340: 30% MASI + 70% MBI | I340: HEBDOMADAIRE | J340: FGP | K340: CAPITALISANT | L340: 0.015 | M340: 0.015 | N340: 0.01 | O340: CFG BANK | P340: TWIN CAPITAL GESTION; CFG BANK | Q340: 2.8618888e+08 | R340: 1199.23 | S340: -0.033526 | T340: - | U340: -0.003358 | V340: -0.00291 | W340: 0.011684 | X340: 0.025211 | Y340: -0.110304 | Z340: 0.122885 | AA340: 0.190515 | AB340: -
A341: MA0000039216 | B341: 3921 | C341: FCP CAPITAL ISR | D341: BMCE CAPITAL GESTION | E341: FCP | F341: DIVERSIFIÉ | G341: - | H341: 75% MBI GLOBAL + 25% MASI ESG | I341: QUOTIDIENNE | J341: FGP | K341: CAPITALISANT | L341: 0.02 | M341: 0.01 | N341: 0.02 | O341: BANK OF AFRICA | P341: BMCE CAPITAL GESTION | Q341: 8.123772e+08 | R341: 1470.52 | S341: -0.025513 | T341: - | U341: 0.000933 | V341: 0.002905 | W341: 0.014124 | X341: 0.0174 | Y341: -0.082594 | Z341: 0.105879 | AA341: 0.253929 | AB341: 0.129605
A342: MA0000039224 | B342: 3922 | C342: IRGAM ALLOCATION | D342: IRG ASSET MANAGEMENT | E342: FCP | F342: DIVERSIFIÉ | G342: - | H342: 40 % MASI RB + 60 % MBI GLOBAL | I342: HEBDOMADAIRE | J342: FNPP | K342: MIXTE | L342: 0 | M342: 0 | N342: 0.02 | O342: ATTIJARIWAFA BANK | P342: IRG ASSET MANAGEMENT | Q342: 5.1887505e+08 | R342: 252.66 | S342: 0.018212 | T342: - | U342: -0.003942 | V342: 0.002341 | W342: 0.028034 | X342: 0.068545 | Y342: -0.039245 | Z342: 0.232795 | AA342: 0.444145 | AB342: 0.383046
A343: MA0000039232 | B343: 3923 | C343: CAPITAL RENDEMENT PLUS | D343: BMCE CAPITAL GESTION | E343: FCP | F343: OMLT | G343: ]1,1 5] | H343: MBI GLOBAL | I343: QUOTIDIENNE | J343: FGP | K343: MIXTE | L343: 0.02 | M343: 0.01 | N343: 0.02 | O343: BANK OF AFRICA | P343: BMCE CAPITAL GESTION; BANK OF AFRICA | Q343: 1131315.2 | R343: 1131.31 | S343: 0.00679 | T343: - | U343: -0.000777 | V343: 0.00209 | W343: 0.005162 | X343: 0.007579 | Y343: 0.007077 | Z343: 0.048879 | AA343: 0.106892 | AB343: -
A344: MA0000039240 | B344: 3924 | C344: AFG SECUR RENDEMENT | D344: AFG ASSET MANAGEMENT | E344: FCP | F344: OMLT | G344: ]1,1 7] | H344: MBI Global | I344: HEBDOMADAIRE | J344: FNPP | K344: CAPITALISANT | L344: 0 | M344: 0 | N344: 0.02 | O344: CDG | P344: AFG ASSET MANAGEMENT | Q344: 2.8564811e+09 | R344: 1257.58 | S344: -0.000715 | T344: - | U344: -0.001968 | V344: 0.001362 | W344: 0.007442 | X344: 0.012919 | Y344: -0.015385 | Z344: 0.091763 | AA344: 0.213494 | AB344: -
A345: MA0000039281 | B345: 3928 | C345: BMCI PREMIUM SHORT BOND DIST | D345: CIH CAPITAL MANAGEMENT | E345: FCP | F345: OCT | G345: ]0,5 1,1] | H345: MBI CT | I345: QUOTIDIENNE | J345: FGP | K345: DISTRIBUANT | L345: 0 | M345: 0 | N345: 0.02 | O345: BMCI | P345: CIH CAPITAL MANAGEMENT | Q345: 4768705.9 | R345: 134.21 | S345: 0.013518 | T345: - | U345: -0.000372 | V345: 0.001268 | W345: 0.004566 | X345: 0.010618 | Y345: 0.018208 | Z345: 0.046227 | AA345: 0.090216 | AB345: 0.132843
A346: MA0000039299 | B346: 3929 | C346: WINEO SECUR RENDEMENT | D346: WINEO GESTION | E346: FCP | F346: OMLT | G346: ]1,1 7] | H346: MBI GLOBAL | I346: HEBDOMADAIRE | J346: FNPP | K346: CAPITALISANT | L346: 0 | M346: 0 | N346: 0.02 | O346: CDG | P346: WINEO GESTION | Q346: 2.1924105e+09 | R346: 1259.95 | S346: 0.007654 | T346: - | U346: -0.001221 | V346: 0.002642 | W346: 0.008727 | X346: 0.013971 | Y346: -0.003015 | Z346: 0.097355 | AA346: 0.211176 | AB346: -
A347: MA0000039315 | B347: 3931 | C347: CFG OPPORTUNITÉS | D347: CFG GESTION | E347: FCP | F347: DIVERSIFIÉ | G347: - | H347: 70% MBI GLOBAL + 30% MASI | I347: QUOTIDIENNE | J347: FGP | K347: MIXTE | L347: 0.03 | M347: 0.015 | N347: 0.02 | O347: CFG BANK | P347: CFG GESTION; CFG BANK | Q347: 97448692 | R347: 1245.49 | S347: 0.03477 | T347: - | U347: -0.002243 | V347: -0.001443 | W347: 0.008584 | X347: 0.039641 | Y347: -0.014348 | Z347: 0.14869 | AA347: 0.209073 | AB347: -
A348: MA0000039323 | B348: 3932 | C348: CFG Diversifié | D348: CFG GESTION | E348: FCP | F348: DIVERSIFIÉ | G348: - | H348: 80% MBI GLOBAL + 20% MASI RN | I348: QUOTIDIENNE | J348: FGP | K348: CAPITALISANT | L348: 0.03 | M348: 0.015 | N348: 0.02 | O348: CFG BANK | P348: CFG GESTION; CFG BANK | Q348: 94680823 | R348: 1219.58 | S348: -0.01271 | T348: - | U348: -0.003847 | V348: -0.004116 | W348: 0.014946 | X348: 0.068823 | Y348: -0.019007 | Z348: 0.095297 | AA348: 0.168997 | AB348: -
A349: MA0000039331 | B349: 3933 | C349: UPLINE CROISSANCE | D349: UPLINE CAPITAL MANAGEMENT | E349: FCP | F349: DIVERSIFIÉ | G349: - | H349: 70% MBI + 30% MASI RB | I349: QUOTIDIENNE | J349: FNPP | K349: MIXTE | L349: 0 | M349: 0 | N349: 0.02 | O349: BCP | P349: UPLINE CAPITAL MANAGEMENT | Q349: 1104864 | R349: 1104.86 | S349: -0.006474 | T349: - | U349: -0.001888 | V349: 0.001823 | W349: 0.012583 | X349: 0.015571 | Y349: -0.02021 | Z349: 0.061467 | AA349: 0.089273 | AB349: -
A350: MA0000039349 | B350: 3934 | C350: UPLINE SECURITIES PERFORMANCE | D350: UPLINE CAPITAL MANAGEMENT | E350: FCP | F350: DIVERSIFIÉ | G350: - | H350: 75% MBI + 25% MASI RB | I350: HEBDOMADAIRE | J350: FNPP | K350: MIXTE | L350: 0 | M350: 0 | N350: 0.02 | O350: BCP | P350: UPLINE CAPITAL MANAGEMENT | Q350: 1091806 | R350: 1091.81 | S350: -0.009121 | T350: - | U350: -0.002148 | V350: 0.001578 | W350: 0.012257 | X350: 0.013554 | Y350: -0.023976 | Z350: 0.054247 | AA350: 0.078224 | AB350: -
A351: MA0000039356 | B351: 3935 | C351: FCP EMERGENCE PATRIMOINE | D351: VALORIS MANAGEMENT | E351: FCP | F351: DIVERSIFIÉ | G351: - | H351: 80% MBI GLOBAL + 20% MASI RB | I351: QUOTIDIENNE | J351: FNPP | K351: CAPITALISANT | L351: 0 | M351: 0 | N351: 0.02 | O351: BANK OF AFRICA | P351: VALORIS MANAGEMENT | Q351: 869934.58 | R351: 178.52 | S351: -0.016419 | T351: - | U351: -0.000336 | V351: -0.003628 | W351: 0.018659 | X351: 0.023859 | Y351: -0.054449 | Z351: 0.205809 | AA351: 0.358083 | AB351: 0.348033
A352: MA0000039364 | B352: 3936 | C352: PROFIL FLEXIBLE | D352: WAFA GESTION | E352: FCP | F352: DIVERSIFIÉ | G352: - | H352: 75% MASI + 25% MBI MT | I352: QUOTIDIENNE | J352: FGP | K352: DISTRIBUANT | L352: 0.02 | M352: 0.02 | N352: 0.02 | O352: ATTIJARIWAFA BANK | P352: WAFA GESTION; ATTIJARIWAFA BANK | Q352: 1.083591e+09 | R352: 1727.6 | S352: 0.092526 | T352: - | U352: -8.1e-05 | V352: 0.006074 | W352: 0.033371 | X352: 0.101027 | Y352: 0.028444 | Z352: 0.251168 | AA352: 0.329383 | AB352: 0.284003
A353: MA0000039372 | B353: 3937 | C353: AFG T-BOND FUND | D353: AFG ASSET MANAGEMENT | E353: FCP | F353: OMLT | G353: ]1,1 10] | H353: MBI MLT | I353: QUOTIDIENNE | J353: FNPP | K353: MIXTE | L353: 0 | M353: 0 | N353: 0.02 | O353: ATTIJARIWAFA BANK | P353: AFG ASSET MANAGEMENT | Q353: 1.2279669e+09 | R353: 1125.13 | S353: -0.031101 | T353: - | U353: -0.001969 | V353: 0.000872 | W353: 0.004356 | X353: 0.00367 | Y353: -0.040702 | Z353: 0.101964 | AA353: 0.247608 | AB353: -
A354: MA0000039380 | B354: 3938 | C354: ATLAS HARMONIE | D354: ATLAS CAPITAL MANAGEMENT | E354: FCP | F354: OMLT | G354: ]1,1; 8] | H354: MBI GLOBAL | I354: HEBDOMADAIRE | J354: FNPP | K354: CAPITALISANT | L354: 0.03 | M354: 0.03 | N354: 0.02 | O354: CIH BANK | P354: ATLAS CAPITAL MANAGEMENT | Q354: 2.5529269e+09 | R354: 250.32 | S354: 0.00048 | T354: - | U354: -0.001117 | V354: 0.002322 | W354: 0.004615 | X354: 0.005503 | Y354: -0.004969 | Z354: 0.076044 | AA354: 0.177035 | AB354: 0.162927
A355: MA0000039398 | B355: 3939 | C355: IRGAM DISTRIEQUILIBRE | D355: IRG ASSET MANAGEMENT | E355: FCP | F355: DIVERSIFIÉ | G355: - | H355: 30% MASI FLOTTANT + 70% MBI GLOBAL | I355: HEBDOMADAIRE | J355: FGP | K355: MIXTE | L355: 0.03 | M355: 0.015 | N355: 0.02 | O355: BCP | P355: IRG ASSET MANAGEMENT | Q355: 1.2315864e+09 | R355: 140.88 | S355: -0.009004 | T355: - | U355: -0.002972 | V355: -0.000426 | W355: 0.009892 | X355: 0.020278 | Y355: -0.040327 | Z355: 0.273895 | AA355: 0.407393 | AB355: -
A356: MA0000039406 | B356: 3940 | C356: IRGAM DISTRIEQUITY | D356: IRG ASSET MANAGEMENT | E356: FCP | F356: ACTIONS | G356: - | H356: MASI | I356: HEBDOMADAIRE | J356: FGP | K356: MIXTE | L356: 0.03 | M356: 0.015 | N356: 0.02 | O356: BCP | P356: IRG ASSET MANAGEMENT | Q356: 1613296.5 | R356: 161.33 | S356: -0.050106 | T356: - | U356: -0.006038 | V356: -0.01544 | W356: 0.021205 | X356: 0.037492 | Y356: -0.081892 | Z356: 0.375714 | AA356: 0.607353 | AB356: -
A357: MA0000039414 | B357: 3941 | C357: FCP EMERGENCE ACTIONS | D357: VALORIS MANAGEMENT | E357: FCP | F357: ACTIONS | G357: - | H357: MASI 20 | I357: QUOTIDIENNE | J357: FGP | K357: CAPITALISANT | L357: 0.03 | M357: 0.015 | N357: 0.02 | O357: ATTIJARIWAFA BANK | P357: VALORIS GROUP;VALORIS MANAGEMENT | Q357: 3.4557177e+08 | R357: 1881.48 | S357: 0.001117 | T357: - | U357: -0.00682 | V357: -0.002402 | W357: 0.04063 | X357: 0.108487 | Y357: -0.098774 | Z357: 0.405936 | AA357: 0.813597 | AB357: -
A358: MA0000039422 | B358: 3942 | C358: FCP EMERGENCE PERSPECTIVES | D358: VALORIS MANAGEMENT | E358: FCP | F358: DIVERSIFIÉ | G358: - | H358: 80% MBI GLOBAL + 20% MASI RB | I358: HEBDOMADAIRE | J358: FNPP | K358: MIXTE | L358: 0 | M358: 0 | N358: 0.02 | O358: SAHAM BANK | P358: VALORIS GROUP;VALORIS MANAGEMENT | Q358: 1.841614e+09 | R358: 1318.65 | S358: 0.008883 | T358: - | U358: -0.000856 | V358: 0.003378 | W358: 0.014502 | X358: 0.027851 | Y358: -0.016072 | Z358: 0.156122 | AA358: 0.307316 | AB358: -
A359: MA0000039430 | B359: 3943 | C359: FCP SANLAM OBLIGATIONS | D359: VALORIS MANAGEMENT | E359: FCP | F359: OMLT | G359: ]1,1 10] | H359: MBI GLOBAL | I359: QUOTIDIENNE | J359: FNPP | K359: MIXTE | L359: 0.03 | M359: 0.015 | N359: 0.02 | O359: BCP | P359: VALORIS MANAGEMENT | Q359: 9.9878371e+08 | R359: 1280.37 | S359: -0.016862 | T359: - | U359: -0.001894 | V359: 0.002043 | W359: 0.006509 | X359: 0.003976 | Y359: -0.02176 | Z359: 0.11353 | AA359: 0.262482 | AB359: -
A360: MA0000039448 | B360: 3944 | C360: AFG GOV BOND FUND | D360: AFG ASSET MANAGEMENT | E360: FCP | F360: OMLT | G360: ]4 8] | H360: MBI GLOBAL | I360: QUOTIDIENNE | J360: FGP | K360: MIXTE | L360: 0.03 | M360: 0.03 | N360: 0.02 | O360: ATTIJARIWAFA BANK | P360: AFG ASSET MANAGEMENT | Q360: 2.5122413e+09 | R360: 1222.16 | S360: -0.011093 | T360: - | U360: -0.001642 | V360: 0.001557 | W360: 0.002518 | X360: 0.002395 | Y360: -0.027678 | Z360: 0.071084 | AA360: 0.191143 | AB360: -
A361: MA0000039455 | B361: 3945 | C361: AFG FLEXIBLE FUND | D361: AFG ASSET MANAGEMENT | E361: FCP | F361: DIVERSIFIÉ | G361: - | H361: 75% MBI GLOBAL + 25% MASI RB | I361: QUOTIDIENNE | J361: FNPP | K361: MIXTE | L361: 0.03 | M361: 0.03 | N361: 0.02 | O361: BCP | P361: AFG ASSET MANAGEMENT | Q361: 9.2148076e+08 | R361: 1346.08 | S361: -0.00793 | T361: - | U361: -0.00311 | V361: 0.000885 | W361: 0.015725 | X361: 0.039532 | Y361: -0.043946 | Z361: 0.17631 | AA361: 0.385807 | AB361: -
A362: MA0000039463 | B362: 3946 | C362: ATLAS LIQUIDITE | D362: ATLAS CAPITAL MANAGEMENT | E362: FCP | F362: OCT | G362: 0,5 ; 1,1] | H362: MBI CT | I362: QUOTIDIENNE | J362: FGP | K362: CAPITALISANT | L362: 0.03 | M362: 0.03 | N362: 0.02 | O362: BANK OF AFRICA | P362: ATLAS CAPITAL MANAGEMENT | Q362: 51708145 | R362: 148.31 | S362: 0.017983 | T362: - | U362: -0.000135 | V362: 0.001892 | W362: 0.006583 | X362: 0.014016 | Y362: 0.025232 | Z362: 0.058979 | AA362: 0.080504 | AB362: 0.068747
A363: MA0000039471 | B363: 3947 | C363: AZ TAWFIR | D363: WAFA GESTION | E363: FCP | F363: OMLT | G363: ]1,1 13] | H363: MBI MLT | I363: QUOTIDIENNE | J363: FNPP | K363: MIXTE | L363: 0.03 | M363: 0.015 | N363: 0.02 | O363: BCP | P363: WAFA GESTION | Q363: 3.8228321e+08 | R363: 842033.5 | S363: -0.014647 | T363: - | U363: -0.001041 | V363: 0.002595 | W363: 0.001332 | X363: -0.003472 | Y363: -0.024616 | Z363: 0.059971 | AA363: 0.236813 | AB363: 0.116449
A364: MA0000039489 | B364: 3948 | C364: UNIVERS DIVERSIFIE | D364: WAFA GESTION | E364: FCP | F364: DIVERSIFIÉ | G364: - | H364: 30% MASI RB + 70% MBI MLT | I364: HEBDOMADAIRE | J364: FNPP | K364: MIXTE | L364: 0 | M364: 0 | N364: 0.02 | O364: ATTIJARIWAFA BANK | P364: WAFA GESTION | Q364: 2.1601284e+08 | R364: 2023.71 | S364: 0.018347 | T364: - | U364: -0.003624 | V364: -0.00152 | W364: 0.025364 | X364: 0.062298 | Y364: -0.02274 | Z364: 0.230024 | AA364: 0.409534 | AB364: 0.366282
A365: MA0000039497 | B365: 3949 | C365: CAPITAL IMTIYAZ GARANTI | D365: BMCE CAPITAL GESTION | E365: FCP | F365: CONTRACTUEL | G365: - | H365: MONIA | I365: QUOTIDIENNE | J365: FGP | K365: CAPITALISANT | L365: 0.01 | M365: 0.01 | N365: 0.02 | O365: BANK OF AFRICA | P365: BMCE CAPITAL GESTION | Q365: 1559702191 | R365: 1061.41 | S365: 0.014286 | T365: - | U365: 0.000396 | V365: 0.001576 | W365: 0.005133 | X365: 0.010289 | Y365: 0.020577 | Z365: 0.043986 | AA365: - | AB365: -
A366: MA0000039505 | B366: 3950 | C366: GENERATION PERFORMANCE | D366: UPLINE CAPITAL MANAGEMENT | E366: SICAV | F366: OMLT | G366: ]1,1 12] | H366: MBI GLOBAL + 50 pbs | I366: HEBDOMADAIRE | J366: FNPP | K366: CAPITALISANT | L366: 0 | M366: 0 | N366: 0.02 | O366: BCP | P366: UPLINE CAPITAL MANAGEMENT | Q366: 4.7670436e+08 | R366: 1107.33 | S366: 0.00973 | T366: - | U366: -0.000307 | V366: 0.002254 | W366: 0.006389 | X366: 0.009196 | Y366: 0.010347 | Z366: 0.080059 | AA366: - | AB366: -
A367: MA0000039513 | B367: 3951 | C367: FCP MAROGEST BONDS | D367: MAROGEST | E367: FCP | F367: OMLT | G367: ]1,1 8,1] | H367: 100% MBI GLOBAL | I367: QUOTIDIENNE | J367: FNPP | K367: CAPITALISANT | L367: 0 | M367: 0 | N367: 0 | O367: CIH BANK | P367: MAROGEST | Q367: 7.6358995e+08 | R367: 1084.17 | S367: -0.017285 | T367: - | U367: -0.003044 | V367: -0.000839 | W367: 0.003369 | X367: 0.002172 | Y367: -0.028696 | Z367: 0.060832 | AA367: - | AB367: -
A368: MA0000039521 | B368: 3952 | C368: MAROGEST SECUR RENDEMENT | D368: MAROGEST | E368: FCP | F368: OMLT | G368: ]1,1 7] | H368: 100% MBI GLOBAL | I368: HEBDOMADAIRE | J368: FNPP | K368: CAPITALISANT | L368: 0 | M368: 0 | N368: 0 | O368: CDG | P368: MAROGEST | Q368: 5.4447463e+08 | R368: 1132.25 | S368: -0.002177 | T368: - | U368: -0.001596 | V368: 0.0013 | W368: 0.007591 | X368: 0.009883 | Y368: -0.011386 | Z368: 0.08751 | AA368: - | AB368: -
A369: MA0000039539 | B369: 3953 | C369: ATTIJARI PRIVATE FUND | D369: WAFA GESTION | E369: FCP | F369: DIVERSIFIÉ | G369: - | H369: 50% MASI RB + 50% MBI GLOBAL | I369: HEBDOMADAIRE | J369: FGP | K369: MIXTE | L369: 0.02 | M369: 0.02 | N369: 0.02 | O369: ATTIJARIWAFA BANK | P369: WAFA GESTION | Q369: 8.5198545e+08 | R369: 1145141.7 | S369: 0.068807 | T369: - | U369: -0.003977 | V369: 0.011259 | W369: 0.034857 | X369: 0.087839 | Y369: 0.051335 | Z369: 0.127554 | AA369: - | AB369: -
A370: MA0000039547 | B370: 3954 | C370: FCP ALPHA BONDS | D370: RED MED ASSET MANAGEMENT | E370: FCP | F370: OMLT | G370: ]1,1 10] | H370: MBI GLOBAL | I370: QUOTIDIENNE | J370: FNPP | K370: CAPITALISANT | L370: 0 | M370: 0 | N370: 0.02 | O370: BCP | P370: RED MED ASSET MANAGEMENT | Q370: 2.3238112e+09 | R370: 1208.99 | S370: 7.4e-05 | T370: - | U370: -0.000744 | V370: 0.002388 | W370: 0.004236 | X370: 0.005038 | Y370: -0.003388 | Z370: 0.075681 | AA370: 0.172593 | AB370: -
A371: MA0000039554 | B371: 3955 | C371: AD HARMONIE DIVERSIFIÉ | D371: AD CAPITAL ASSET MANAGEMENT | E371: FCP | F371: DIVERSIFIÉ | G371: - | H371: 50% MASI + 50% MBI MLT | I371: HEBDOMADAIRE | J371: FGP | K371: DISTRIBUANT | L371: 0.03 | M371: 0.03 | N371: 0.02 | O371: ATTIJARIWAFA BANK | P371: AD CAPITAL ASSET MANAGEMENT; AD CAPITAL GROUP | Q371: 5.0305741e+08 | R371: 1115.27 | S371: -0.048794 | T371: - | U371: 0.002139 | V371: -0.000735 | W371: 0.009742 | X371: 0.017684 | Y371: -0.098429 | Z371: 0.115303 | AA371: - | AB371: -
A372: MA0000039570 | B372: 3957 | C372: AFG ACTIVE BOND FUND | D372: AFG ASSET MANAGEMENT | E372: FCP | F372: OMLT | G372: ]4 8] | H372: 95% MBI GLOBAL + 5% MASI | I372: QUOTIDIENNE | J372: FGP | K372: MIXTE | L372: 0.03 | M372: 0.03 | N372: 0.02 | O372: BANQUE CENTRALE POPULAIRE | P372: AFG ASSET MANAGEMENT | Q372: 1.1618219e+09 | R372: 1097.66 | S372: -0.013534 | T372: - | U372: -0.002245 | V372: -0.000173 | W372: 0.003015 | X372: 0.00352 | Y372: -0.026586 | Z372: - | AA372: - | AB372: -
A373: MA0000039596 | B373: 3959 | C373: FH2 OBLIGATAIRE DYNAMIQUE II | D373: BMCE CAPITAL GESTION | E373: FCP | F373: OMLT | G373: ]1,1 7,1] | H373: MBI Global | I373: HEBDOMADAIRE | J373: FNPP | K373: MIXTE | L373: 0 | M373: 0 | N373: 0.02 | O373: BANK OF AFRICA | P373: BMCE CAPITAL GESTION | Q373: 2.1195421e+09 | R373: 1229.86 | S373: 0.000464 | T373: - | U373: -0.001056 | V373: 0.002462 | W373: 0.002502 | X373: 0.001865 | Y373: -0.002636 | Z373: - | AA373: - | AB373: -
A374: MA0000039604 | B374: 3960 | C374: FCP EMERGENCE OPTIMUM | D374: VALORIS MANAGEMENT | E374: FCP | F374: DIVERSIFIÉ | G374: - | H374: 60% MBI + 40% MASI | I374: QUOTIDIENNE | J374: FGP | K374: MIXTE | L374: 0.03 | M374: 0.015 | N374: 0.02 | O374: CREDIT DU MAROC | P374: VALORIS MANAGEMENT | Q374: 1.5927462e+09 | R374: 1183.84 | S374: -0.01578 | T374: - | U374: -0.003326 | V374: 0.000634 | W374: 0.016337 | X374: 0.03554 | Y374: -0.062194 | Z374: - | AA374: - | AB374: -
A375: MA0000039612 | B375: 3961 | C375: CCM SECUR RENDEMENT | D375: CIH CAPITAL MANAGEMENT | E375: FCP | F375: OMLT | G375: [1,1 7] | H375: MBI GLOBAL | I375: HEBDOMADAIRE | J375: FNPP | K375: CAPITALISANT | L375: 0 | M375: 0 | N375: 0.02 | O375: CDG | P375: CIH CAPITAL MANAGEMENT | Q375: 1.0277879e+09 | R375: 1131.88 | S375: 0.000716 | T375: - | U375: -0.001306 | V375: 0.00193 | W375: 0.006491 | X375: 0.010688 | Y375: -0.009971 | Z375: - | AA375: - | AB375: -
A376: MA0000039620 | B376: 3962 | C376: FCP FH2 OBLIGATAIRE DP | D376: VALORIS MANAGEMENT | E376: FCP | F376: OMLT | G376: [1,1 5] | H376: 90% MBI MT + 10% MBI MLT + 50 pbs | I376: QUOTIDIENNE | J376: FNPP | K376: MIXTE | L376: 0 | M376: 0 | N376: 0.02 | O376: CDM | P376: VALORIS MANAGEMENT | Q376: 8.8721931e+08 | R376: 1076.7 | S376: 0.016196 | T376: - | U376: -0.000882 | V376: 0.002439 | W376: 0.00893 | X376: 0.015104 | Y376: 0.01968 | Z376: - | AA376: - | AB376: -
A377: MA0000039638 | B377: 3963 | C377: FCP AFRICAPITAL RENDEMENT | D377: AFRICAPITAL MANAGEMENT | E377: FCP | F377: OMLT | G377: [2 6] | H377: MBI GLOBAL | I377: QUOTIDIENNE | J377: FGP | K377: CAPITALISANT | L377: 0.03 | M377: 0.03 | N377: 0.02 | O377: BCP | P377: AFRICAPITAL MANAGEMENT | Q377: 1.0566633e+09 | R377: 1031.08 | S377: -0.00659 | T377: - | U377: -0.001975 | V377: 0.001661 | W377: 0.006089 | X377: 0.00717 | Y377: -0.020165 | Z377: - | AA377: - | AB377: -
A378: MA0000039653 | B378: 3965 | C378: FCP ALPHA OBLIGATAIRE | D378: RED MED ASSET MANAGEMENT | E378: FCP | F378: OMLT | G378: ]1,1 10] | H378: MBI GLOBAL | I378: QUOTIDIENNE | J378: FNPP | K378: CAPITALISANT | L378: 0 | M378: 0 | N378: 0.02 | O378: BCP | P378: RED MED ASSET MANAGEMENT;RED MED SECURITIES | Q378: 1122154 | R378: 1122.15 | S378: -0.000365 | T378: - | U378: -0.001664 | V378: 0.001893 | W378: 0.005006 | X378: 0.003919 | Y378: -0.00612 | Z378: 0.066176 | AA378: 0.146338 | AB378: -
A379: MA0000039661 | B379: 3966 | C379: FCP EMERGENCE HARMONY FUND | D379: VALORIS MANAGEMENT | E379: FCP | F379: OMLT | G379: [1,1 10] | H379: MBI MT | I379: QUOTIDIENNE | J379: FNPP | K379: MIXTE | L379: 0 | M379: 0 | N379: 0.02 | O379: CIH BANK | P379: VALORIS MANAGEMENT | Q379: 37647354 | R379: 1356.71 | S379: 0.013643 | T379: - | U379: -0.001156 | V379: 0.001942 | W379: 0.0057 | X379: 0.013181 | Y379: 0.011195 | Z379: 0.101556 | AA379: 0.238541 | AB379: 0.282407
A380: MA0000039679 | B380: 3967 | C380: FCP OPTIMA EQUILIBRE | D380: ALPHAVEST ASSET MANAGEMENT | E380: FCP | F380: DIVERSIFIÉ | G380: - | H380: 60% MBI GLOBAL + 40% MASI | I380: QUOTIDIENNE | J380: FGP | K380: CAPITALISANT | L380: 0.03 | M380: 0.015 | N380: 0.02 | O380: BANQUE CENTRALE POPULAIRE | P380: ALPHAVEST ASSET MANAGEMENT | Q380: 2.6330604e+08 | R380: 983.17 | S380: -0.018694 | T380: - | U380: -0.005312 | V380: -0.003062 | W380: 0.015011 | X380: 0.040788 | Y380: -0.081459 | Z380: - | AA380: - | AB380: -
A381: MA0000039687 | B381: 3968 | C381: FCP OPTIMA MONETAIRE | D381: ALPHAVEST ASSET MANAGEMENT | E381: FCP | F381: MONÉTAIRE | G381: [0 0,5] | H381: MONIA | I381: QUOTIDIENNE | J381: FGP | K381: CAPITALISANT | L381: 0.03 | M381: 0.015 | N381: 0.02 | O381: BANQUE CENTRALE POPULAIRE | P381: ALPHAVEST ASSET MANAGEMENT | Q381: 9.4981296e+08 | R381: 1031.17 | S381: 0.017615 | T381: - | U381: 0.000126 | V381: 0.001681 | W381: 0.006039 | X381: 0.012967 | Y381: 0.025101 | Z381: - | AA381: - | AB381: -
A382: MA0000039695 | B382: 3969 | C382: FCP OPTIMA OBLIGATAIRE | D382: ALPHAVEST ASSET MANAGEMENT | E382: FCP | F382: OMLT | G382: [4 8] | H382: MBI GLOBAL | I382: QUOTIDIENNE | J382: FGP | K382: CAPITALISANT | L382: 0.03 | M382: 0.015 | N382: 0.02 | O382: BANQUE CENTRALE POPULAIRE | P382: ALPHAVEST ASSET MANAGEMENT | Q382: 5.1953612e+08 | R382: 1008.47 | S382: -0.007275 | T382: - | U382: -0.002374 | V382: -0.000337 | W382: 0.004352 | X382: 0.003513 | Y382: -0.011788 | Z382: - | AA382: - | AB382: -
A383: MA0000039703 | B383: 3970 | C383: FCP OPTIMA SOUVERAIN | D383: ALPHAVEST ASSET MANAGEMENT | E383: FCP | F383: OMLT | G383: [4 8] | H383: MBI GLOBAL | I383: QUOTIDIENNE | J383: FGP | K383: CAPITALISANT | L383: 0.03 | M383: 0.015 | N383: 0.02 | O383: BANK OF AFRICA | P383: ALPHAVEST ASSET MANAGEMENT | Q383: 2.8890635e+08 | R383: 1075.34 | S383: 0.059146 | T383: - | U383: -0.001347 | V383: 0.002302 | W383: 0.002573 | X383: -0.000372 | Y383: 0.058135 | Z383: - | AA383: - | AB383: -
A384: MA0000039711 | B384: 3971 | C384: FCP OPTIMA DYNAMIQUE | D384: ALPHAVEST ASSET MANAGEMENT | E384: FCP | F384: OCT | G384: [0,5 1,1] | H384: MBI CT | I384: QUOTIDIENNE | J384: FGP | K384: CAPITALISANT | L384: 0.03 | M384: 0.015 | N384: 0.02 | O384: BANK OF AFRICA | P384: ALPHAVEST ASSET MANAGEMENT | Q384: 9.294492e+08 | R384: 1033.46 | S384: 0.019372 | T384: - | U384: -9.7e-05 | V384: 0.00191 | W384: 0.006869 | X384: 0.014519 | Y384: 0.026602 | Z384: - | AA384: - | AB384: -
...

Sheet 28_08
A1: Tableau des performances hebdomadaires au 28-08-2026
A2: CODE ISIN | B2: Code Maroclear | C2: OPCVM | D2: Société de Gestion | E2: Nature juridique | F2: Classification | G2: Sensibilité | H2: Indice Bentchmark | I2: Périodicité VL | J2: Souscripteurs | K2: Affectation des résultats | L2: Commission de souscription | M2: Commission de rachat | N2: Frais de gestion | O2: Dépositaire | P2: Réseau placeur | Q2: AN | R2: VL | S2: YTD | T2: 1 jour | U2: 1 semaine | V2: 1 mois | W2: 3 mois | X2: 6 mois | Y2: 1 an | Z2: 2 ans | AA2: 3 ans | AB2: 5 ans
A3: MA0000030058 | B3: 3005 | C3: BMCI COSMOS | D3: CIH CAPITAL MANAGEMENT | E3: SICAV | F3: ACTIONS | G3: - | H3: MASI | I3: HEBDOMADAIRE | J3: FGP | K3: CAPITALISANT | L3: 0.02 | M3: 0.0075 | N3: 0.02 | O3: BMCI | P3: CIH CAPITAL MANAGEMENT | Q3: 30059592 | R3: 448.19 | S3: 0.027841 | T3: - | U3: -0.009875 | V3: 0.062137 | W3: 0.025395 | X3: 0.0592 | Y3: -0.077912 | Z3: 0.369648 | AA3: 0.590849 | AB3: 0.523316
A4: MA0000030066 | B4: 3006 | C4: BMCI EPARGNE OBLIGATIONS | D4: CIH CAPITAL MANAGEMENT | E4: SICAV | F4: OMLT | G4: [3 7[ | H4: MBI MLT | I4: HEBDOMADAIRE | J4: FGP | K4: CAPITALISANT | L4: 0.005 | M4: 0.0025 | N4: 0.0093 | O4: BMCI | P4: CIH CAPITAL MANAGEMENT | Q4: 1.1630302e+08 | R4: 274.67 | S4: -0.007301 | T4: - | U4: 0.000692 | V4: 0.004462 | W4: 0.001166 | X4: -0.005827 | Y4: -0.010519 | Z4: 0.067758 | AA4: 0.160708 | AB4: 0.092953
A5: MA0000030132 | B5: 3013 | C5: BMCI TRESORERIE | D5: CIH CAPITAL MANAGEMENT | E5: SICAV | F5: MONÉTAIRE | G5: [0 0,5[ | H5: TMJ(jj) | I5: QUOTIDIENNE | J5: FGP | K5: CAPITALISANT | L5: 0.0125 | M5: 0.005 | N5: 0.0195 | O5: BMCI | P5: CIH CAPITAL MANAGEMENT | Q5: 1.6672222e+08 | R5: 123497.94 | S5: 0.01033 | T5: - | U5: 0.000154 | V5: 0.001165 | W5: 0.003663 | X5: 0.007657 | Y5: 0.015108 | Z5: 0.033071 | AA5: 0.056927 | AB5: 0.083851
A6: MA0000030215 | B6: 3021 | C6: CDG IZDIHAR | D6: CDG CAPITAL GESTION | E6: SICAV | F6: DIVERSIFIÉ | G6: - | H6: 77% MBI GLOBAL + 23% CFG 25 FLOTTANT | I6: HEBDOMADAIRE | J6: FGP | K6: CAPITALISANT | L6: 0.003 | M6: 0.0025 | N6: 0.02 | O6: CDG CAPITAL | P6: CDG CAPITAL GESTION | Q6: 1.3111562e+09 | R6: 4148.32 | S6: -0.03392 | T6: - | U6: -0.00333 | V6: 0.029822 | W6: 0.006862 | X6: -0.01927 | Y6: -0.094073 | Z6: 0.130588 | AA6: 0.273811 | AB6: 0.182268
A7: MA0000030280 | B7: 3028 | C7: CDG TAWFIR | D7: CDG CAPITAL GESTION | E7: SICAV | F7: OMLT | G7: [3 7[ | H7: MBI GLOBAL | I7: QUOTIDIENNE | J7: FGP | K7: CAPITALISANT | L7: 0.005 | M7: 0 | N7: 0.02 | O7: CDG CAPITAL | P7: CDG CAPITAL GESTION | Q7: 1.7862818e+09 | R7: 3480.13 | S7: 0.000725 | T7: - | U7: 0.001059 | V7: 0.007825 | W7: 0.004979 | X7: 0.000106 | Y7: -0.005001 | Z7: 0.080306 | AA7: 0.171438 | AB7: 0.10606
A8: MA0000030298 | B8: 3029 | C8: SICAV OBLIGATIONS PÉRENNITÉ | D8: CDG CAPITAL GESTION | E8: SICAV | F8: OMLT | G8: [1,1 16[ | H8: MBI MT | I8: QUOTIDIENNE | J8: FNPP | K8: CAPITALISANT | L8: 0.03 | M8: 0.015 | N8: 0.02 | O8: CDG CAPITAL | P8: CDG CAPITAL GESTION | Q8: 7.6482153e+09 | R8: 3303.39 | S8: -0.003731 | T8: - | U8: 0.001382 | V8: 0.003573 | W8: 0.005574 | X8: 0.006024 | Y8: -0.002211 | Z8: 0.051881 | AA8: 0.106567 | AB8: 0.120351
A9: MA0000030306 | B9: 3030 | C9: CDG TRESORERIE | D9: CDG CAPITAL GESTION | E9: SICAV | F9: MONÉTAIRE | G9: [0 0,5[ | H9: 50% MBI CT + 50% TMP | I9: QUOTIDIENNE | J9: FGP | K9: CAPITALISANT | L9: 0 | M9: 0 | N9: 0.02 | O9: CDG CAPITAL | P9: CDG CAPITAL GESTION | Q9: 4.9557964e+09 | R9: 2279.19 | S9: 0.018387 | T9: - | U9: 0.000272 | V9: 0.002362 | W9: 0.006616 | X9: 0.01405 | Y9: 0.026792 | Z9: 0.056952 | AA9: 0.093987 | AB9: 0.138292
A10: MA0000030363 | B10: 3036 | C10: BMCI EPARGNE CROISSANCE | D10: CIH CAPITAL MANAGEMENT | E10: SICAV | F10: DIVERSIFIÉ | G10: - | H10: 60% MASI + 40% MBI MT | I10: HEBDOMADAIRE | J10: FGP | K10: CAPITALISANT | L10: 0.0125 | M10: 0.005 | N10: 0.0195 | O10: BMCI | P10: CIH CAPITAL MANAGEMENT | Q10: 2.6922323e+08 | R10: 165.44 | S10: -0.016058 | T10: - | U10: -0.002292 | V10: 0.020353 | W10: 0.009334 | X10: -0.001268 | Y10: -0.046455 | Z10: 0.137123 | AA10: 0.269198 | AB10: 0.274282
A11: MA0000030371 | B11: 3037 | C11: CIMR TRESO PLUS | D11: SAHAM CAPITAL GESTION | E11: SICAV | F11: OCT | G11: ]0,5 1,1] | H11: MBI CT | I11: QUOTIDIENNE | J11: FNPP | K11: CAPITALISANT | L11: 0 | M11: 0 | N11: 0.02 | O11: SAHAM BANK | P11: SAHAM BANK | Q11: 1.3708945e+08 | R11: 403204.27 | S11: 0.016246 | T11: - | U11: 0.000278 | V11: 0.001997 | W11: 0.005877 | X11: 0.012101 | Y11: 0.021817 | Z11: 0.051166 | AA11: 0.089102 | AB11: 0.132216
A12: MA0000030397 | B12: 3039 | C12: CDG BARID | D12: CDG CAPITAL GESTION | E12: SICAV | F12: OMLT | G12: [3 7[ | H12: - | I12: HEBDOMADAIRE | J12: FNPP | K12: CAPITALISANT | L12: 0.005 | M12: 0 | N12: 0.02 | O12: CDG | P12: CDG CAPITAL GESTION | Q12: 3404328173 | R12: 3736.34 | S12: -0.005025 | T12: - | U12: 0.000753 | V12: 0.007608 | W12: 0.004611 | X12: -0.002587 | Y12: -0.015569 | Z12: 0.080082 | AA12: 0.185601 | AB12: 0.077379
A13: MA0000030405 | B13: 3040 | C13: SICAV MAROC CROISSANCE | D13: MAROGEST | E13: SICAV | F13: DIVERSIFIÉ | G13: - | H13: - | I13: HEBDOMADAIRE | J13: FGP | K13: CAPITALISANT | L13: 0.02 | M13: 0.005 | N13: 0.02 | O13: CIH BANK | P13: MAROGEST | Q13: 3.0593642e+08 | R13: 5213.64 | S13: -0.038709 | T13: - | U13: -0.003492 | V13: 0.027268 | W13: 0.019783 | X13: -0.015609 | Y13: -0.099284 | Z13: 0.149024 | AA13: 0.351234 | AB13: 0.33887
A14: MA0000030413 | B14: 3041 | C14: BMCI CASH | D14: CIH CAPITAL MANAGEMENT | E14: SICAV | F14: OCT | G14: [0,6 1,1[ | H14: MBI CT | I14: QUOTIDIENNE | J14: FGP | K14: CAPITALISANT | L14: 0 | M14: 0 | N14: 0.0067 | O14: BMCI | P14: CIH CAPITAL MANAGEMENT | Q14: 31370990 | R14: 196.53 | S14: 0.02136 | T14: - | U14: 0.000407 | V14: 0.004857 | W14: 0.007743 | X14: 0.018396 | Y14: 0.032087 | Z14: 0.063301 | AA14: 0.094021 | AB14: 0.116077
... A57: MA0000035453 | B57: 3545 | C57: SCR INTEGRALE | D57: CDG CAPITAL GESTION | E57: FCP | F57: ACTIONS | G57: - | H57: CFG 25 FLOTTANT | I57: HEBDOMADAIRE | J57: FNPP | K57: DISTRIBUANT | L57: 0.03 | M57: 0.015 | N57: 0.02 | O57: CDG CAPITAL | P57: CDG CAPITAL GESTION | Q57: 2.2849113e+08 | R57: 6636.97 | S57: -0.046074 | T57: - | U57: -0.007946 | V57: 0.057585 | W57: 0.025991 | X57: 0.011195 | Y57: -0.136093 | Z57: 0.271175 | AA57: 0.491041 | AB57: 0.414498
A58: MA0000035461 | B58: 3546 | C58: SCR OBLIGATIONS | D58: CDG CAPITAL GESTION | E58: FCP | F58: OMLT | G58: ]1,1 9] | H58: MBI GLOBAL | I58: HEBDOMADAIRE | J58: FNPP | K58: CAPITALISANT | L58: 0 | M58: 0 | N58: - | O58: CDG CAPITAL | P58: CDG CAPITAL GESTION | Q58: 2.4233819e+09 | R58: 2734.15 | S58: -0.000314 | T58: - | U58: 0.001021 | V58: 0.004896 | W58: 0.004873 | X58: -0.000215 | Y58: -0.005781 | Z58: 0.081221 | AA58: 0.184158 | AB58: 0.081585
A59: MA0000035487 | B59: 3548 | C59: CDG ACTIONS | D59: CDG CAPITAL GESTION | E59: FCP | F59: ACTIONS | G59: - | H59: CFG 25 FLOTTANT | I59: HEBDOMADAIRE | J59: FNPP | K59: CAPITALISANT | L59: 0.03 | M59: 0.015 | N59: 0.02 | O59: CDG CAPITAL | P59: CDG CAPITAL GESTION | Q59: 1.7754131e+09 | R59: 7699.36 | S59: -0.023814 | T59: - | U59: -0.009618 | V59: 0.064281 | W59: 0.032857 | X59: 0.030486 | Y59: -0.122024 | Z59: 0.237715 | AA59: 0.409457 | AB59: 0.3516
A60: MA0000035495 | B60: 3549 | C60: AL IKRAM | D60: CIH CAPITAL MANAGEMENT | E60: FCP | F60: DIVERSIFIÉ | G60: - | H60: 60% MASI + 40% MBI MT | I60: HEBDOMADAIRE | J60: FNPP | K60: CAPITALISANT | L60: 0.03 | M60: 0.015 | N60: 0.0075 | O60: BMCI | P60: CIH CAPITAL MANAGEMENT | Q60: 35009545 | R60: 36852.15 | S60: -0.000594 | T60: - | U60: 6.7e-05 | V60: 0.014647 | W60: 0.010182 | X60: 0.012357 | Y60: -0.025537 | Z60: 0.123481 | AA60: 0.234668 | AB60: 0.255275
A61: MA0000035503 | B61: 3550 | C61: CASACTIONS | D61: CIH CAPITAL MANAGEMENT | E61: FCP | F61: DIVERSIFIÉ | G61: - | H61: 80% MBI GLOBAL + 20% MASI | I61: HEBDOMADAIRE | J61: FNPP | K61: DISTRIBUANT | L61: 0.03 | M61: 0.015 | N61: 0.02 | O61: BMCI | P61: CIH CAPITAL MANAGEMENT | Q61: 2472456.7 | R61: 176604.05 | S61: 0.000654 | T61: - | U61: 0.000529 | V61: 0.00282 | W61: 0.002963 | X61: 0.002556 | Y61: -0.00143 | Z61: 0.010906 | AA61: 0.032505 | AB61: 0.032218
A62: MA0000035511 | B62: 3551 | C62: AVENIR ACTIONS | D62: CIH CAPITAL MANAGEMENT | E62: FCP | F62: DIVERSIFIÉ | G62: - | H62: 80% MBI GLOBAL + 20% MASI | I62: HEBDOMADAIRE | J62: FNPP | K62: DISTRIBUANT | L62: 0.03 | M62: 0.015 | N62: 0.02 | O62: BMCI | P62: CIH CAPITAL MANAGEMENT | Q62: 2.2552901e+08 | R62: 249478.99 | S62: -0.001505 | T62: - | U62: -0.003695 | V62: 0.02463 | W62: 0.011255 | X62: 0.012772 | Y62: -0.047082 | Z62: 0.13284 | AA62: 0.251502 | AB62: 0.244117
A63: MA0000035529 | B63: 3552 | C63: AXA HORIZON | D63: CIH CAPITAL MANAGEMENT | E63: FCP | F63: DIVERSIFIÉ | G63: - | H63: CFG 25 FLOTTANT | I63: HEBDOMADAIRE | J63: FNPP | K63: MIXTE | L63: 0.03 | M63: 0.015 | N63: 0 | O63: BMCI | P63: CIH CAPITAL MANAGEMENT | Q63: 8.2312574e+08 | R63: 181185.5 | S63: 0.008685 | T63: - | U63: -0.001721 | V63: 0.02342 | W63: 0.01131 | X63: 0.015469 | Y63: -0.025224 | Z63: 0.189874 | AA63: 0.333621 | AB63: 0.29179
A64: MA0000035537 | B64: 3553 | C64: CIMR THARWA | D64: CIH CAPITAL MANAGEMENT | E64: FCP | F64: ACTIONS | G64: - | H64: MASI RN | I64: HEBDOMADAIRE | J64: FNPP | K64: CAPITALISANT | L64: 0 | M64: 0 | N64: 0.02 | O64: BMCI | P64: CIH CAPITAL MANAGEMENT | Q64: 1.1534852e+09 | R64: 519120.27 | S64: 0.029033 | T64: - | U64: -0.01047 | V64: 0.064866 | W64: 0.023985 | X64: 0.060736 | Y64: -0.065596 | Z64: 0.388493 | AA64: 0.644857 | AB64: 0.646837
A65: MA0000035545 | B65: 3554 | C65: BMCI INVEST | D65: CIH CAPITAL MANAGEMENT | E65: FCP | F65: DIVERSIFIÉ | G65: - | H65: 60% MASI + 40% MBI MT | I65: HEBDOMADAIRE | J65: FNPP | K65: CAPITALISANT | L65: 0.03 | M65: 0.015 | N65: 0.006 | O65: BMCI | P65: CIH CAPITAL MANAGEMENT | Q65: 837408.87 | R65: 239.26 | S65: 0.00243 | T65: - | U65: -0.00246 | V65: 0.008855 | W65: -0.011649 | X65: -0.002917 | Y65: -0.014296 | Z65: 0.041937 | AA65: 0.065556 | AB65: 0.059282
A66: MA0000035552 | B66: 3555 | C66: AXA AVENIR | D66: CDG CAPITAL GESTION | E66: FCP | F66: DIVERSIFIÉ | G66: - | H66: 80% MBI GLOBAL + 25% MASI RN | I66: HEBDOMADAIRE | J66: FNPP | K66: MIXTE | L66: 0.03 | M66: 0.015 | N66: 0.02 | O66: CDG CAPITAL | P66: CDG CAPITAL GESTION | Q66: 7.8159914e+08 | R66: 3654.27 | S66: -0.017477 | T66: - | U66: -0.001626 | V66: 0.022857 | W66: 0.012302 | X66: 0.000803 | Y66: -0.060437 | Z66: 0.142865 | AA66: 0.253722 | AB66: 0.197511
A67: MA0000035594 | B67: 3559 | C67: HORIZON BALANCED FUND | D67: SAHAM CAPITAL GESTION | E67: FCP | F67: DIVERSIFIÉ | G67: - | H67: 50% MBI GLOBAL + 50% MASI | I67: QUOTIDIENNE | J67: FGP | K67: DISTRIBUANT | L67: 0.02 | M67: 0.015 | N67: 0.02 | O67: SAHAM BANK | P67: SAHAM BANK | Q67: 1288282.7 | R67: 107356.89 | S67: -0.005531 | T67: - | U67: -0.004107 | V67: 0.027485 | W67: -0.024732 | X67: 0.002693 | Y67: -0.055787 | Z67: 0.178758 | AA67: 0.356765 | AB67: 0.373956
A68: MA0000035651 | B68: 3565 | C68: ATLAS PREMIUM | D68: ATLAS CAPITAL MANAGEMENT | E68: FCP | F68: ACTIONS | G68: - | H68: MASI | I68: HEBDOMADAIRE | J68: FGP | K68: CAPITALISANT | L68: 0.03 | M68: 0.015 | N68: 0.015 | O68: CIH BANK | P68: ATLAS CAPITAL MANAGEMENT | Q68: 1043235 | R68: 760.92 | S68: 0.041671 | T68: - | U68: -0.009103 | V68: 0.061285 | W68: 0.029313 | X68: 0.071673 | Y68: -0.058384 | Z68: 0.425985 | AA68: 0.69022 | AB68: 0.633471
A69: MA0000035677 | B69: 3567 | C69: CDG HORIZONS | D69: CDG CAPITAL GESTION | E69: FCP | F69: OMLT | G69: ]1,1 5,1] | H69: 50% MBI MLT + 50% MBI MT | I69: QUOTIDIENNE | J69: FGP | K69: CAPITALISANT | L69: 0.03 | M69: 0.015 | N69: 0.02 | O69: CDG CAPITAL | P69: CDG CAPITAL GESTION | Q69: 2.3093372e+08 | R69: 2259.73 | S69: 0.008245 | T69: - | U69: 0.001187 | V69: 0.004302 | W69: 0.005621 | X69: 0.006785 | Y69: 0.014501 | Z69: 0.082588 | AA69: 0.143877 | AB69: 0.132118
A70: MA0000035685 | B70: 3568 | C70: AVENIR OBLIGATION | D70: CFG GESTION | E70: FCP | F70: OMLT | G70: [4 8[ | H70: CFG BONDS MT | I70: HEBDOMADAIRE | J70: FNPP | K70: MIXTE | L70: 0 | M70: 0 | N70: 0.01 | O70: ATTIJARIWAFA BANK | P70: CFG GESTION | Q70: 1.4030124e+09 | R70: 26125.89 | S70: -0.00212 | T70: - | U70: 0.000587 | V70: 0.002894 | W70: 0.001978 | X70: -0.003436 | Y70: -0.011381 | Z70: 0.076156 | AA70: 0.181095 | AB70: 0.087739
... A118: MA0000036329 | B118: 3632 | C118: FCP CAPITAL TERME | D118: BMCE CAPITAL GESTION | E118: FCP | F118: DIVERSIFIÉ | G118: - | H118: 80% MBI GLOBAL + 20% MASI | I118: QUOTIDIENNE | J118: FGP | K118: CAPITALISANT | L118: 0.02 | M118: 0.02 | N118: 0.02 | O118: BANK OF AFRICA | P118: BMCE CAPITAL GESTION | Q118: 81163921 | R118: 248.49 | S118: 0.023519 | T118: - | U118: -0.002249 | V118: 0.015779 | W118: 0.024321 | X118: 0.030352 | Y118: -0.005244 | Z118: 0.171183 | AA118: 0.29943 | AB118: 0.253038
A119: MA0000036345 | B119: 3634 | C119: CFG INSTIBONDS | D119: CFG GESTION | E119: FCP | F119: OMLT | G119: ]1,5 5,5] | H119: MBI GLOBAL | I119: QUOTIDIENNE | J119: FGP | K119: CAPITALISANT | L119: 0.03 | M119: 0.015 | N119: 0.02 | O119: CFG BANK | P119: CFG GESTION; CFG BANK | Q119: 5.5306098e+08 | R119: 34.19 | S119: 0.002933 | T119: - | U119: 0.001171 | V119: 0.004702 | W119: 0.004112 | X119: -0.00146 | Y119: -0.779916 | Z119: -0.767304 | AA119: -0.754823 | AB119: -
A120: MA0000036352 | B120: 3635 | C120: FCP CAM TRESO PLUS | D120: MAROGEST | E120: FCP | F120: OCT | G120: ]0,5 1,1] | H120: 85% MBI CT + 15 % MBI MT | I120: QUOTIDIENNE | J120: FGP | K120: CAPITALISANT | L120: 0.03 | M120: 0.015 | N120: 0.02 | O120: CIH BANK | P120: CIH | Q120: 8.8574952e+08 | R120: 174.82 | S120: 0.019061 | T120: - | U120: 0.000458 | V120: 0.002466 | W120: 0.00668 | X120: 0.014155 | Y120: 0.026481 | Z120: 0.062413 | AA120: 0.105476 | AB120: 0.152102
A121: MA0000036378 | B121: 3637 | C121: AVENIR CROISSANCE | D121: CFG GESTION | E121: FCP | F121: ACTIONS | G121: - | H121: CFG 25 FLOTTANT | I121: HEBDOMADAIRE | J121: FNPP | K121: MIXTE | L121: 0.03 | M121: 0.015 | N121: 0.02 | O121: ATTIJARIWAFA BANK | P121: CFG GESTION | Q121: 1301988.9 | R121: 36166.36 | S121: -0.035743 | T121: - | U121: -0.004215 | V121: 0.034883 | W121: 0.018223 | X121: -0.004291 | Y121: -0.117829 | Z121: 0.207055 | AA121: 0.451031 | AB121: 0.437278
A122: MA0000036394 | B122: 3639 | C122: FCP CAPITAL TAALIM | D122: BMCE CAPITAL GESTION | E122: FCP | F122: OMLT | G122: [4 8[ | H122: 95% MBI MLT + 5% MASI | I122: HEBDOMADAIRE | J122: FNPP | K122: CAPITALISANT | L122: 0.03 | M122: 0.015 | N122: 0.02 | O122: BANK OF AFRICA | P122: BMCE CAPITAL GESTION | Q122: 3.5547497e+09 | R122: 2374.5 | S122: -0.000282 | T122: - | U122: 0.000362 | V122: 0.008404 | W122: 0.005428 | X122: 0.001121 | Y122: -0.014031 | Z122: 0.104927 | AA122: 0.225915 | AB122: 0.16963
A123: MA0000036402 | B123: 3640 | C123: UPLINE EQUILIBRE | D123: UPLINE CAPITAL MANAGEMENT | E123: FCP | F123: DIVERSIFIÉ | G123: - | H123: 75% MBI GLOBAL + 25% MASI 20 | I123: QUOTIDIENNE | J123: FNPP | K123: MIXTE | L123: 0 | M123: 0 | N123: 0.02 | O123: BCP | P123: UPLINE CAPITAL MANAGEMENT | Q123: 5.7104715e+08 | R123: 125.05 | S123: 0.009216 | T123: - | U123: -0.004141 | V123: 0.028626 | W123: 0.010832 | X123: 0.026504 | Y123: -0.044665 | Z123: 0.206163 | AA123: -0.046397 | AB123: -0.082875
A124: MA0000036436 | B124: 3643 | C124: EMERGENCE CAPITAL | D124: VALORIS MANAGEMENT | E124: FCP | F124: OMLT | G124: [1,1 5,1[ | H124: MBI GLOBAL | I124: HEBDOMADAIRE | J124: FGP | K124: CAPITALISANT | L124: 0.03 | M124: 0.015 | N124: 0.005 | O124: BANK OF AFRICA | P124: VALORIS MANAGEMENT | Q124: 2.7355827e+08 | R124: 1801.15 | S124: 0.006122 | T124: - | U124: 0.000767 | V124: 0.00313 | W124: 0.005173 | X124: 0.004461 | Y124: 0.006032 | Z124: 0.063315 | AA124: 0.129722 | AB124: 0.11156
A125: MA0000036444 | B125: 3644 | C125: AL IJTIMAI PATRIMOINE | D125: VALORIS MANAGEMENT | E125: FCP | F125: OMLT | G125: [1,1 7,1[ | H125: MBI GLOBAL | I125: HEBDOMADAIRE | J125: FNPP | K125: CAPITALISANT | L125: 0.03 | M125: 0.015 | N125: 0.008 | O125: CDG | P125: VALORIS MANAGEMENT | Q125: 5.0402563e+09 | R125: 213887.39 | S125: 0.002621 | T125: - | U125: 0.000429 | V125: 0.006832 | W125: 0.005676 | X125: 0.002966 | Y125: -0.007824 | Z125: 0.097847 | AA125: 0.214907 | AB125: 0.136954
A126: MA0000036485 | B126: 3648 | C126: CAT ACTIONS | D126: CIH CAPITAL MANAGEMENT | E126: FCP | F126: ACTIONS | G126: - | H126: MASI RN | I126: HEBDOMADAIRE | J126: FNPP | K126: DISTRIBUANT | L126: 0 | M126: 0 | N126: 0.02 | O126: BMCI | P126: CIH CAPITAL MANAGEMENT | Q126: 2.907318e+08 | R126: 508272.37 | S126: 0.015476 | T126: - | U126: -0.010232 | V126: 0.062833 | W126: 0.024885 | X126: 0.044927 | Y126: -0.081622 | Z126: 0.357726 | AA126: 0.565456 | AB126: 0.549467
A127: MA0000036493 | B127: 3649 | C127: FCP CAPITAL MAGHREB | D127: BMCE CAPITAL GESTION | E127: FCP | F127: ACTIONS | G127: - | H127: MASI | I127: QUOTIDIENNE | J127: FGP | K127: CAPITALISANT | L127: 0.02 | M127: 0.02 | N127: 0.02 | O127: BANK OF AFRICA | P127: BMCE CAPITAL GESTION | Q127: 1.5134673e+09 | R127: 1807.1 | S127: 0.01627 | T127: - | U127: -0.010041 | V127: 0.063713 | W127: 0.020937 | X127: 0.051783 | Y127: -0.092014 | Z127: 0.392455 | AA127: 0.714825 | AB127: 0.633921
A128: MA0000036501 | B128: 3650 | C128: FCP CAPITAL MULTI-GESTION | D128: BMCE CAPITAL GESTION | E128: FCP | F128: DIVERSIFIÉ | G128: - | H128: 80% MBI GLOBAL + 20% MASI | I128: QUOTIDIENNE | J128: FGP | K128: CAPITALISANT | L128: 0.02 | M128: 0.02 | N128: 0.02 | O128: BANK OF AFRICA | P128: BMCE CAPITAL GESTION | Q128: 1.7541006e+09 | R128: 546.04 | S128: -0.013175 | T128: - | U128: -0.002466 | V128: 0.022375 | W128: 0.006395 | X128: 0.002884 | Y128: -0.058194 | Z128: 0.14053 | AA128: 0.268268 | AB128: 0.173296
A129: MA0000036519 | B129: 3651 | C129: FCP AL IJTIMAI SECURITE | D129: BMCE CAPITAL GESTION | E129: FCP | F129: OMLT | G129: [1,1 7[ | H129: MBI GLOBAL | I129: HEBDOMADAIRE | J129: FNPP | K129: CAPITALISANT | L129: 0.03 | M129: 0.015 | N129: 0.02 | O129: BANK OF AFRICA | P129: BMCE CAPITAL GESTION | Q129: 3.0226897e+09 | R129: 225422.45 | S129: -0.001761 | T129: - | U129: 0.000367 | V129: 0.007496 | W129: 0.003587 | X129: -0.000614 | Y129: -0.015649 | Z129: 0.093923 | AA129: 0.209737 | AB129: 0.151964
A130: MA0000036527 | B130: 3652 | C130: AL IJTIMAI INMAA | D130: WAFA GESTION | E130: FCP | F130: OMLT | G130: ]1,1 7] | H130: MBI GLOBAL | I130: HEBDOMADAIRE | J130: FNPP | K130: CAPITALISANT | L130: 0.03 | M130: 0.03 | N130: 0.02 | O130: ATTIJARIWAFA BANK | P130: WAFA GESTION | Q130: 5241888805 | R130: 218767.53 | S130: 0.007465 | T130: - | U130: 0.00047 | V130: 0.007082 | W130: 0.006109 | X130: 0.007424 | Y130: 0.000648 | Z130: 0.107416 | AA130: 0.229136 | AB130: 0.148677
A131: MA0000036535 | B131: 3653 | C131: AL IJTIMAI SOLIDARITE | D131: CFG GESTION | E131: FCP | F131: OMLT | G131: [1,1 7[ | H131: MBI GLOBAL | I131: HEBDOMADAIRE | J131: FNPP | K131: CAPITALISANT | L131: 0 | M131: 0 | N131: 0.02 | O131: CDG | P131: CFG GESTION | Q131: 3.8542648e+09 | R131: 219916.97 | S131: -0.002093 | T131: - | U131: 0.000399 | V131: 0.006889 | W131: 0.00394 | X131: -0.000466 | Y131: -0.012597 | Z131: 0.094768 | AA131: 0.21173 | AB131: 0.129891
... A324: MA0000039034 | B324: 3903 | C324: FH2 ACTIONS | D324: BMCE CAPITAL GESTION | E324: FCP | F324: ACTIONS | G324: - | H324: MASI | I324: QUOTIDIENNE | J324: FNPP | K324: MIXTE | L324: 0 | M324: 0 | N324: 0.02 | O324: BANK OF AFRICA | P324: BMCE CAPITAL GESTION | Q324: 1.4506842e+09 | R324: 1817.2 | S324: 0.023446 | T324: - | U324: -0.009873 | V324: 0.063418 | W324: 0.021674 | X324: 0.055505 | Y324: -0.082625 | Z324: 0.419277 | AA324: 0.754732 | AB324: 0.708328
A325: MA0000039059 | B325: 3905 | C325: WG VALEURS | D325: WAFA GESTION | E325: FCP | F325: ACTIONS | G325: - | H325: MASI RB | I325: QUOTIDIENNE | J325: FGP | K325: MIXTE | L325: 0 | M325: 0 | N325: 0.01 | O325: ATTIJARIWAFA BANK | P325: WAFA GESTION | Q325: 215989602 | R325: 1623.19 | S325: 0.113765 | T325: - | U325: -0.01063 | V325: 0.062276 | W325: 0.033905 | X325: 0.114851 | Y325: 0.04042 | Z325: 0.48177 | AA325: 0.70135 | AB325: -
A326: MA0000039067 | B326: 3906 | C326: WG TAYSSIR | D326: WAFA GESTION | E326: FCP | F326: ACTIONS | G326: - | H326: MASI RB | I326: HEBDOMADAIRE | J326: FGP | K326: CAPITALISANT | L326: 0 | M326: 0 | N326: 0.01 | O326: ATTIJARIWAFA BANK | P326: WAFA GESTION | Q326: 2.1002557e+08 | R326: 1519.96 | S326: 0.100392 | T326: - | U326: -0.011125 | V326: 0.060188 | W326: 0.018542 | X326: 0.105675 | Y326: -0.005106 | Z326: 0.466761 | AA326: 0.683196 | AB326: -
A327: MA0000039075 | B327: 3907 | C327: FCP OBLIG OPPORTUNITES | D327: IRG ASSET MANAGEMENT | E327: FCP | F327: OMLT | G327: ]1,1 5,1] | H327: MBI MT | I327: QUOTIDIENNE | J327: FGP | K327: CAPITALISANT | L327: 0.03 | M327: 0.015 | N327: 0.02 | O327: CDG | P327: IRG ASSET MANAGEMENT | Q327: 4.4431695e+08 | R327: 104.87 | S327: -0.001618 | T327: - | U327: 0 | V327: 0.007203 | W327: 0.004117 | X327: 0.003445 | Y327: -0.009165 | Z327: 0.050486 | AA327: 0.107977 | AB327: -
A328: MA0000039083 | B328: 3908 | C328: FCP OBLIG LONG TERM | D328: IRG ASSET MANAGEMENT | E328: FCP | F328: OMLT | G328: ]4 8] | H328: 80% MBI MLT+20% MBI LT | I328: HEBDOMADAIRE | J328: FGP | K328: CAPITALISANT | L328: 0.03 | M328: 0.015 | N328: 0.02 | O328: ATTIJARIWAFA BANK | P328: IRG ASSET MANAGEMENT | Q328: 1.2844205e+08 | R328: 113.72 | S328: -0.011732 | T328: - | U328: 0.000616 | V328: 0.001938 | W328: -0.002281 | X328: -0.008717 | Y328: -0.017877 | Z328: 0.053744 | AA328: 0.317271 | AB328: -
A329: MA0000039091 | B329: 3909 | C329: CAPITAL TRUST EQUITY | D329: CAPITAL TRUST GESTION | E329: FCP | F329: ACTIONS | G329: - | H329: MASI | I329: QUOTIDIENNE | J329: FGP | K329: CAPITALISANT | L329: 0.03 | M329: 0.015 | N329: 0.02 | O329: BCP | P329: CAPITAL TRUST GESTION | Q329: 9.2297906e+08 | R329: 1467.89 | S329: -0.026553 | T329: - | U329: -0.009768 | V329: 0.059 | W329: 0.014893 | X329: 0.012526 | Y329: -0.138163 | Z329: 0.281206 | AA329: 0.582528 | AB329: -
A330: MA0000039109 | B330: 3910 | C330: UPLINE PROTECTION DYNAMIQUE | D330: UPLINE CAPITAL MANAGEMENT | E330: FCP | F330: DIVERSIFIÉ | G330: - | H330: - | I330: HEBDOMADAIRE | J330: FGP | K330: CAPITALISANT | L330: 0.002 | M330: 0.002 | N330: 0.02 | O330: BCP | P330: BANQUE POPULAIRE | Q330: 5.7009152e+08 | R330: 1176.33 | S330: 0.008116 | T330: - | U330: -0.003212 | V330: 0.017675 | W330: 0.005505 | X330: 0.013099 | Y330: -0.014857 | Z330: 0.114635 | AA330: 0.180568 | AB330: -
A331: MA0000039117 | B331: 3911 | C331: CAM OBLIBANQUES | D331: MAROGEST | E331: FCP | F331: OCT | G331: ]0,5 1,1] | H331: 85% MBI CT + 15% MBI MT | I331: QUOTIDIENNE | J331: FGP | K331: CAPITALISANT | L331: 0.03 | M331: 0.015 | N331: 0.02 | O331: CIH BANK | P331: CAM; MSIN; CIH; MAROGEST | Q331: 2.1230924e+09 | R331: 1147.55 | S331: 0.018894 | T331: - | U331: 0.00048 | V331: 0.00256 | W331: 0.006455 | X331: 0.014113 | Y331: 0.027516 | Z331: 0.064804 | AA331: 0.108873 | AB331: -
A332: MA0000039125 | B332: 3912 | C332: CAM OBLIRENDEMENT | D332: MAROGEST | E332: FCP | F332: OMLT | G332: ]1,1 5,1] | H332: 100% MBI MT | I332: QUOTIDIENNE | J332: FGP | K332: CAPITALISANT | L332: 0.03 | M332: 0.015 | N332: 0.02 | O332: CIH BANK | P332: CAM; MSIN; CIH; MAROGEST | Q332: 4.0242227e+08 | R332: 1154.32 | S332: -0.002833 | T332: - | U332: 0.001067 | V332: 0.005698 | W332: 0.004543 | X332: -0.001885 | Y332: -0.006626 | Z332: 0.07225 | AA332: 0.140385 | AB332: -
A333: MA0000039133 | B333: 3913 | C333: CKG ISR SELECTION | D333: CDG CAPITAL GESTION | E333: FCP | F333: ACTIONS | G333: - | H333: ESG 10 | I333: HEBDOMADAIRE | J333: FGP | K333: CAPITALISANT | L333: 0.03 | M333: 0.015 | N333: 0.02 | O333: CDG CAPITAL | P333: CDG CAPITAL GESTION | Q333: 2.5004559e+08 | R333: 962.54 | S333: 0.018044 | T333: - | U333: -0.011015 | V333: 0.055972 | W333: 0.022369 | X333: 0.05298 | Y333: -0.085742 | Z333: 0.034756 | AA333: 0.111247 | AB333: -
A334: MA0000039141 | B334: 3914 | C334: AD SELECT BANQUES | D334: AD CAPITAL ASSET MANAGEMENT | E334: FCP | F334: OCT | G334: ]0,5 1,1] | H334: MBI CT | I334: QUOTIDIENNE | J334: FGP | K334: CAPITALISANT | L334: 0.03 | M334: 0.03 | N334: 0.02 | O334: CFG BANK | P334: AD CAPITAL ASSET MANAGEMENT; AD CAPITAL GROUP | Q334: 2.1244148e+09 | R334: 1153.58 | S334: 0.019956 | T334: - | U334: 0.000477 | V334: 0.002677 | W334: 0.007397 | X334: 0.015207 | Y334: 0.028742 | Z334: 0.068545 | AA334: 0.115389 | AB334: -
A335: MA0000039158 | B335: 3915 | C335: AD COMPACT OBLIGATAIRE | D335: AD CAPITAL ASSET MANAGEMENT | E335: FCP | F335: OMLT | G335: [3,5 7,5[ | H335: MBI GLOBAL | I335: HEBDOMADAIRE | J335: FGP | K335: CAPITALISANT | L335: 0.03 | M335: 0.03 | N335: 0.02 | O335: CFG BANK | P335: AD CAPITAL ASSET MANAGEMENT; AD CAPITAL GROUP | Q335: 3.16632e+09 | R335: 1167.55 | S335: -0.003933 | T335: - | U335: 0.000231 | V335: 0.007108 | W335: 0.003921 | X335: -0.00304 | Y335: -0.01627 | Z335: 0.099481 | AA335: 0.192156 | AB335: -
A336: MA0000039166 | B336: 3916 | C336: CAPITAL TRUST PATRIMOINE | D336: CAPITAL TRUST GESTION | E336: FCP | F336: DIVERSIFIÉ | G336: - | H336: 25% MASI + 30% MBI GLOBAL + 45% MBI MLT | I336: QUOTIDIENNE | J336: FGP | K336: CAPITALISANT | L336: 0.03 | M336: 0.015 | N336: 0.02 | O336: BCP | P336: CAPITAL TRUST GESTION | Q336: 7.2784273e+08 | R336: 1358.88 | S336: -0.016473 | T336: - | U336: -0.005365 | V336: 0.033754 | W336: 0.004287 | X336: 0.002686 | Y336: -0.074276 | Z336: 0.270278 | AA336: 0.403773 | AB336: -
... A340: MA0000039208 | B340: 3920 | C340: TWIN OPPORTUNITY | D340: TWIN CAPITAL GESTION | E340: FCP | F340: DIVERSIFIÉ | G340: - | H340: 30% MASI + 70% MBI | I340: HEBDOMADAIRE | J340: FGP | K340: CAPITALISANT | L340: 0.015 | M340: 0.015 | N340: 0.01 | O340: CFG BANK | P340: TWIN CAPITAL GESTION; CFG BANK | Q340: 2.9701674e+08 | R340: 1203.27 | S340: -0.03027 | T340: - | U340: -0.004616 | V340: 0.028902 | W340: 0.000807 | X340: -0.004122 | Y340: -0.111138 | Z340: 0.129036 | AA340: 0.189437 | AB340: -
A341: MA0000039216 | B341: 3921 | C341: FCP CAPITAL ISR | D341: BMCE CAPITAL GESTION | E341: FCP | F341: DIVERSIFIÉ | G341: - | H341: 75% MBI GLOBAL + 25% MASI ESG | I341: QUOTIDIENNE | J341: FGP | K341: CAPITALISANT | L341: 0.02 | M341: 0.01 | N341: 0.02 | O341: BANK OF AFRICA | P341: BMCE CAPITAL GESTION | Q341: 8.1162177e+08 | R341: 1469.15 | S341: -0.026421 | T341: - | U341: -0.003453 | V341: 0.019203 | W341: 0.003964 | X341: -0.01058 | Y341: -0.08471 | Z341: 0.106146 | AA341: 0.248842 | AB341: 0.127288
A342: MA0000039224 | B342: 3922 | C342: IRGAM ALLOCATION | D342: IRG ASSET MANAGEMENT | E342: FCP | F342: DIVERSIFIÉ | G342: - | H342: 40 % MASI RB + 60 % MBI GLOBAL | I342: HEBDOMADAIRE | J342: FNPP | K342: MIXTE | L342: 0 | M342: 0 | N342: 0.02 | O342: ATTIJARIWAFA BANK | P342: IRG ASSET MANAGEMENT | Q342: 5.209217e+08 | R342: 253.66 | S342: 0.022242 | T342: - | U342: -0.004787 | V342: 0.038696 | W342: 0.018919 | X342: 0.035969 | Y342: -0.036586 | Z342: 0.246172 | AA342: 0.443195 | AB342: 0.385923
A343: MA0000039232 | B343: 3923 | C343: CAPITAL RENDEMENT PLUS | D343: BMCE CAPITAL GESTION | E343: FCP | F343: OMLT | G343: ]1,1 5] | H343: MBI GLOBAL | I343: QUOTIDIENNE | J343: FGP | K343: MIXTE | L343: 0.02 | M343: 0.01 | N343: 0.02 | O343: BANK OF AFRICA | P343: BMCE CAPITAL GESTION; BANK OF AFRICA | Q343: 1132195.9 | R343: 1132.19 | S343: 0.007573 | T343: - | U343: 0.000964 | V343: 0.003296 | W343: 0.00506 | X343: 0.005283 | Y343: 0.008704 | Z343: 0.050864 | AA343: 0.108241 | AB343: -
A344: MA0000039240 | B344: 3924 | C344: AFG SECUR RENDEMENT | D344: AFG ASSET MANAGEMENT | E344: FCP | F344: OMLT | G344: ]1,1 7] | H344: MBI Global | I344: HEBDOMADAIRE | J344: FNPP | K344: CAPITALISANT | L344: 0 | M344: 0 | N344: 0.02 | O344: CDG | P344: AFG ASSET MANAGEMENT | Q344: 2.8621108e+09 | R344: 1260.06 | S344: 0.001255 | T344: - | U344: -5.6e-05 | V344: 0.008976 | W344: 0.005314 | X344: 0.002897 | Y344: -0.013034 | Z344: 0.101355 | AA344: 0.217708 | AB344: -
A345: MA0000039281 | B345: 3928 | C345: BMCI PREMIUM SHORT BOND DIST | D345: CIH CAPITAL MANAGEMENT | E345: FCP | F345: OCT | G345: ]0,5 1,1] | H345: MBI CT | I345: QUOTIDIENNE | J345: FGP | K345: DISTRIBUANT | L345: 0 | M345: 0 | N345: 0.02 | O345: BMCI | P345: CIH CAPITAL MANAGEMENT | Q345: 4770325.1 | R345: 134.26 | S345: 0.013895 | T345: - | U345: 0.000447 | V345: 0.002015 | W345: 0.00479 | X345: 0.010918 | Y345: 0.018974 | Z345: 0.047189 | AA345: 0.091314 | AB345: 0.13334
A346: MA0000039299 | B346: 3929 | C346: WINEO SECUR RENDEMENT | D346: WINEO GESTION | E346: FCP | F346: OMLT | G346: ]1,1 7] | H346: MBI GLOBAL | I346: HEBDOMADAIRE | J346: FNPP | K346: CAPITALISANT | L346: 0 | M346: 0 | N346: 0.02 | O346: CDG | P346: WINEO GESTION | Q346: 2.1950905e+09 | R346: 1261.49 | S346: 0.008885 | T346: - | U346: 0.000293 | V346: 0.008329 | W346: 0.006045 | X346: 0.006527 | Y346: -0.001346 | Z346: 0.105194 | AA346: 0.213776 | AB346: -
A347: MA0000039315 | B347: 3931 | C347: CFG OPPORTUNITÉS | D347: CFG GESTION | E347: FCP | F347: DIVERSIFIÉ | G347: - | H347: 70% MBI GLOBAL + 30% MASI | I347: QUOTIDIENNE | J347: FGP | K347: MIXTE | L347: 0.03 | M347: 0.015 | N347: 0.02 | O347: CFG BANK | P347: CFG GESTION; CFG BANK | Q347: 97667573 | R347: 1248.29 | S347: 0.037096 | T347: - | U347: 0.000537 | V347: 0.006499 | W347: 0.005623 | X347: 0.020846 | Y347: -0.0131 | Z347: 0.149354 | AA347: 0.2068 | AB347: -
A348: MA0000039323 | B348: 3932 | C348: CFG Diversifié | D348: CFG GESTION | E348: FCP | F348: DIVERSIFIÉ | G348: - | H348: 80% MBI GLOBAL + 20% MASI RN | I348: QUOTIDIENNE | J348: FGP | K348: CAPITALISANT | L348: 0.03 | M348: 0.015 | N348: 0.02 | O348: CFG BANK | P348: CFG GESTION; CFG BANK | Q348: 95046456 | R348: 1224.29 | S348: -0.008897 | T348: - | U348: -0.004691 | V348: 0.030573 | W348: 0.003549 | X348: 0.02885 | Y348: -0.013997 | Z348: 0.098235 | AA348: 0.169075 | AB348: -
A349: MA0000039331 | B349: 3933 | C349: UPLINE CROISSANCE | D349: UPLINE CAPITAL MANAGEMENT | E349: FCP | F349: DIVERSIFIÉ | G349: - | H349: 70% MBI + 30% MASI RB | I349: QUOTIDIENNE | J349: FNPP | K349: MIXTE | L349: 0 | M349: 0 | N349: 0.02 | O349: BCP | P349: UPLINE CAPITAL MANAGEMENT | Q349: 1106946.6 | R349: 1106.95 | S349: -0.004595 | T349: - | U349: 0.000416 | V349: 0.012059 | W349: 0.011495 | X349: 0.00577 | Y349: -0.016639 | Z349: 0.063945 | AA349: 0.091871 | AB349: -
A350: MA0000039349 | B350: 3934 | C350: UPLINE SECURITIES PERFORMANCE | D350: UPLINE CAPITAL MANAGEMENT | E350: FCP | F350: DIVERSIFIÉ | G350: - | H350: 75% MBI + 25% MASI RB | I350: HEBDOMADAIRE | J350: FNPP | K350: MIXTE | L350: 0 | M350: 0 | N350: 0.02 | O350: BCP | P350: UPLINE CAPITAL MANAGEMENT | Q350: 1094155.3 | R350: 1094.16 | S350: -0.006988 | T350: - | U350: 0.000503 | V350: 0.012043 | W350: 0.011435 | X350: 0.003918 | Y350: -0.020246 | Z350: 0.056925 | AA350: 0.081047 | AB350: -
A351: MA0000039356 | B351: 3935 | C351: FCP EMERGENCE PATRIMOINE | D351: VALORIS MANAGEMENT | E351: FCP | F351: DIVERSIFIÉ | G351: - | H351: 80% MBI GLOBAL + 20% MASI RB | I351: QUOTIDIENNE | J351: FNPP | K351: CAPITALISANT | L351: 0 | M351: 0 | N351: 0.02 | O351: BANK OF AFRICA | P351: VALORIS MANAGEMENT | Q351: 870220.85 | R351: 178.58 | S351: -0.016088 | T351: - | U351: -0.002123 | V351: 0.009611 | W351: 0.012818 | X351: 0.001908 | Y351: -0.052827 | Z351: 0.210056 | AA351: 0.356063 | AB351: 0.347875
A352: MA0000039364 | B352: 3936 | C352: PROFIL FLEXIBLE | D352: WAFA GESTION | E352: FCP | F352: DIVERSIFIÉ | G352: - | H352: 75% MASI + 25% MBI MT | I352: QUOTIDIENNE | J352: FGP | K352: DISTRIBUANT | L352: 0.02 | M352: 0.02 | N352: 0.02 | O352: ATTIJARIWAFA BANK | P352: WAFA GESTION; ATTIJARIWAFA BANK | Q352: 1.0836829e+09 | R352: 1727.74 | S352: 0.092614 | T352: - | U352: -0.006286 | V352: 0.04205 | W352: 0.02096 | X352: 0.085939 | Y352: 0.024921 | Z352: 0.250997 | AA352: 0.328193 | AB352: 0.284393
A353: MA0000039372 | B353: 3937 | C353: AFG T-BOND FUND | D353: AFG ASSET MANAGEMENT | E353: FCP | F353: OMLT | G353: ]1,1 10] | H353: MBI MLT | I353: QUOTIDIENNE | J353: FNPP | K353: MIXTE | L353: 0 | M353: 0 | N353: 0.02 | O353: ATTIJARIWAFA BANK | P353: AFG ASSET MANAGEMENT | Q353: 1.2303831e+09 | R353: 1127.35 | S353: -0.029189 | T353: - | U353: 0.000435 | V353: 0.007318 | W353: 0.000177 | X353: -0.008305 | Y353: -0.03891 | Z353: 0.114806 | AA353: 0.251682 | AB353: -
A354: MA0000039380 | B354: 3938 | C354: ATLAS HARMONIE | D354: ATLAS CAPITAL MANAGEMENT | E354: FCP | F354: OMLT | G354: ]1,1; 8] | H354: MBI GLOBAL | I354: HEBDOMADAIRE | J354: FNPP | K354: CAPITALISANT | L354: 0.03 | M354: 0.03 | N354: 0.02 | O354: CIH BANK | P354: ATLAS CAPITAL MANAGEMENT | Q354: 2.5557896e+09 | R354: 250.6 | S354: 0.001599 | T354: - | U354: 0.001119 | V354: 0.003805 | W354: 0.003484 | X354: 0.001319 | Y354: -0.003182 | Z354: 0.084144 | AA354: 0.17996 | AB354: 0.164661
A355: MA0000039398 | B355: 3939 | C355: IRGAM DISTRIEQUILIBRE | D355: IRG ASSET MANAGEMENT | E355: FCP | F355: DIVERSIFIÉ | G355: - | H355: 30% MASI FLOTTANT + 70% MBI GLOBAL | I355: HEBDOMADAIRE | J355: FGP | K355: MIXTE | L355: 0.03 | M355: 0.015 | N355: 0.02 | O355: BCP | P355: IRG ASSET MANAGEMENT | Q355: 1.2352709e+09 | R355: 141.3 | S355: -0.00605 | T355: - | U355: -0.00226 | V355: 0.018819 | W355: 0.004407 | X355: 0.005122 | Y355: -0.037007 | Z355: 0.365877 | AA355: 0.404992 | AB355: -
A356: MA0000039406 | B356: 3940 | C356: IRGAM DISTRIEQUITY | D356: IRG ASSET MANAGEMENT | E356: FCP | F356: ACTIONS | G356: - | H356: MASI | I356: HEBDOMADAIRE | J356: FGP | K356: MIXTE | L356: 0.03 | M356: 0.015 | N356: 0.02 | O356: BCP | P356: IRG ASSET MANAGEMENT | Q356: 1623134.4 | R356: 162.31 | S356: -0.044336 | T356: - | U356: -0.006184 | V356: 0.020818 | W356: 0.016725 | X356: -0.004966 | Y356: -0.083926 | Z356: 0.386672 | AA356: 0.599901 | AB356: -
A357: MA0000039414 | B357: 3941 | C357: FCP EMERGENCE ACTIONS | D357: VALORIS MANAGEMENT | E357: FCP | F357: ACTIONS | G357: - | H357: MASI 20 | I357: QUOTIDIENNE | J357: FGP | K357: CAPITALISANT | L357: 0.03 | M357: 0.015 | N357: 0.02 | O357: ATTIJARIWAFA BANK | P357: VALORIS GROUP;VALORIS MANAGEMENT | Q357: 3.4834091e+08 | R357: 1894.4 | S357: 0.007992 | T357: - | U357: -0.010282 | V357: 0.062783 | W357: 0.027945 | X357: 0.050105 | Y357: -0.091349 | Z357: 0.419888 | AA357: 0.806393 | AB357: -
A358: MA0000039422 | B358: 3942 | C358: FCP EMERGENCE PERSPECTIVES | D358: VALORIS MANAGEMENT | E358: FCP | F358: DIVERSIFIÉ | G358: - | H358: 80% MBI GLOBAL + 20% MASI RB | I358: HEBDOMADAIRE | J358: FNPP | K358: MIXTE | L358: 0 | M358: 0 | N358: 0.02 | O358: SAHAM BANK | P358: VALORIS GROUP;VALORIS MANAGEMENT | Q358: 1.8431868e+09 | R358: 1319.78 | S358: 0.009747 | T358: - | U358: -0.001022 | V358: 0.013991 | W358: 0.01001 | X358: 0.012707 | Y358: -0.015663 | Z358: 0.162751 | AA358: 0.306144 | AB358: -
A359: MA0000039430 | B359: 3943 | C359: FCP SANLAM OBLIGATIONS | D359: VALORIS MANAGEMENT | E359: FCP | F359: OMLT | G359: ]1,1 10] | H359: MBI GLOBAL | I359: QUOTIDIENNE | J359: FNPP | K359: MIXTE | L359: 0.03 | M359: 0.015 | N359: 0.02 | O359: BCP | P359: VALORIS MANAGEMENT | Q359: 1.000679e+09 | R359: 1282.8 | S359: -0.014996 | T359: - | U359: 0.000843 | V359: 0.007247 | W359: 0.004463 | X359: -0.001432 | Y359: -0.019603 | Z359: 0.124662 | AA359: 0.267196 | AB359: -
A360: MA0000039448 | B360: 3944 | C360: AFG GOV BOND FUND | D360: AFG ASSET MANAGEMENT | E360: FCP | F360: OMLT | G360: ]4 8] | H360: MBI GLOBAL | I360: QUOTIDIENNE | J360: FGP | K360: MIXTE | L360: 0.03 | M360: 0.03 | N360: 0.02 | O360: ATTIJARIWAFA BANK | P360: AFG ASSET MANAGEMENT | Q360: 2.5912799e+09 | R360: 1224.17 | S360: -0.009467 | T360: - | U360: 0.000662 | V360: 0.004942 | W360: 0.000858 | X360: -0.007322 | Y360: -0.025808 | Z360: 0.080411 | AA360: 0.194685 | AB360: -
A361: MA0000039455 | B361: 3945 | C361: AFG FLEXIBLE FUND | D361: AFG ASSET MANAGEMENT | E361: FCP | F361: DIVERSIFIÉ | G361: - | H361: 75% MBI GLOBAL + 25% MASI RB | I361: QUOTIDIENNE | J361: FNPP | K361: MIXTE | L361: 0.03 | M361: 0.03 | N361: 0.02 | O361: BCP | P361: AFG ASSET MANAGEMENT | Q361: 9.2435546e+08 | R361: 1350.28 | S361: -0.004835 | T361: - | U361: -0.002408 | V361: 0.025565 | W361: 0.006657 | X361: 0.013792 | Y361: -0.041825 | Z361: 0.190064 | AA361: 0.38863 | AB361: -
A362: MA0000039463 | B362: 3946 | C362: ATLAS LIQUIDITE | D362: ATLAS CAPITAL MANAGEMENT | E362: FCP | F362: OCT | G362: 0,5 ; 1,1] | H362: MBI CT | I362: QUOTIDIENNE | J362: FGP | K362: CAPITALISANT | L362: 0.03 | M362: 0.03 | N362: 0.02 | O362: BANK OF AFRICA | P362: ATLAS CAPITAL MANAGEMENT | Q362: 53400064 | R362: 148.33 | S362: 0.018121 | T362: - | U362: 0.000472 | V362: 0.002433 | W362: 0.006787 | X362: 0.013876 | Y362: 0.025937 | Z362: 0.059727 | AA362: 0.077353 | AB362: 0.066202
A363: MA0000039471 | B363: 3947 | C363: AZ TAWFIR | D363: WAFA GESTION | E363: FCP | F363: OMLT | G363: ]1,1 13] | H363: MBI MLT | I363: QUOTIDIENNE | J363: FNPP | K363: MIXTE | L363: 0.03 | M363: 0.015 | N363: 0.02 | O363: BCP | P363: WAFA GESTION | Q363: 3.8268173e+08 | R363: 842911.29 | S363: -0.01362 | T363: - | U363: 0.00107 | V363: 0.003949 | W363: -0.000983 | X363: -0.010905 | Y363: -0.022827 | Z363: 0.075566 | AA363: 0.244212 | AB363: 0.116266
A364: MA0000039489 | B364: 3948 | C364: UNIVERS DIVERSIFIE | D364: WAFA GESTION | E364: FCP | F364: DIVERSIFIÉ | G364: - | H364: 30% MASI RB + 70% MBI MLT | I364: HEBDOMADAIRE | J364: FNPP | K364: MIXTE | L364: 0 | M364: 0 | N364: 0.02 | O364: ATTIJARIWAFA BANK | P364: WAFA GESTION | Q364: 2.1679879e+08 | R364: 2031.07 | S364: 0.022051 | T364: - | U364: -0.003415 | V364: 0.034487 | W364: 0.017591 | X364: 0.035594 | Y364: -0.017235 | Z364: 0.236828 | AA364: 0.409027 | AB364: 0.370641
A365: MA0000039497 | B365: 3949 | C365: CAPITAL IMTIYAZ GARANTI | D365: BMCE CAPITAL GESTION | E365: FCP | F365: CONTRACTUEL | G365: - | H365: MONIA | I365: QUOTIDIENNE | J365: FGP | K365: CAPITALISANT | L365: 0.01 | M365: 0.01 | N365: 0.02 | O365: BANK OF AFRICA | P365: BMCE CAPITAL GESTION | Q365: 1.8698557e+09 | R365: 1060.99 | S365: 0.013885 | T365: - | U365: 0.000226 | V365: 0.001576 | W365: 0.004963 | X365: 0.010293 | Y365: 0.020742 | Z365: 0.044086 | AA365: - | AB365: -
A366: MA0000039505 | B366: 3950 | C366: GENERATION PERFORMANCE | D366: UPLINE CAPITAL MANAGEMENT | E366: SICAV | F366: OMLT | G366: ]1,1 12] | H366: MBI GLOBAL + 50 pbs | I366: HEBDOMADAIRE | J366: FNPP | K366: CAPITALISANT | L366: 0 | M366: 0 | N366: 0.02 | O366: BCP | P366: UPLINE CAPITAL MANAGEMENT | Q366: 4.7684992e+08 | R366: 1107.67 | S366: 0.01004 | T366: - | U366: 0.000687 | V366: 0.002988 | W366: 0.00572 | X366: 0.005748 | Y366: 0.011358 | Z366: 0.081392 | AA366: - | AB366: -
A367: MA0000039513 | B367: 3951 | C367: FCP MAROGEST BONDS | D367: MAROGEST | E367: FCP | F367: OMLT | G367: ]1,1 8,1] | H367: 100% MBI GLOBAL | I367: QUOTIDIENNE | J367: FNPP | K367: CAPITALISANT | L367: 0 | M367: 0 | N367: 0 | O367: CIH BANK | P367: MAROGEST | Q367: 7.659178e+08 | R367: 1087.48 | S367: -0.014285 | T367: - | U367: 0.00081 | V367: 0.006693 | W367: 0.002175 | X367: -0.010905 | Y367: -0.02441 | Z367: 0.069144 | AA367: - | AB367: -
A368: MA0000039521 | B368: 3952 | C368: MAROGEST SECUR RENDEMENT | D368: MAROGEST | E368: FCP | F368: OMLT | G368: ]1,1 7] | H368: 100% MBI GLOBAL | I368: HEBDOMADAIRE | J368: FNPP | K368: CAPITALISANT | L368: 0 | M368: 0 | N368: 0 | O368: CDG | P368: MAROGEST | Q368: 5.4534468e+08 | R368: 1134.06 | S368: -0.000582 | T368: - | U368: 0.000326 | V368: 0.006997 | W368: 0.006139 | X368: 0.001988 | Y368: -0.008966 | Z368: 0.095816 | AA368: - | AB368: -
A369: MA0000039539 | B369: 3953 | C369: ATTIJARI PRIVATE FUND | D369: WAFA GESTION | E369: FCP | F369: DIVERSIFIÉ | G369: - | H369: 50% MASI RB + 50% MBI GLOBAL | I369: HEBDOMADAIRE | J369: FGP | K369: MIXTE | L369: 0.02 | M369: 0.02 | N369: 0.02 | O369: ATTIJARIWAFA BANK | P369: WAFA GESTION | Q369: 8.5538738e+08 | R369: 1149714.2 | S369: 0.073075 | T369: - | U369: -0.006323 | V369: 0.051996 | W369: 0.024981 | X369: 0.067738 | Y369: 0.056745 | Z369: 0.131797 | AA369: - | AB369: -
A370: MA0000039547 | B370: 3954 | C370: FCP ALPHA BONDS | D370: RED MED ASSET MANAGEMENT | E370: FCP | F370: OMLT | G370: ]1,1 10] | H370: MBI GLOBAL | I370: QUOTIDIENNE | J370: FNPP | K370: CAPITALISANT | L370: 0 | M370: 0 | N370: 0.02 | O370: BCP | P370: RED MED ASSET MANAGEMENT | Q370: 2.3255486e+09 | R370: 1209.89 | S370: 0.000819 | T370: - | U370: 0.000927 | V370: 0.0037 | W370: 0.002793 | X370: 0.000885 | Y370: -0.002054 | Z370: 0.083762 | AA370: 0.174776 | AB370: -
A371: MA0000039554 | B371: 3955 | C371: AD HARMONIE DIVERSIFIÉ | D371: AD CAPITAL ASSET MANAGEMENT | E371: FCP | F371: DIVERSIFIÉ | G371: - | H371: 50% MASI + 50% MBI MLT | I371: HEBDOMADAIRE | J371: FGP | K371: DISTRIBUANT | L371: 0.03 | M371: 0.03 | N371: 0.02 | O371: ATTIJARIWAFA BANK | P371: AD CAPITAL ASSET MANAGEMENT; AD CAPITAL GROUP | Q371: 5.0198635e+08 | R371: 1112.89 | S371: -0.050824 | T371: - | U371: -0.001355 | V371: 0.019289 | W371: 0.005975 | X371: -0.025815 | Y371: -0.101109 | Z371: - | AA371: - | AB371: -
A372: MA0000039570 | B372: 3957 | C372: AFG ACTIVE BOND FUND | D372: AFG ASSET MANAGEMENT | E372: FCP | F372: OMLT | G372: ]4 8] | H372: 95% MBI GLOBAL + 5% MASI | I372: QUOTIDIENNE | J372: FGP | K372: MIXTE | L372: 0.03 | M372: 0.03 | N372: 0.02 | O372: BANQUE CENTRALE POPULAIRE | P372: AFG ASSET MANAGEMENT | Q372: 1.1644337e+09 | R372: 1100.13 | S372: -0.011315 | T372: - | U372: -5.5e-05 | V372: 0.007879 | W372: 0.000837 | X372: -0.007004 | Y372: -0.024534 | Z372: - | AA372: - | AB372: -
A373: MA0000039596 | B373: 3959 | C373: FH2 OBLIGATAIRE DYNAMIQUE II | D373: BMCE CAPITAL GESTION | E373: FCP | F373: OMLT | G373: ]1,1 7,1] | H373: MBI Global | I373: HEBDOMADAIRE | J373: FNPP | K373: MIXTE | L373: 0 | M373: 0 | N373: 0.02 | O373: BANK OF AFRICA | P373: BMCE CAPITAL GESTION | Q373: 2.1217876e+09 | R373: 1231.16 | S373: 0.001521 | T373: - | U373: 0.001065 | V373: 0.003775 | W373: 0.000772 | X373: -0.002673 | Y373: -0.000755 | Z373: - | AA373: - | AB373: -
A374: MA0000039604 | B374: 3960 | C374: FCP EMERGENCE OPTIMUM | D374: VALORIS MANAGEMENT | E374: FCP | F374: DIVERSIFIÉ | G374: - | H374: 60% MBI + 40% MASI | I374: QUOTIDIENNE | J374: FGP | K374: MIXTE | L374: 0.03 | M374: 0.015 | N374: 0.02 | O374: CREDIT DU MAROC | P374: VALORIS MANAGEMENT | Q374: 1.5980582e+09 | R374: 1187.79 | S374: -0.012496 | T374: - | U374: -0.004476 | V374: 0.028034 | W374: 0.010627 | X374: 0.005792 | Y374: -0.057339 | Z374: - | AA374: - | AB374: -
A375: MA0000039612 | B375: 3961 | C375: CCM SECUR RENDEMENT | D375: CIH CAPITAL MANAGEMENT | E375: FCP | F375: OMLT | G375: [1,1 7] | H375: MBI GLOBAL | I375: HEBDOMADAIRE | J375: FNPP | K375: CAPITALISANT | L375: 0 | M375: 0 | N375: 0.02 | O375: CDG | P375: CIH CAPITAL MANAGEMENT | Q375: 1.0291317e+09 | R375: 1133.36 | S375: 0.002025 | T375: - | U375: 0.000212 | V375: 0.007136 | W375: 0.003942 | X375: 0.0034 | Y375: -0.008156 | Z375: - | AA375: - | AB375: -
A376: MA0000039620 | B376: 3962 | C376: FCP FH2 OBLIGATAIRE DP | D376: VALORIS MANAGEMENT | E376: FCP | F376: OMLT | G376: [1,1 5] | H376: 90% MBI MT + 10% MBI MLT + 50 pbs | I376: QUOTIDIENNE | J376: FNPP | K376: MIXTE | L376: 0 | M376: 0 | N376: 0.02 | O376: CDM | P376: VALORIS MANAGEMENT | Q376: 8.880077e+08 | R376: 1077.65 | S376: 0.017092 | T376: - | U376: 0.000901 | V376: 0.004586 | W376: 0.008941 | X376: 0.013019 | Y376: 0.021169 | Z376: - | AA376: - | AB376: -
A377: MA0000039638 | B377: 3963 | C377: FCP AFRICAPITAL RENDEMENT | D377: AFRICAPITAL MANAGEMENT | E377: FCP | F377: OMLT | G377: [2 6] | H377: MBI GLOBAL | I377: QUOTIDIENNE | J377: FGP | K377: CAPITALISANT | L377: 0.03 | M377: 0.03 | N377: 0.02 | O377: BCP | P377: AFRICAPITAL MANAGEMENT | Q377: 1.0587457e+09 | R377: 1033.12 | S377: -0.004625 | T377: - | U377: 0.000271 | V377: 0.009044 | W377: 0.003633 | X377: -0.001083 | Y377: -0.018115 | Z377: - | AA377: - | AB377: -
A378: MA0000039653 | B378: 3965 | C378: FCP ALPHA OBLIGATAIRE | D378: RED MED ASSET MANAGEMENT | E378: FCP | F378: OMLT | G378: ]1,1 10] | H378: MBI GLOBAL | I378: QUOTIDIENNE | J378: FNPP | K378: CAPITALISANT | L378: 0 | M378: 0 | N378: 0.02 | O378: BCP | P378: RED MED ASSET MANAGEMENT;RED MED SECURITIES | Q378: 1124025.2 | R378: 1124.02 | S378: 0.001301 | T378: - | U378: 0.000828 | V378: 0.00358 | W378: 0.004253 | X378: -0.001554 | Y378: -0.003926 | Z378: 0.076699 | AA378: 0.148565 | AB378: -
A379: MA0000039661 | B379: 3966 | C379: FCP EMERGENCE HARMONY FUND | D379: VALORIS MANAGEMENT | E379: FCP | F379: OMLT | G379: [1,1 10] | H379: MBI MT | I379: QUOTIDIENNE | J379: FNPP | K379: MIXTE | L379: 0 | M379: 0 | N379: 0.02 | O379: CIH BANK | P379: VALORIS MANAGEMENT | Q379: 17668518 | R379: 1358.28 | S379: 0.014816 | T379: - | U379: 0.00101 | V379: 0.00348 | W379: 0.005917 | X379: 0.012591 | Y379: 0.012523 | Z379: 0.104733 | AA379: 0.234912 | AB379: 0.283467
A380: MA0000039679 | B380: 3967 | C380: FCP OPTIMA EQUILIBRE | D380: ALPHAVEST ASSET MANAGEMENT | E380: FCP | F380: DIVERSIFIÉ | G380: - | H380: 60% MBI GLOBAL + 40% MASI | I380: QUOTIDIENNE | J380: FGP | K380: CAPITALISANT | L380: 0.03 | M380: 0.015 | N380: 0.02 | O380: BANQUE CENTRALE POPULAIRE | P380: ALPHAVEST ASSET MANAGEMENT | Q380: 2.6471158e+08 | R380: 988.42 | S380: -0.013454 | T380: - | U380: -0.004672 | V380: 0.030785 | W380: 0.008396 | X380: 0.003666 | Y380: -0.075076 | Z380: - | AA380: - | AB380: -
A381: MA0000039687 | B381: 3968 | C381: FCP OPTIMA MONETAIRE | D381: ALPHAVEST ASSET MANAGEMENT | E381: FCP | F381: MONÉTAIRE | G381: [0 0,5] | H381: MONIA | I381: QUOTIDIENNE | J381: FGP | K381: CAPITALISANT | L381: 0.03 | M381: 0.015 | N381: 0.02 | O381: BANQUE CENTRALE POPULAIRE | P381: ALPHAVEST ASSET MANAGEMENT | Q381: 9.533508e+08 | R381: 1031.04 | S381: 0.017487 | T381: - | U381: 0.000281 | V381: 0.001992 | W381: 0.006069 | X381: 0.013178 | Y381: 0.025594 | Z381: - | AA381: - | AB381: -
A382: MA0000039695 | B382: 3969 | C382: FCP OPTIMA OBLIGATAIRE | D382: ALPHAVEST ASSET MANAGEMENT | E382: FCP | F382: OMLT | G382: [4 8] | H382: MBI GLOBAL | I382: QUOTIDIENNE | J382: FGP | K382: CAPITALISANT | L382: 0.03 | M382: 0.015 | N382: 0.02 | O382: BANQUE CENTRALE POPULAIRE | P382: ALPHAVEST ASSET MANAGEMENT | Q382: 5.2077216e+08 | R382: 1010.87 | S382: -0.004912 | T382: - | U382: 0.000307 | V382: 0.006001 | W382: 0.003833 | X382: -0.005118 | Y382: -0.008261 | Z382: - | AA382: - | AB382: -
A383: MA0000039703 | B383: 3970 | C383: FCP OPTIMA SOUVERAIN | D383: ALPHAVEST ASSET MANAGEMENT | E383: FCP | F383: OMLT | G383: [4 8] | H383: MBI GLOBAL | I383: QUOTIDIENNE | J383: FGP | K383: CAPITALISANT | L383: 0.03 | M383: 0.015 | N383: 0.02 | O383: BANK OF AFRICA | P383: ALPHAVEST ASSET MANAGEMENT | Q383: 2.8929605e+08 | R383: 1076.79 | S383: 0.060574 | T383: - | U383: 0.001283 | V383: 0.003663 | W383: 0.000669 | X383: -0.005495 | Y383: 0.058686 | Z383: - | AA383: - | AB383: -
A384: MA0000039711 | B384: 3971 | C384: FCP OPTIMA DYNAMIQUE | D384: ALPHAVEST ASSET MANAGEMENT | E384: FCP | F384: OCT | G384: [0,5 1,1] | H384: MBI CT | I384: QUOTIDIENNE | J384: FGP | K384: CAPITALISANT | L384: 0.03 | M384: 0.015 | N384: 0.02 | O384: BANK OF AFRICA | P384: ALPHAVEST ASSET MANAGEMENT | Q384: 9.7966602e+08 | R384: 1033.56 | S384: 0.019471 | T384: - | U384: 0.000416 | V384: 0.002473 | W384: 0.006917 | X384: 0.014607 | Y384: 0.027263 | Z384: - | AA384: - | AB384: -
...

Sheet 24_08
A1: Tableau des performances hebdomadaires au 24-08-2026
A2: CODE ISIN | B2: Code Maroclear | C2: OPCVM | D2: Société de Gestion | E2: Nature juridique | F2: Classification | G2: Sensibilité | H2: Indice Bentchmark | I2: Périodicité VL | J2: Souscripteurs | K2: Affectation des résultats | L2: Commission de souscription | M2: Commission de rachat | N2: Frais de gestion | O2: Dépositaire | P2: Réseau placeur | Q2: AN | R2: VL | S2: YTD | T2: 1 jour | U2: 1 semaine | V2: 1 mois | W2: 3 mois | X2: 6 mois | Y2: 1 an | Z2: 2 ans | AA2: 3 ans | AB2: 5 ans
A3: MA0000030058 | B3: 3005 | C3: BMCI COSMOS | D3: CIH CAPITAL MANAGEMENT | E3: SICAV | F3: ACTIONS | G3: - | H3: MASI | I3: HEBDOMADAIRE | J3: FGP | K3: CAPITALISANT | L3: 0.02 | M3: 0.0075 | N3: 0.02 | O3: BMCI | P3: CIH CAPITAL MANAGEMENT | Q3: 30359266 | R3: 452.66 | S3: 0.038092 | T3: - | U3: 0.015707 | V3: 0.078019 | W3: 0.063806 | X3: 0.035196 | Y3: -0.065852 | Z3: 0.384027 | AA3: 0.603983 | AB3: 0.548614
A4: MA0000030066 | B4: 3006 | C4: BMCI EPARGNE OBLIGATIONS | D4: CIH CAPITAL MANAGEMENT | E4: SICAV | F4: OMLT | G4: [3 7[ | H4: MBI MLT | I4: HEBDOMADAIRE | J4: FGP | K4: CAPITALISANT | L4: 0.005 | M4: 0.0025 | N4: 0.0093 | O4: BMCI | P4: CIH CAPITAL MANAGEMENT | Q4: 1.1637948e+08 | R4: 274.48 | S4: -0.007987 | T4: - | U4: 0.001204 | V4: 0.004281 | W4: 0.001642 | X4: -0.006623 | Y4: -0.010812 | Z4: 0.070974 | AA4: 0.160101 | AB4: 0.091893
A5: MA0000030132 | B5: 3013 | C5: BMCI TRESORERIE | D5: CIH CAPITAL MANAGEMENT | E5: SICAV | F5: MONÉTAIRE | G5: [0 0,5[ | H5: TMJ(jj) | I5: QUOTIDIENNE | J5: FGP | K5: CAPITALISANT | L5: 0.0125 | M5: 0.005 | N5: 0.0195 | O5: BMCI | P5: CIH CAPITAL MANAGEMENT | Q5: 1.6793136e+08 | R5: 123478.94 | S5: 0.010174 | T5: - | U5: 0.000319 | V5: 0.001243 | W5: 0.003902 | X5: 0.007801 | Y5: 0.014992 | Z5: 0.033321 | AA5: 0.057219 | AB5: 0.083757
A6: MA0000030215 | B6: 3021 | C6: CDG IZDIHAR | D6: CDG CAPITAL GESTION | E6: SICAV | F6: DIVERSIFIÉ | G6: - | H6: 77% MBI GLOBAL + 23% CFG 25 FLOTTANT | I6: HEBDOMADAIRE | J6: FGP | K6: CAPITALISANT | L6: 0.003 | M6: 0.0025 | N6: 0.02 | O6: CDG CAPITAL | P6: CDG CAPITAL GESTION | Q6: 1.3155362e+09 | R6: 4162.18 | S6: -0.030692 | T6: - | U6: 0.005132 | V6: 0.036443 | W6: 0.019765 | X6: -0.034151 | Y6: -0.093387 | Z6: 0.135957 | AA6: 0.276445 | AB6: 0.189878
A7: MA0000030280 | B7: 3028 | C7: CDG TAWFIR | D7: CDG CAPITAL GESTION | E7: SICAV | F7: OMLT | G7: [3 7[ | H7: MBI GLOBAL | I7: QUOTIDIENNE | J7: FGP | K7: CAPITALISANT | L7: 0.005 | M7: 0 | N7: 0.02 | O7: CDG CAPITAL | P7: CDG CAPITAL GESTION | Q7: 1.7843932e+09 | R7: 3476.45 | S7: -0.000334 | T7: - | U7: 0.0014 | V7: 0.007427 | W7: 0.005874 | X7: -0.002239 | Y7: -0.00651 | Z7: 0.084067 | AA7: 0.170577 | AB7: 0.104599
A8: MA0000030298 | B8: 3029 | C8: SICAV OBLIGATIONS PÉRENNITÉ | D8: CDG CAPITAL GESTION | E8: SICAV | F8: OMLT | G8: [1,1 16[ | H8: MBI MT | I8: QUOTIDIENNE | J8: FNPP | K8: CAPITALISANT | L8: 0.03 | M8: 0.015 | N8: 0.02 | O8: CDG CAPITAL | P8: CDG CAPITAL GESTION | Q8: 8.1706182e+09 | R8: 3298.83 | S8: -0.005106 | T8: - | U8: 0.000752 | V8: 0.002413 | W8: 0.005465 | X8: 0.005364 | Y8: -0.003272 | Z8: 0.053741 | AA8: 0.106029 | AB8: 0.119188
A9: MA0000030306 | B9: 3030 | C9: CDG TRESORERIE | D9: CDG CAPITAL GESTION | E9: SICAV | F9: MONÉTAIRE | G9: [0 0,5[ | H9: 50% MBI CT + 50% TMP | I9: QUOTIDIENNE | J9: FGP | K9: CAPITALISANT | L9: 0 | M9: 0 | N9: 0.02 | O9: CDG CAPITAL | P9: CDG CAPITAL GESTION | Q9: 5.2254534e+09 | R9: 2278.57 | S9: 0.01811 | T9: - | U9: 0.000624 | V9: 0.00242 | W9: 0.007423 | X9: 0.014294 | Y9: 0.026637 | Z9: 0.057375 | AA9: 0.094451 | AB9: 0.138135
A10: MA0000030363 | B10: 3036 | C10: BMCI EPARGNE CROISSANCE | D10: CIH CAPITAL MANAGEMENT | E10: SICAV | F10: DIVERSIFIÉ | G10: - | H10: 60% MASI + 40% MBI MT | I10: HEBDOMADAIRE | J10: FGP | K10: CAPITALISANT | L10: 0.0125 | M10: 0.005 | N10: 0.0195 | O10: BMCI | P10: CIH CAPITAL MANAGEMENT | Q10: 2.7352334e+08 | R10: 165.82 | S10: -0.013798 | T10: - | U10: 0.004848 | V10: 0.023391 | W10: 0.0183 | X10: -0.009557 | Y10: -0.044265 | Z10: 0.143192 | AA10: 0.271723 | AB10: 0.278883
A11: MA0000030371 | B11: 3037 | C11: CIMR TRESO PLUS | D11: SAHAM CAPITAL GESTION | E11: SICAV | F11: OCT | G11: ]0,5 1,1] | H11: MBI CT | I11: QUOTIDIENNE | J11: FNPP | K11: CAPITALISANT | L11: 0 | M11: 0 | N11: 0.02 | O11: SAHAM BANK | P11: SAHAM BANK | Q11: 1.3705129e+08 | R11: 403092.03 | S11: 0.015963 | T11: - | U11: 0.000608 | V11: 0.001914 | W11: 0.006369 | X11: 0.012233 | Y11: 0.021941 | Z11: 0.051635 | AA11: 0.089465 | AB11: 0.132169
A12: MA0000030397 | B12: 3039 | C12: CDG BARID | D12: CDG CAPITAL GESTION | E12: SICAV | F12: OMLT | G12: [3 7[ | H12: - | I12: HEBDOMADAIRE | J12: FNPP | K12: CAPITALISANT | L12: 0.005 | M12: 0 | N12: 0.02 | O12: CDG | P12: CDG CAPITAL GESTION | Q12: 3.4367662e+09 | R12: 3733.53 | S12: -0.005773 | T12: - | U12: 0.001792 | V12: 0.007578 | W12: 0.005456 | X12: -0.00475 | Y12: -0.016039 | Z12: 0.083697 | AA12: 0.184717 | AB12: 0.076848
A13: MA0000030405 | B13: 3040 | C13: SICAV MAROC CROISSANCE | D13: MAROGEST | E13: SICAV | F13: DIVERSIFIÉ | G13: - | H13: - | I13: HEBDOMADAIRE | J13: FGP | K13: CAPITALISANT | L13: 0.02 | M13: 0.005 | N13: 0.02 | O13: CIH BANK | P13: MAROGEST | Q13: 3.0700823e+08 | R13: 5231.91 | S13: -0.03534 | T13: - | U13: 0.004072 | V13: 0.032381 | W13: 0.02404 | X13: -0.034236 | Y13: -0.096243 | Z13: 0.153974 | AA13: 0.356521 | AB13: 0.347298
A14: MA0000030413 | B14: 3041 | C14: BMCI CASH | D14: CIH CAPITAL MANAGEMENT | E14: SICAV | F14: OCT | G14: [0,6 1,1[ | H14: MBI CT | I14: QUOTIDIENNE | J14: FGP | K14: CAPITALISANT | L14: 0 | M14: 0 | N14: 0.0067 | O14: BMCI | P14: CIH CAPITAL MANAGEMENT | Q14: 31219914 | R14: 196.45 | S14: 0.020944 | T14: - | U14: 0.000509 | V14: 0.004602 | W14: 0.010389 | X14: 0.018351 | Y14: 0.031829 | Z14: 0.063444 | AA14: 0.094002 | AB14: 0.115813
... A57: MA0000035453 | B57: 3545 | C57: SCR INTEGRALE | D57: CDG CAPITAL GESTION | E57: FCP | F57: ACTIONS | G57: - | H57: CFG 25 FLOTTANT | I57: HEBDOMADAIRE | J57: FNPP | K57: DISTRIBUANT | L57: 0.03 | M57: 0.015 | N57: 0.02 | O57: CDG CAPITAL | P57: CDG CAPITAL GESTION | Q57: 2.303213e+08 | R57: 6690.13 | S57: -0.038433 | T57: - | U57: 0.010406 | V57: 0.071733 | W57: 0.054994 | X57: -0.022108 | Y57: -0.131005 | Z57: 0.277403 | AA57: 0.497753 | AB57: 0.438198
A58: MA0000035461 | B58: 3546 | C58: SCR OBLIGATIONS | D58: CDG CAPITAL GESTION | E58: FCP | F58: OMLT | G58: ]1,1 9] | H58: MBI GLOBAL | I58: HEBDOMADAIRE | J58: FNPP | K58: CAPITALISANT | L58: 0 | M58: 0 | N58: - | O58: CDG CAPITAL | P58: CDG CAPITAL GESTION | Q58: 2.4209056e+09 | R58: 2731.36 | S58: -0.001334 | T58: - | U58: 0.001188 | V58: 0.004306 | W58: 0.00483 | X58: -0.001193 | Y58: -0.006446 | Z58: 0.084771 | AA58: 0.18333 | AB58: 0.080557
A59: MA0000035487 | B59: 3548 | C59: CDG ACTIONS | D59: CDG CAPITAL GESTION | E59: FCP | F59: ACTIONS | G59: - | H59: CFG 25 FLOTTANT | I59: HEBDOMADAIRE | J59: FNPP | K59: CAPITALISANT | L59: 0.03 | M59: 0.015 | N59: 0.02 | O59: CDG CAPITAL | P59: CDG CAPITAL GESTION | Q59: 1.792654e+09 | R59: 7774.13 | S59: -0.014334 | T59: - | U59: 0.015106 | V59: 0.081716 | W59: 0.065523 | X59: -0.001513 | Y59: -0.114996 | Z59: 0.241263 | AA59: 0.420996 | AB59: 0.373427
A60: MA0000035495 | B60: 3549 | C60: AL IKRAM | D60: CIH CAPITAL MANAGEMENT | E60: FCP | F60: DIVERSIFIÉ | G60: - | H60: 60% MASI + 40% MBI MT | I60: HEBDOMADAIRE | J60: FNPP | K60: CAPITALISANT | L60: 0.03 | M60: 0.015 | N60: 0.0075 | O60: BMCI | P60: CIH CAPITAL MANAGEMENT | Q60: 35007207 | R60: 36849.69 | S60: -0.000661 | T60: - | U60: 0.001643 | V60: 0.014847 | W60: 0.014993 | X60: 0.00318 | Y60: -0.026422 | Z60: 0.129366 | AA60: 0.235448 | AB60: 0.255718
A61: MA0000035503 | B61: 3550 | C61: CASACTIONS | D61: CIH CAPITAL MANAGEMENT | E61: FCP | F61: DIVERSIFIÉ | G61: - | H61: 80% MBI GLOBAL + 20% MASI | I61: HEBDOMADAIRE | J61: FNPP | K61: DISTRIBUANT | L61: 0.03 | M61: 0.015 | N61: 0.02 | O61: BMCI | P61: CIH CAPITAL MANAGEMENT | Q61: 2471148.6 | R61: 176510.61 | S61: 0.000125 | T61: - | U61: 0.000821 | V61: 0.002192 | W61: 0.003305 | X61: 0.001332 | Y61: -0.001839 | Z61: 0.011621 | AA61: 0.032218 | AB61: 0.031679
A62: MA0000035511 | B62: 3551 | C62: AVENIR ACTIONS | D62: CIH CAPITAL MANAGEMENT | E62: FCP | F62: DIVERSIFIÉ | G62: - | H62: 80% MBI GLOBAL + 20% MASI | I62: HEBDOMADAIRE | J62: FNPP | K62: DISTRIBUANT | L62: 0.03 | M62: 0.015 | N62: 0.02 | O62: BMCI | P62: CIH CAPITAL MANAGEMENT | Q62: 226365390 | R62: 250404.19 | S62: 0.002198 | T62: - | U62: 0.005349 | V62: 0.030053 | W62: 0.02379 | X62: 0.00182 | Y62: -0.044081 | Z62: 0.139823 | AA62: 0.25105 | AB62: 0.24884
A63: MA0000035529 | B63: 3552 | C63: AXA HORIZON | D63: CIH CAPITAL MANAGEMENT | E63: FCP | F63: DIVERSIFIÉ | G63: - | H63: CFG 25 FLOTTANT | I63: HEBDOMADAIRE | J63: FNPP | K63: MIXTE | L63: 0.03 | M63: 0.015 | N63: 0 | O63: BMCI | P63: CIH CAPITAL MANAGEMENT | Q63: 8.2454502e+08 | R63: 181497.91 | S63: 0.010424 | T63: - | U63: 0.005996 | V63: 0.026809 | W63: 0.022661 | X63: 0.007734 | Y63: -0.023711 | Z63: 0.196411 | AA63: 0.335349 | AB63: 0.295967
A64: MA0000035537 | B64: 3553 | C64: CIMR THARWA | D64: CIH CAPITAL MANAGEMENT | E64: FCP | F64: ACTIONS | G64: - | H64: MASI RN | I64: HEBDOMADAIRE | J64: FNPP | K64: CAPITALISANT | L64: 0 | M64: 0 | N64: 0.02 | O64: BMCI | P64: CIH CAPITAL MANAGEMENT | Q64: 1.1656895e+09 | R64: 524612.73 | S64: 0.03992 | T64: - | U64: 0.015904 | V64: 0.082095 | W64: 0.063812 | X64: 0.040307 | Y64: -0.052075 | Z64: 0.403137 | AA64: 0.659227 | AB64: 0.675629
A65: MA0000035545 | B65: 3554 | C65: BMCI INVEST | D65: CIH CAPITAL MANAGEMENT | E65: FCP | F65: DIVERSIFIÉ | G65: - | H65: 60% MASI + 40% MBI MT | I65: HEBDOMADAIRE | J65: FNPP | K65: CAPITALISANT | L65: 0.03 | M65: 0.015 | N65: 0.006 | O65: BMCI | P65: CIH CAPITAL MANAGEMENT | Q65: 839472.75 | R65: 239.85 | S65: 0.004902 | T65: - | U65: -0.00025 | V65: 0.011129 | W65: -0.004607 | X65: -0.000458 | Y65: -0.011906 | Z65: 0.044324 | AA65: 0.067756 | AB65: 0.059221
A66: MA0000035552 | B66: 3555 | C66: AXA AVENIR | D66: CDG CAPITAL GESTION | E66: FCP | F66: DIVERSIFIÉ | G66: - | H66: 80% MBI GLOBAL + 25% MASI RN | I66: HEBDOMADAIRE | J66: FNPP | K66: MIXTE | L66: 0.03 | M66: 0.015 | N66: 0.02 | O66: CDG CAPITAL | P66: CDG CAPITAL GESTION | Q66: 7.8287141e+08 | R66: 3660.22 | S66: -0.015877 | T66: - | U66: 0.005119 | V66: 0.025961 | W66: 0.021215 | X66: -0.011906 | Y66: -0.059141 | Z66: 0.146368 | AA66: 0.251108 | AB66: 0.201625
A67: MA0000035594 | B67: 3559 | C67: HORIZON BALANCED FUND | D67: SAHAM CAPITAL GESTION | E67: FCP | F67: DIVERSIFIÉ | G67: - | H67: 50% MBI GLOBAL + 50% MASI | I67: QUOTIDIENNE | J67: FGP | K67: DISTRIBUANT | L67: 0.02 | M67: 0.015 | N67: 0.02 | O67: SAHAM BANK | P67: SAHAM BANK | Q67: 1293595.6 | R67: 107799.63 | S67: -0.00143 | T67: - | U67: 0.007262 | V67: 0.03519 | W67: -0.005421 | X67: -0.006674 | Y67: -0.049498 | Z67: 0.189829 | AA67: 0.362213 | AB67: 0.381902
A68: MA0000035651 | B68: 3565 | C68: ATLAS PREMIUM | D68: ATLAS CAPITAL MANAGEMENT | E68: FCP | F68: ACTIONS | G68: - | H68: MASI | I68: HEBDOMADAIRE | J68: FGP | K68: CAPITALISANT | L68: 0.03 | M68: 0.015 | N68: 0.015 | O68: CIH BANK | P68: ATLAS CAPITAL MANAGEMENT | Q68: 1052815.6 | R68: 767.91 | S68: 0.05124 | T68: - | U68: 0.014452 | V68: 0.077738 | W68: 0.063749 | X68: 0.044989 | Y68: -0.046868 | Z68: 0.44325 | AA68: 0.700044 | AB68: 0.659628
A69: MA0000035677 | B69: 3567 | C69: CDG HORIZONS | D69: CDG CAPITAL GESTION | E69: FCP | F69: OMLT | G69: ]1,1 5,1] | H69: 50% MBI MLT + 50% MBI MT | I69: QUOTIDIENNE | J69: FGP | K69: CAPITALISANT | L69: 0.03 | M69: 0.015 | N69: 0.02 | O69: CDG CAPITAL | P69: CDG CAPITAL GESTION | Q69: 2.3065998e+08 | R69: 2257.05 | S69: 0.00705 | T69: - | U69: 0.000656 | V69: 0.003325 | W69: 0.005605 | X69: 0.005511 | Y69: 0.013002 | Z69: 0.086306 | AA69: 0.143349 | AB69: 0.130934
A70: MA0000035685 | B70: 3568 | C70: AVENIR OBLIGATION | D70: CFG GESTION | E70: FCP | F70: OMLT | G70: [4 8[ | H70: CFG BONDS MT | I70: HEBDOMADAIRE | J70: FNPP | K70: MIXTE | L70: 0 | M70: 0 | N70: 0.01 | O70: ATTIJARIWAFA BANK | P70: CFG GESTION | Q70: 1.4021896e+09 | R70: 26110.57 | S70: -0.002706 | T70: - | U70: 0.000853 | V70: 0.002806 | W70: 0.001529 | X70: -0.00326 | Y70: -0.011532 | Z70: 0.07997 | AA70: 0.180455 | AB70: 0.087448
... A118: MA0000036329 | B118: 3632 | C118: FCP CAPITAL TERME | D118: BMCE CAPITAL GESTION | E118: FCP | F118: DIVERSIFIÉ | G118: - | H118: 80% MBI GLOBAL + 20% MASI | I118: QUOTIDIENNE | J118: FGP | K118: CAPITALISANT | L118: 0.02 | M118: 0.02 | N118: 0.02 | O118: BANK OF AFRICA | P118: BMCE CAPITAL GESTION | Q118: 81346694 | R118: 249.05 | S118: 0.025826 | T118: - | U118: 0.003748 | V118: 0.019652 | W118: 0.033402 | X118: 0.024307 | Y118: -0.003202 | Z118: 0.177096 | AA118: 0.301202 | AB118: 0.257447
A119: MA0000036345 | B119: 3634 | C119: CFG INSTIBONDS | D119: CFG GESTION | E119: FCP | F119: OMLT | G119: ]1,5 5,5] | H119: MBI GLOBAL | I119: QUOTIDIENNE | J119: FGP | K119: CAPITALISANT | L119: 0.03 | M119: 0.015 | N119: 0.02 | O119: CFG BANK | P119: CFG GESTION; CFG BANK | Q119: 5.5249415e+08 | R119: 34.15 | S119: 0.00176 | T119: - | U119: 0.000879 | V119: 0.004116 | W119: 0.003821 | X119: -0.001462 | Y119: -0.780386 | Z119: -0.767133 | AA119: -0.754969 | AB119: -
A120: MA0000036352 | B120: 3635 | C120: FCP CAM TRESO PLUS | D120: MAROGEST | E120: FCP | F120: OCT | G120: ]0,5 1,1] | H120: 85% MBI CT + 15 % MBI MT | I120: QUOTIDIENNE | J120: FGP | K120: CAPITALISANT | L120: 0.03 | M120: 0.015 | N120: 0.02 | O120: CIH BANK | P120: CIH | Q120: 8.8535144e+08 | R120: 174.74 | S120: 0.018595 | T120: - | U120: 0.000745 | V120: 0.002237 | W120: 0.007379 | X120: 0.01422 | Y120: 0.026313 | Z120: 0.062701 | AA120: 0.10553 | AB120: 0.151803
A121: MA0000036378 | B121: 3637 | C121: AVENIR CROISSANCE | D121: CFG GESTION | E121: FCP | F121: ACTIONS | G121: - | H121: CFG 25 FLOTTANT | I121: HEBDOMADAIRE | J121: FNPP | K121: MIXTE | L121: 0.03 | M121: 0.015 | N121: 0.02 | O121: ATTIJARIWAFA BANK | P121: CFG GESTION | Q121: 1307500.1 | R121: 36319.45 | S121: -0.031662 | T121: - | U121: 0.004315 | V121: 0.039068 | W121: 0.030488 | X121: -0.031372 | Y121: -0.117025 | Z121: 0.217066 | AA121: 0.457583 | AB121: 0.449455
A122: MA0000036394 | B122: 3639 | C122: FCP CAPITAL TAALIM | D122: BMCE CAPITAL GESTION | E122: FCP | F122: OMLT | G122: [4 8[ | H122: 95% MBI MLT + 5% MASI | I122: HEBDOMADAIRE | J122: FNPP | K122: CAPITALISANT | L122: 0.03 | M122: 0.015 | N122: 0.02 | O122: BANK OF AFRICA | P122: BMCE CAPITAL GESTION | Q122: 3.5534625e+09 | R122: 2373.64 | S122: -0.000644 | T122: - | U122: 0.002081 | V122: 0.008587 | W122: 0.007474 | X122: -0.001073 | Y122: -0.014429 | Z122: 0.109748 | AA122: 0.225623 | AB122: 0.168538
A123: MA0000036402 | B123: 3640 | C123: UPLINE EQUILIBRE | D123: UPLINE CAPITAL MANAGEMENT | E123: FCP | F123: DIVERSIFIÉ | G123: - | H123: 75% MBI GLOBAL + 25% MASI 20 | I123: QUOTIDIENNE | J123: FNPP | K123: MIXTE | L123: 0 | M123: 0 | N123: 0.02 | O123: BCP | P123: UPLINE CAPITAL MANAGEMENT | Q123: 5.7343279e+08 | R123: 125.57 | S123: 0.013412 | T123: - | U123: 0.006654 | V123: 0.036227 | W123: 0.029853 | X123: 0.013968 | Y123: -0.039624 | Z123: -0.070169 | AA123: -0.042015 | AB123: -0.078932
A124: MA0000036436 | B124: 3643 | C124: EMERGENCE CAPITAL | D124: VALORIS MANAGEMENT | E124: FCP | F124: OMLT | G124: [1,1 5,1[ | H124: MBI GLOBAL | I124: HEBDOMADAIRE | J124: FGP | K124: CAPITALISANT | L124: 0.03 | M124: 0.015 | N124: 0.005 | O124: BANK OF AFRICA | P124: VALORIS MANAGEMENT | Q124: 2.7334802e+08 | R124: 1799.77 | S124: 0.005351 | T124: - | U124: 0.000873 | V124: 0.002568 | W124: 0.004807 | X124: 0.004129 | Y124: 0.005615 | Z124: 0.065571 | AA124: 0.129105 | AB124: 0.110997
A125: MA0000036444 | B125: 3644 | C125: AL IJTIMAI PATRIMOINE | D125: VALORIS MANAGEMENT | E125: FCP | F125: OMLT | G125: [1,1 7,1[ | H125: MBI GLOBAL | I125: HEBDOMADAIRE | J125: FNPP | K125: CAPITALISANT | L125: 0.03 | M125: 0.015 | N125: 0.008 | O125: CDG | P125: VALORIS MANAGEMENT | Q125: 5.0380953e+09 | R125: 213795.68 | S125: 0.002191 | T125: - | U125: 0.001744 | V125: 0.006867 | W125: 0.007323 | X125: 0.002058 | Y125: -0.007078 | Z125: 0.101811 | AA125: 0.214506 | AB125: 0.136983
A126: MA0000036485 | B126: 3648 | C126: CAT ACTIONS | D126: CIH CAPITAL MANAGEMENT | E126: FCP | F126: ACTIONS | G126: - | H126: MASI RN | I126: HEBDOMADAIRE | J126: FNPP | K126: DISTRIBUANT | L126: 0 | M126: 0 | N126: 0.02 | O126: BMCI | P126: CIH CAPITAL MANAGEMENT | Q126: 2.9373739e+08 | R126: 513526.9 | S126: 0.025974 | T126: - | U126: 0.015267 | V126: 0.079545 | W126: 0.064483 | X126: 0.024318 | Y126: -0.06851 | Z126: 0.369246 | AA126: 0.578165 | AB126: 0.576016
A127: MA0000036493 | B127: 3649 | C127: FCP CAPITAL MAGHREB | D127: BMCE CAPITAL GESTION | E127: FCP | F127: ACTIONS | G127: - | H127: MASI | I127: QUOTIDIENNE | J127: FGP | K127: CAPITALISANT | L127: 0.02 | M127: 0.02 | N127: 0.02 | O127: BANK OF AFRICA | P127: BMCE CAPITAL GESTION | Q127: 1.5288164e+09 | R127: 1825.43 | S127: 0.026578 | T127: - | U127: 0.014584 | V127: 0.079134 | W127: 0.061562 | X127: 0.028504 | Y127: -0.084323 | Z127: 0.412882 | AA127: 0.728021 | AB127: 0.661823
A128: MA0000036501 | B128: 3650 | C128: FCP CAPITAL MULTI-GESTION | D128: BMCE CAPITAL GESTION | E128: FCP | F128: DIVERSIFIÉ | G128: - | H128: 80% MBI GLOBAL + 20% MASI | I128: QUOTIDIENNE | J128: FGP | K128: CAPITALISANT | L128: 0.02 | M128: 0.02 | N128: 0.02 | O128: BANK OF AFRICA | P128: BMCE CAPITAL GESTION | Q128: 1.758446e+09 | R128: 547.39 | S128: -0.010735 | T128: - | U128: 0.004607 | V128: 0.02617 | W128: 0.017605 | X128: -0.007632 | Y128: -0.056501 | Z128: 0.148941 | AA128: 0.270135 | AB128: 0.17774
A129: MA0000036519 | B129: 3651 | C129: FCP AL IJTIMAI SECURITE | D129: BMCE CAPITAL GESTION | E129: FCP | F129: OMLT | G129: [1,1 7[ | H129: MBI GLOBAL | I129: HEBDOMADAIRE | J129: FNPP | K129: CAPITALISANT | L129: 0.03 | M129: 0.015 | N129: 0.02 | O129: BANK OF AFRICA | P129: BMCE CAPITAL GESTION | Q129: 3.0215812e+09 | R129: 225339.78 | S129: -0.002127 | T129: - | U129: 0.001795 | V129: 0.007851 | W129: 0.006543 | X129: -0.002662 | Y129: -0.015547 | Z129: 0.098135 | AA129: 0.209569 | AB129: 0.151806
A130: MA0000036527 | B130: 3652 | C130: AL IJTIMAI INMAA | D130: WAFA GESTION | E130: FCP | F130: OMLT | G130: ]1,1 7] | H130: MBI GLOBAL | I130: HEBDOMADAIRE | J130: FNPP | K130: CAPITALISANT | L130: 0.03 | M130: 0.03 | N130: 0.02 | O130: ATTIJARIWAFA BANK | P130: WAFA GESTION | Q130: 5.2394273e+09 | R130: 218664.8 | S130: 0.006991 | T130: - | U130: 0.001891 | V130: 0.007301 | W130: 0.008371 | X130: 0.006849 | Y130: 0.00149 | Z130: 0.112582 | AA130: 0.228475 | AB130: 0.148351
A131: MA0000036535 | B131: 3653 | C131: AL IJTIMAI SOLIDARITE | D131: CFG GESTION | E131: FCP | F131: OMLT | G131: [1,1 7[ | H131: MBI GLOBAL | I131: HEBDOMADAIRE | J131: FNPP | K131: CAPITALISANT | L131: 0 | M131: 0 | N131: 0.02 | O131: CDG | P131: CFG GESTION | Q131: 3.8527281e+09 | R131: 219829.29 | S131: -0.00249 | T131: - | U131: 0.001705 | V131: 0.006957 | W131: 0.005265 | X131: -0.001771 | Y131: -0.0127 | Z131: 0.098913 | AA131: 0.211396 | AB131: 0.129536
... A324: MA0000039034 | B324: 3903 | C324: FH2 ACTIONS | D324: BMCE CAPITAL GESTION | E324: FCP | F324: ACTIONS | G324: - | H324: MASI | I324: QUOTIDIENNE | J324: FNPP | K324: MIXTE | L324: 0 | M324: 0 | N324: 0.02 | O324: BANK OF AFRICA | P324: BMCE CAPITAL GESTION | Q324: 1.4651532e+09 | R324: 1835.32 | S324: 0.033651 | T324: - | U324: 0.014634 | V324: 0.079511 | W324: 0.062082 | X324: 0.030754 | Y324: -0.074674 | Z324: 0.440257 | AA324: 0.767961 | AB324: 0.736233
A325: MA0000039059 | B325: 3905 | C325: WG VALEURS | D325: WAFA GESTION | E325: FCP | F325: ACTIONS | G325: - | H325: MASI RB | I325: QUOTIDIENNE | J325: FGP | K325: MIXTE | L325: 0 | M325: 0 | N325: 0.01 | O325: ATTIJARIWAFA BANK | P325: WAFA GESTION | Q325: 2.1831003e+08 | R325: 1640.63 | S325: 0.125732 | T325: - | U325: 0.015524 | V325: 0.081546 | W325: 0.075936 | X325: 0.096648 | Y325: 0.060195 | Z325: 0.499744 | AA325: 0.724438 | AB325: -
A326: MA0000039067 | B326: 3906 | C326: WG TAYSSIR | D326: WAFA GESTION | E326: FCP | F326: ACTIONS | G326: - | H326: MASI RB | I326: HEBDOMADAIRE | J326: FGP | K326: CAPITALISANT | L326: 0 | M326: 0 | N326: 0.01 | O326: ATTIJARIWAFA BANK | P326: WAFA GESTION | Q326: 2.1238839e+08 | R326: 1537.06 | S326: 0.112771 | T326: - | U326: 0.015345 | V326: 0.082795 | W326: 0.064807 | X326: 0.088292 | Y326: 0.017806 | Z326: 0.492567 | AA326: 0.681409 | AB326: -
A327: MA0000039075 | B327: 3907 | C327: FCP OBLIG OPPORTUNITES | D327: IRG ASSET MANAGEMENT | E327: FCP | F327: OMLT | G327: ]1,1 5,1] | H327: MBI MT | I327: QUOTIDIENNE | J327: FGP | K327: CAPITALISANT | L327: 0.03 | M327: 0.015 | N327: 0.02 | O327: CDG | P327: IRG ASSET MANAGEMENT | Q327: 4.4430428e+08 | R327: 104.87 | S327: -0.001618 | T327: - | U327: 0.001911 | V327: 0.007494 | W327: 0.006237 | X327: 0.001911 | Y327: -0.009165 | Z327: 0.052912 | AA327: 0.108211 | AB327: -
A328: MA0000039083 | B328: 3908 | C328: FCP OBLIG LONG TERM | D328: IRG ASSET MANAGEMENT | E328: FCP | F328: OMLT | G328: ]4 8] | H328: 80% MBI MLT+20% MBI LT | I328: HEBDOMADAIRE | J328: FGP | K328: CAPITALISANT | L328: 0.03 | M328: 0.015 | N328: 0.02 | O328: ATTIJARIWAFA BANK | P328: IRG ASSET MANAGEMENT | Q328: 1.2845306e+08 | R328: 113.65 | S328: -0.01234 | T328: - | U328: 0.000616 | V328: 0.00141 | W328: -0.002458 | X328: -0.008982 | Y328: -0.018312 | Z328: 0.057504 | AA328: 0.31707 | AB328: -
A329: MA0000039091 | B329: 3909 | C329: CAPITAL TRUST EQUITY | D329: CAPITAL TRUST GESTION | E329: FCP | F329: ACTIONS | G329: - | H329: MASI | I329: QUOTIDIENNE | J329: FGP | K329: CAPITALISANT | L329: 0.03 | M329: 0.015 | N329: 0.02 | O329: BCP | P329: CAPITAL TRUST GESTION | Q329: 9.3208705e+08 | R329: 1482.37 | S329: -0.01695 | T329: - | U329: 0.014384 | V329: 0.074586 | W329: 0.057137 | X329: -0.013975 | Y329: -0.129119 | Z329: 0.2998 | AA329: 0.602701 | AB329: -
A330: MA0000039109 | B330: 3910 | C330: UPLINE PROTECTION DYNAMIQUE | D330: UPLINE CAPITAL MANAGEMENT | E330: FCP | F330: DIVERSIFIÉ | G330: - | H330: - | I330: HEBDOMADAIRE | J330: FGP | K330: CAPITALISANT | L330: 0.002 | M330: 0.002 | N330: 0.02 | O330: BCP | P330: BANQUE POPULAIRE | Q330: 5.7192721e+08 | R330: 1180.12 | S330: 0.011364 | T330: - | U330: 0.004785 | V330: 0.022732 | W330: 0.018047 | X330: 0.006525 | Y330: -0.010664 | Z330: 0.119255 | AA330: 0.184241 | AB330: -
A331: MA0000039117 | B331: 3911 | C331: CAM OBLIBANQUES | D331: MAROGEST | E331: FCP | F331: OCT | G331: ]0,5 1,1] | H331: 85% MBI CT + 15% MBI MT | I331: QUOTIDIENNE | J331: FGP | K331: CAPITALISANT | L331: 0.03 | M331: 0.015 | N331: 0.02 | O331: CIH BANK | P331: CAM; MSIN; CIH; MAROGEST | Q331: 2.0854469e+09 | R331: 1147 | S331: 0.018406 | T331: - | U331: 0.000742 | V331: 0.002298 | W331: 0.007121 | X331: 0.01421 | Y331: 0.02718 | Z331: 0.065134 | AA331: 0.109102 | AB331: -
A332: MA0000039125 | B332: 3912 | C332: CAM OBLIRENDEMENT | D332: MAROGEST | E332: FCP | F332: OMLT | G332: ]1,1 5,1] | H332: 100% MBI MT | I332: QUOTIDIENNE | J332: FGP | K332: CAPITALISANT | L332: 0.03 | M332: 0.015 | N332: 0.02 | O332: CIH BANK | P332: CAM; MSIN; CIH; MAROGEST | Q332: 4.0199368e+08 | R332: 1153.09 | S332: -0.003896 | T332: - | U332: 0.000712 | V332: 0.004758 | W332: 0.003446 | X332: -0.00467 | Y332: -0.008657 | Z332: 0.073931 | AA332: 0.140059 | AB332: -
A333: MA0000039133 | B333: 3913 | C333: CKG ISR SELECTION | D333: CDG CAPITAL GESTION | E333: FCP | F333: ACTIONS | G333: - | H333: ESG 10 | I333: HEBDOMADAIRE | J333: FGP | K333: CAPITALISANT | L333: 0.03 | M333: 0.015 | N333: 0.02 | O333: CDG CAPITAL | P333: CDG CAPITAL GESTION | Q333: 2.5282893e+08 | R333: 973.26 | S333: 0.029382 | T333: - | U333: 0.015028 | V333: 0.068061 | W333: 0.061121 | X333: 0.027567 | Y333: -0.070297 | Z333: 0.034547 | AA333: 0.115945 | AB333: -
A334: MA0000039141 | B334: 3914 | C334: AD SELECT BANQUES | D334: AD CAPITAL ASSET MANAGEMENT | E334: FCP | F334: OCT | G334: ]0,5 1,1] | H334: MBI CT | I334: QUOTIDIENNE | J334: FGP | K334: CAPITALISANT | L334: 0.03 | M334: 0.03 | N334: 0.02 | O334: CFG BANK | P334: AD CAPITAL ASSET MANAGEMENT; AD CAPITAL GROUP | Q334: 2.0796049e+09 | R334: 1153.03 | S334: 0.019469 | T334: - | U334: 0.000755 | V334: 0.002478 | W334: 0.007946 | X334: 0.015268 | Y334: 0.028573 | Z334: 0.068986 | AA334: 0.115656 | AB334: -
A335: MA0000039158 | B335: 3915 | C335: AD COMPACT OBLIGATAIRE | D335: AD CAPITAL ASSET MANAGEMENT | E335: FCP | F335: OMLT | G335: [3,5 7,5[ | H335: MBI GLOBAL | I335: HEBDOMADAIRE | J335: FGP | K335: CAPITALISANT | L335: 0.03 | M335: 0.03 | N335: 0.02 | O335: CFG BANK | P335: AD CAPITAL ASSET MANAGEMENT; AD CAPITAL GROUP | Q335: 3.2975872e+09 | R335: 1167.28 | S335: -0.004163 | T335: - | U335: 0.001708 | V335: 0.0075 | W335: 0.005141 | X335: -0.005148 | Y335: -0.016506 | Z335: 0.103853 | AA335: 0.192233 | AB335: -
A336: MA0000039166 | B336: 3916 | C336: CAPITAL TRUST PATRIMOINE | D336: CAPITAL TRUST GESTION | E336: FCP | F336: DIVERSIFIÉ | G336: - | H336: 25% MASI + 30% MBI GLOBAL + 45% MBI MLT | I336: QUOTIDIENNE | J336: FGP | K336: CAPITALISANT | L336: 0.03 | M336: 0.015 | N336: 0.02 | O336: BCP | P336: CAPITAL TRUST GESTION | Q336: 7.3176837e+08 | R336: 1366.21 | S336: -0.011168 | T336: - | U336: 0.008459 | V336: 0.041954 | W336: 0.023179 | X336: -0.009533 | Y336: -0.069136 | Z336: 0.277548 | AA336: 0.409248 | AB336: -
... A340: MA0000039208 | B340: 3920 | C340: TWIN OPPORTUNITY | D340: TWIN CAPITAL GESTION | E340: FCP | F340: DIVERSIFIÉ | G340: - | H340: 30% MASI + 70% MBI | I340: HEBDOMADAIRE | J340: FGP | K340: CAPITALISANT | L340: 0.015 | M340: 0.015 | N340: 0.01 | O340: CFG BANK | P340: TWIN CAPITAL GESTION; CFG BANK | Q340: 2.9839289e+08 | R340: 1208.85 | S340: -0.025773 | T340: - | U340: 0.006461 | V340: 0.036687 | W340: 0.018579 | X340: -0.018217 | Y340: -0.103878 | Z340: 0.134006 | AA340: 0.196668 | AB340: -
A341: MA0000039216 | B341: 3921 | C341: FCP CAPITAL ISR | D341: BMCE CAPITAL GESTION | E341: FCP | F341: DIVERSIFIÉ | G341: - | H341: 75% MBI GLOBAL + 25% MASI ESG | I341: QUOTIDIENNE | J341: FGP | K341: CAPITALISANT | L341: 0.02 | M341: 0.01 | N341: 0.02 | O341: BANK OF AFRICA | P341: BMCE CAPITAL GESTION | Q341: 8.1443523e+08 | R341: 1474.24 | S341: -0.023048 | T341: - | U341: 0.005408 | V341: 0.021395 | W341: 0.016059 | X341: -0.020217 | Y341: -0.080324 | Z341: 0.122615 | AA341: 0.251381 | AB341: 0.135166
A342: MA0000039224 | B342: 3922 | C342: IRGAM ALLOCATION | D342: IRG ASSET MANAGEMENT | E342: FCP | F342: DIVERSIFIÉ | G342: - | H342: 40 % MASI RB + 60 % MBI GLOBAL | I342: HEBDOMADAIRE | J342: FNPP | K342: MIXTE | L342: 0 | M342: 0 | N342: 0.02 | O342: ATTIJARIWAFA BANK | P342: IRG ASSET MANAGEMENT | Q342: 5.2341982e+08 | R342: 254.88 | S342: 0.027159 | T342: - | U342: 0.010186 | V342: 0.046391 | W342: 0.040327 | X342: 0.021975 | Y342: -0.029543 | Z342: 0.256332 | AA342: 0.447865 | AB342: 0.392806
A343: MA0000039232 | B343: 3923 | C343: CAPITAL RENDEMENT PLUS | D343: BMCE CAPITAL GESTION | E343: FCP | F343: OMLT | G343: ]1,1 5] | H343: MBI GLOBAL | I343: QUOTIDIENNE | J343: FGP | K343: MIXTE | L343: 0.02 | M343: 0.01 | N343: 0.02 | O343: BANK OF AFRICA | P343: BMCE CAPITAL GESTION; BANK OF AFRICA | Q343: 1131108.6 | R343: 1131.1 | S343: 0.006603 | T343: - | U343: 0.000876 | V343: 0.002748 | W343: 0.004413 | X343: 0.005154 | Y343: 0.007652 | Z343: 0.051042 | AA343: 0.10789 | AB343: -
A344: MA0000039240 | B344: 3924 | C344: AFG SECUR RENDEMENT | D344: AFG ASSET MANAGEMENT | E344: FCP | F344: OMLT | G344: ]1,1 7] | H344: MBI Global | I344: HEBDOMADAIRE | J344: FNPP | K344: CAPITALISANT | L344: 0 | M344: 0 | N344: 0.02 | O344: CDG | P344: AFG ASSET MANAGEMENT | Q344: 2.8622713e+09 | R344: 1260.13 | S344: 0.001311 | T344: - | U344: 0.002251 | V344: 0.009744 | W344: 0.007999 | X344: 0.00058 | Y344: -0.012461 | Z344: 0.106309 | AA344: 0.217823 | AB344: -
A345: MA0000039281 | B345: 3928 | C345: BMCI PREMIUM SHORT BOND DIST | D345: CIH CAPITAL MANAGEMENT | E345: FCP | F345: OCT | G345: ]0,5 1,1] | H345: MBI CT | I345: QUOTIDIENNE | J345: FGP | K345: DISTRIBUANT | L345: 0 | M345: 0 | N345: 0.02 | O345: BMCI | P345: CIH CAPITAL MANAGEMENT | Q345: 4768209.6 | R345: 134.2 | S345: 0.013442 | T345: - | U345: 0.000596 | V345: 0.001717 | W345: 0.005093 | X345: 0.010847 | Y345: 0.018828 | Z345: 0.047374 | AA345: 0.091519 | AB345: 0.13289
A346: MA0000039299 | B346: 3929 | C346: WINEO SECUR RENDEMENT | D346: WINEO GESTION | E346: FCP | F346: OMLT | G346: ]1,1 7] | H346: MBI GLOBAL | I346: HEBDOMADAIRE | J346: FNPP | K346: CAPITALISANT | L346: 0 | M346: 0 | N346: 0.02 | O346: CDG | P346: WINEO GESTION | Q346: 2.1944399e+09 | R346: 1261.12 | S346: 0.008589 | T346: - | U346: 0.002138 | V346: 0.008581 | W346: 0.008864 | X346: 0.005037 | Y346: -0.000483 | Z346: 0.110131 | AA346: 0.213666 | AB346: -
A347: MA0000039315 | B347: 3931 | C347: CFG OPPORTUNITÉS | D347: CFG GESTION | E347: FCP | F347: DIVERSIFIÉ | G347: - | H347: 70% MBI GLOBAL + 30% MASI | I347: QUOTIDIENNE | J347: FGP | K347: MIXTE | L347: 0.03 | M347: 0.015 | N347: 0.02 | O347: CFG BANK | P347: CFG GESTION; CFG BANK | Q347: 97614865 | R347: 1247.62 | S347: 0.036539 | T347: - | U347: 0.000778 | V347: 0.006299 | W347: 0.011906 | X347: 0.011308 | Y347: -0.018295 | Z347: 0.147648 | AA347: 0.207881 | AB347: -
A348: MA0000039323 | B348: 3932 | C348: CFG Diversifié | D348: CFG GESTION | E348: FCP | F348: DIVERSIFIÉ | G348: - | H348: 80% MBI GLOBAL + 20% MASI RN | I348: QUOTIDIENNE | J348: FGP | K348: CAPITALISANT | L348: 0.03 | M348: 0.015 | N348: 0.02 | O348: CFG BANK | P348: CFG GESTION; CFG BANK | Q348: 95494667 | R348: 1230.06 | S348: -0.004226 | T348: - | U348: 0.006909 | V348: 0.037299 | W348: 0.026633 | X348: 0.012345 | Y348: -0.009406 | Z348: 0.102688 | AA348: 0.176596 | AB348: -
A349: MA0000039331 | B349: 3933 | C349: UPLINE CROISSANCE | D349: UPLINE CAPITAL MANAGEMENT | E349: FCP | F349: DIVERSIFIÉ | G349: - | H349: 70% MBI + 30% MASI RB | I349: QUOTIDIENNE | J349: FNPP | K349: MIXTE | L349: 0 | M349: 0 | N349: 0.02 | O349: BCP | P349: UPLINE CAPITAL MANAGEMENT | Q349: 1106488.7 | R349: 1106.49 | S349: -0.005009 | T349: - | U349: 0.004257 | V349: 0.013696 | W349: 0.01262 | X349: 0.001403 | Y349: -0.01392 | Z349: 0.063974 | AA349: 0.091956 | AB349: -
A350: MA0000039349 | B350: 3934 | C350: UPLINE SECURITIES PERFORMANCE | D350: UPLINE CAPITAL MANAGEMENT | E350: FCP | F350: DIVERSIFIÉ | G350: - | H350: 75% MBI + 25% MASI RB | I350: HEBDOMADAIRE | J350: FNPP | K350: MIXTE | L350: 0 | M350: 0 | N350: 0.02 | O350: BCP | P350: UPLINE CAPITAL MANAGEMENT | Q350: 1093605 | R350: 1093.61 | S350: -0.007487 | T350: - | U350: 0.004224 | V350: 0.013578 | W350: 0.012264 | X350: -0.000585 | Y350: -0.01766 | Z350: 0.056791 | AA350: 0.080995 | AB350: -
A351: MA0000039356 | B351: 3935 | C351: FCP EMERGENCE PATRIMOINE | D351: VALORIS MANAGEMENT | E351: FCP | F351: DIVERSIFIÉ | G351: - | H351: 80% MBI GLOBAL + 20% MASI RB | I351: QUOTIDIENNE | J351: FNPP | K351: CAPITALISANT | L351: 0 | M351: 0 | N351: 0.02 | O351: BANK OF AFRICA | P351: VALORIS MANAGEMENT | Q351: 872093.35 | R351: 178.96 | S351: -0.013994 | T351: - | U351: -0.000837 | V351: 0.013134 | W351: 0.01601 | X351: -0.010615 | Y351: -0.051516 | Z351: 0.22157 | AA351: 0.359568 | AB351: 0.351151
A352: MA0000039364 | B352: 3936 | C352: PROFIL FLEXIBLE | D352: WAFA GESTION | E352: FCP | F352: DIVERSIFIÉ | G352: - | H352: 75% MASI + 25% MBI MT | I352: QUOTIDIENNE | J352: FGP | K352: DISTRIBUANT | L352: 0.02 | M352: 0.02 | N352: 0.02 | O352: ATTIJARIWAFA BANK | P352: WAFA GESTION; ATTIJARIWAFA BANK | Q352: 1.0905395e+09 | R352: 1738.67 | S352: 0.099526 | T352: - | U352: 0.010778 | V352: 0.05233 | W352: 0.05034 | X352: 0.088758 | Y352: 0.034904 | Z352: 0.260353 | AA352: 0.338386 | AB352: 0.292682
A353: MA0000039372 | B353: 3937 | C353: AFG T-BOND FUND | D353: AFG ASSET MANAGEMENT | E353: FCP | F353: OMLT | G353: ]1,1 10] | H353: MBI MLT | I353: QUOTIDIENNE | J353: FNPP | K353: MIXTE | L353: 0 | M353: 0 | N353: 0.02 | O353: ATTIJARIWAFA BANK | P353: AFG ASSET MANAGEMENT | Q353: 1.2298496e+09 | R353: 1126.86 | S353: -0.029611 | T353: - | U353: 0.001671 | V353: 0.007267 | W353: 0.002741 | X353: -0.01123 | Y353: -0.038375 | Z353: 0.118995 | AA353: 0.251353 | AB353: -
A354: MA0000039380 | B354: 3938 | C354: ATLAS HARMONIE | D354: ATLAS CAPITAL MANAGEMENT | E354: FCP | F354: OMLT | G354: ]1,1; 8] | H354: MBI GLOBAL | I354: HEBDOMADAIRE | J354: FNPP | K354: CAPITALISANT | L354: 0.03 | M354: 0.03 | N354: 0.02 | O354: CIH BANK | P354: ATLAS CAPITAL MANAGEMENT | Q354: 2.5529986e+09 | R354: 250.32 | S354: 0.00048 | T354: - | U354: 0.001 | V354: 0.003005 | W354: 0.003086 | X354: 0.00112 | Y354: -0.00386 | Z354: 0.087402 | AA354: 0.178753 | AB354: 0.163197
A355: MA0000039398 | B355: 3939 | C355: IRGAM DISTRIEQUILIBRE | D355: IRG ASSET MANAGEMENT | E355: FCP | F355: DIVERSIFIÉ | G355: - | H355: 30% MASI FLOTTANT + 70% MBI GLOBAL | I355: HEBDOMADAIRE | J355: FGP | K355: MIXTE | L355: 0.03 | M355: 0.015 | N355: 0.02 | O355: BCP | P355: IRG ASSET MANAGEMENT | Q355: 1.2380485e+09 | R355: 141.62 | S355: -0.003799 | T355: - | U355: 0.004967 | V355: 0.022379 | W355: 0.014397 | X355: -0.000141 | Y355: -0.034826 | Z355: 0.363698 | AA355: 0.407194 | AB355: -
A356: MA0000039406 | B356: 3940 | C356: IRGAM DISTRIEQUITY | D356: IRG ASSET MANAGEMENT | E356: FCP | F356: ACTIONS | G356: - | H356: MASI | I356: HEBDOMADAIRE | J356: FGP | K356: MIXTE | L356: 0.03 | M356: 0.015 | N356: 0.02 | O356: BCP | P356: IRG ASSET MANAGEMENT | Q356: 1633174.7 | R356: 163.32 | S356: -0.038389 | T356: - | U356: 0.003564 | V356: 0.03015 | W356: 0.032886 | X356: -0.033095 | Y356: -0.078849 | Z356: 0.452121 | AA356: 0.604165 | AB356: -
A357: MA0000039414 | B357: 3941 | C357: FCP EMERGENCE ACTIONS | D357: VALORIS MANAGEMENT | E357: FCP | F357: ACTIONS | G357: - | H357: MASI 20 | I357: QUOTIDIENNE | J357: FGP | K357: CAPITALISANT | L357: 0.03 | M357: 0.015 | N357: 0.02 | O357: ATTIJARIWAFA BANK | P357: VALORIS GROUP;VALORIS MANAGEMENT | Q357: 3.519593e+08 | R357: 1914.08 | S357: 0.018464 | T357: - | U357: 0.014899 | V357: 0.079718 | W357: 0.063993 | X357: 0.023052 | Y357: -0.082711 | Z357: 0.44363 | AA357: 0.820004 | AB357: -
A358: MA0000039422 | B358: 3942 | C358: FCP EMERGENCE PERSPECTIVES | D358: VALORIS MANAGEMENT | E358: FCP | F358: DIVERSIFIÉ | G358: - | H358: 80% MBI GLOBAL + 20% MASI RB | I358: HEBDOMADAIRE | J358: FNPP | K358: MIXTE | L358: 0 | M358: 0 | N358: 0.02 | O358: SAHAM BANK | P358: VALORIS GROUP;VALORIS MANAGEMENT | Q358: 1.8450789e+09 | R358: 1321.13 | S358: 0.01078 | T358: - | U358: 0.011926 | V358: 0.015972 | W358: 0.017052 | X358: 0.005725 | Y358: -0.012372 | Z358: 0.169701 | AA358: 0.30695 | AB358: -
A359: MA0000039430 | B359: 3943 | C359: FCP SANLAM OBLIGATIONS | D359: VALORIS MANAGEMENT | E359: FCP | F359: OMLT | G359: ]1,1 10] | H359: MBI GLOBAL | I359: QUOTIDIENNE | J359: FNPP | K359: MIXTE | L359: 0.03 | M359: 0.015 | N359: 0.02 | O359: BCP | P359: VALORIS MANAGEMENT | Q359: 9.9983518e+08 | R359: 1281.72 | S359: -0.015825 | T359: - | U359: 0.001641 | V359: 0.006842 | W359: 0.005318 | X359: -0.001068 | Y359: -0.01971 | Z359: 0.128541 | AA359: 0.265808 | AB359: -
A360: MA0000039448 | B360: 3944 | C360: AFG GOV BOND FUND | D360: AFG ASSET MANAGEMENT | E360: FCP | F360: OMLT | G360: ]4 8] | H360: MBI GLOBAL | I360: QUOTIDIENNE | J360: FGP | K360: MIXTE | L360: 0.03 | M360: 0.03 | N360: 0.02 | O360: ATTIJARIWAFA BANK | P360: AFG ASSET MANAGEMENT | Q360: 2.5895621e+09 | R360: 1223.36 | S360: -0.010122 | T360: - | U360: 0.001326 | V360: 0.004566 | W360: 0.000663 | X360: -0.009537 | Y360: -0.02639 | Z360: 0.08452 | AA360: 0.194093 | AB360: -
A361: MA0000039455 | B361: 3945 | C361: AFG FLEXIBLE FUND | D361: AFG ASSET MANAGEMENT | E361: FCP | F361: DIVERSIFIÉ | G361: - | H361: 75% MBI GLOBAL + 25% MASI RB | I361: QUOTIDIENNE | J361: FNPP | K361: MIXTE | L361: 0.03 | M361: 0.03 | N361: 0.02 | O361: BCP | P361: AFG ASSET MANAGEMENT | Q361: 9.2658614e+08 | R361: 1353.54 | S361: -0.002432 | T361: - | U361: 0.005714 | V361: 0.029629 | W361: 0.02137 | X361: 0.006806 | Y361: -0.038175 | Z361: 0.198726 | AA361: 0.391863 | AB361: -
A362: MA0000039463 | B362: 3946 | C362: ATLAS LIQUIDITE | D362: ATLAS CAPITAL MANAGEMENT | E362: FCP | F362: OCT | G362: 0,5 ; 1,1] | H362: MBI CT | I362: QUOTIDIENNE | J362: FGP | K362: CAPITALISANT | L362: 0.03 | M362: 0.03 | N362: 0.02 | O362: BANK OF AFRICA | P362: ATLAS CAPITAL MANAGEMENT | Q362: 53375112 | R362: 148.26 | S362: 0.01764 | T362: - | U362: 0.000742 | V362: 0.002163 | W362: 0.007201 | X362: 0.013882 | Y362: 0.025595 | Z362: 0.059908 | AA362: 0.075049 | AB362: 0.070237
A363: MA0000039471 | B363: 3947 | C363: AZ TAWFIR | D363: WAFA GESTION | E363: FCP | F363: OMLT | G363: ]1,1 13] | H363: MBI MLT | I363: QUOTIDIENNE | J363: FNPP | K363: MIXTE | L363: 0.03 | M363: 0.015 | N363: 0.02 | O363: BCP | P363: WAFA GESTION | Q363: 3.8227268e+08 | R363: 842010.3 | S363: -0.014675 | T363: - | U363: 0.001089 | V363: 0.003467 | W363: -0.001939 | X363: -0.011094 | Y363: -0.023208 | Z363: 0.0807 | AA363: 0.239545 | AB363: 0.116438
A364: MA0000039489 | B364: 3948 | C364: UNIVERS DIVERSIFIE | D364: WAFA GESTION | E364: FCP | F364: DIVERSIFIÉ | G364: - | H364: 30% MASI RB + 70% MBI MLT | I364: HEBDOMADAIRE | J364: FNPP | K364: MIXTE | L364: 0 | M364: 0 | N364: 0.02 | O364: ATTIJARIWAFA BANK | P364: WAFA GESTION | Q364: 2.1754177e+08 | R364: 2038.03 | S364: 0.025553 | T364: - | U364: 0.007041 | V364: 0.041538 | W364: 0.036664 | X364: 0.024146 | Y364: -0.010329 | Z364: 0.251031 | AA364: 0.414886 | AB364: 0.37795
A365: MA0000039497 | B365: 3949 | C365: CAPITAL IMTIYAZ GARANTI | D365: BMCE CAPITAL GESTION | E365: FCP | F365: CONTRACTUEL | G365: - | H365: MONIA | I365: QUOTIDIENNE | J365: FGP | K365: CAPITALISANT | L365: 0.01 | M365: 0.01 | N365: 0.02 | O365: BANK OF AFRICA | P365: BMCE CAPITAL GESTION | Q365: 1.8966625e+09 | R365: 1060.75 | S365: 0.013656 | T365: - | U365: 0.000387 | V365: 0.001738 | W365: 0.005298 | X365: 0.010459 | Y365: 0.020914 | Z365: 0.044354 | AA365: - | AB365: -
A366: MA0000039505 | B366: 3950 | C366: GENERATION PERFORMANCE | D366: UPLINE CAPITAL MANAGEMENT | E366: SICAV | F366: OMLT | G366: ]1,1 12] | H366: MBI GLOBAL + 50 pbs | I366: HEBDOMADAIRE | J366: FNPP | K366: CAPITALISANT | L366: 0 | M366: 0 | N366: 0.02 | O366: BCP | P366: UPLINE CAPITAL MANAGEMENT | Q366: 4.7652532e+08 | R366: 1106.91 | S366: 0.009347 | T366: - | U366: 0.000823 | V366: 0.002699 | W366: 0.005761 | X366: 0.006017 | Y366: 0.01108 | Z366: 0.082404 | AA366: - | AB366: -
A367: MA0000039513 | B367: 3951 | C367: FCP MAROGEST BONDS | D367: MAROGEST | E367: FCP | F367: OMLT | G367: ]1,1 8,1] | H367: 100% MBI GLOBAL | I367: QUOTIDIENNE | J367: FNPP | K367: CAPITALISANT | L367: 0 | M367: 0 | N367: 0 | O367: CIH BANK | P367: MAROGEST | Q367: 7.6530029e+08 | R367: 1086.6 | S367: -0.015083 | T367: - | U367: 0.00082 | V367: 0.006363 | W367: 0.001687 | X367: -0.012173 | Y367: -0.025803 | Z367: 0.071323 | AA367: - | AB367: -
A368: MA0000039521 | B368: 3952 | C368: MAROGEST SECUR RENDEMENT | D368: MAROGEST | E368: FCP | F368: OMLT | G368: ]1,1 7] | H368: 100% MBI GLOBAL | I368: HEBDOMADAIRE | J368: FNPP | K368: CAPITALISANT | L368: 0 | M368: 0 | N368: 0 | O368: CDG | P368: MAROGEST | Q368: 5.4516641e+08 | R368: 1133.69 | S368: -0.000908 | T368: - | U368: 0.001643 | V368: 0.007214 | W368: 0.007169 | X368: -1.8e-05 | Y368: -0.008449 | Z368: 0.101012 | AA368: - | AB368: -
A369: MA0000039539 | B369: 3953 | C369: ATTIJARI PRIVATE FUND | D369: WAFA GESTION | E369: FCP | F369: DIVERSIFIÉ | G369: - | H369: 50% MASI RB + 50% MBI GLOBAL | I369: HEBDOMADAIRE | J369: FGP | K369: MIXTE | L369: 0.02 | M369: 0.02 | N369: 0.02 | O369: ATTIJARIWAFA BANK | P369: WAFA GESTION | Q369: 8.6083055e+08 | R369: 1157030.3 | S369: 0.079903 | T369: - | U369: 0.017035 | V369: 0.063077 | W369: 0.052929 | X369: 0.05997 | Y369: 0.063393 | Z369: 0.138924 | AA369: - | AB369: -
A370: MA0000039547 | B370: 3954 | C370: FCP ALPHA BONDS | D370: RED MED ASSET MANAGEMENT | E370: FCP | F370: OMLT | G370: ]1,1 10] | H370: MBI GLOBAL | I370: QUOTIDIENNE | J370: FNPP | K370: CAPITALISANT | L370: 0 | M370: 0 | N370: 0.02 | O370: BCP | P370: RED MED ASSET MANAGEMENT | Q370: 2.323385e+09 | R370: 1208.77 | S370: -0.000108 | T370: - | U370: 0.000961 | V370: 0.00332 | W370: 0.002746 | X370: 0.000753 | Y370: -0.002476 | Z370: 0.087317 | AA370: 0.174076 | AB370: -
A371: MA0000039554 | B371: 3955 | C371: AD HARMONIE DIVERSIFIÉ | D371: AD CAPITAL ASSET MANAGEMENT | E371: FCP | F371: DIVERSIFIÉ | G371: - | H371: 50% MASI + 50% MBI MLT | I371: HEBDOMADAIRE | J371: FGP | K371: DISTRIBUANT | L371: 0.03 | M371: 0.03 | N371: 0.02 | O371: ATTIJARIWAFA BANK | P371: AD CAPITAL ASSET MANAGEMENT; AD CAPITAL GROUP | Q371: 5.0266534e+08 | R371: 1114.4 | S371: -0.049536 | T371: - | U371: 0.002248 | V371: 0.020335 | W371: 0.011564 | X371: -0.051171 | Y371: -0.097637 | Z371: - | AA371: - | AB371: -
A372: MA0000039570 | B372: 3957 | C372: AFG ACTIVE BOND FUND | D372: AFG ASSET MANAGEMENT | E372: FCP | F372: OMLT | G372: ]4 8] | H372: 95% MBI GLOBAL + 5% MASI | I372: QUOTIDIENNE | J372: FGP | K372: MIXTE | L372: 0.03 | M372: 0.03 | N372: 0.02 | O372: BANQUE CENTRALE POPULAIRE | P372: AFG ASSET MANAGEMENT | Q372: 1.164502e+09 | R372: 1100.19 | S372: -0.011261 | T372: - | U372: 0.001812 | V372: 0.00835 | W372: 0.002232 | X372: -0.009436 | Y372: -0.023971 | Z372: - | AA372: - | AB372: -
A373: MA0000039596 | B373: 3959 | C373: FH2 OBLIGATAIRE DYNAMIQUE II | D373: BMCE CAPITAL GESTION | E373: FCP | F373: OMLT | G373: ]1,1 7,1] | H373: MBI Global | I373: HEBDOMADAIRE | J373: FNPP | K373: MIXTE | L373: 0 | M373: 0 | N373: 0.02 | O373: BANK OF AFRICA | P373: BMCE CAPITAL GESTION | Q373: 2.1195234e+09 | R373: 1229.85 | S373: 0.000456 | T373: - | U373: 0.001107 | V373: 0.003018 | W373: 0.000513 | X373: -0.002547 | Y373: -0.001486 | Z373: - | AA373: - | AB373: -
A374: MA0000039604 | B374: 3960 | C374: FCP EMERGENCE OPTIMUM | D374: VALORIS MANAGEMENT | E374: FCP | F374: DIVERSIFIÉ | G374: - | H374: 60% MBI + 40% MASI | I374: QUOTIDIENNE | J374: FGP | K374: MIXTE | L374: 0.03 | M374: 0.015 | N374: 0.02 | O374: CREDIT DU MAROC | P374: VALORIS MANAGEMENT | Q374: 1.6052438e+09 | R374: 1193.13 | S374: -0.008056 | T374: - | U374: 0.006428 | V374: 0.03529 | W374: 0.025775 | X374: -0.005965 | Y374: -0.053229 | Z374: - | AA374: - | AB374: -
A375: MA0000039612 | B375: 3961 | C375: CCM SECUR RENDEMENT | D375: CIH CAPITAL MANAGEMENT | E375: FCP | F375: OMLT | G375: [1,1 7] | H375: MBI GLOBAL | I375: HEBDOMADAIRE | J375: FNPP | K375: CAPITALISANT | L375: 0 | M375: 0 | N375: 0.02 | O375: CDG | P375: CIH CAPITAL MANAGEMENT | Q375: 1.0289063e+09 | R375: 1133.12 | S375: 0.001812 | T375: - | U375: 0.001848 | V375: 0.007451 | W375: 0.006323 | X375: 0.002131 | Y375: -0.007889 | Z375: - | AA375: - | AB375: -
A376: MA0000039620 | B376: 3962 | C376: FCP FH2 OBLIGATAIRE DP | D376: VALORIS MANAGEMENT | E376: FCP | F376: OMLT | G376: [1,1 5] | H376: 90% MBI MT + 10% MBI MLT + 50 pbs | I376: QUOTIDIENNE | J376: FNPP | K376: MIXTE | L376: 0 | M376: 0 | N376: 0.02 | O376: CDM | P376: VALORIS MANAGEMENT | Q376: 8.8720597e+08 | R376: 1076.68 | S376: 0.016177 | T376: - | U376: 0.001079 | V376: 0.003926 | W376: 0.009309 | X376: 0.013155 | Y376: 0.020801 | Z376: - | AA376: - | AB376: -
A377: MA0000039638 | B377: 3963 | C377: FCP AFRICAPITAL RENDEMENT | D377: AFRICAPITAL MANAGEMENT | E377: FCP | F377: OMLT | G377: [2 6] | H377: MBI GLOBAL | I377: QUOTIDIENNE | J377: FGP | K377: CAPITALISANT | L377: 0.03 | M377: 0.03 | N377: 0.02 | O377: BCP | P377: AFRICAPITAL MANAGEMENT | Q377: 1.0584658e+09 | R377: 1032.84 | S377: -0.004894 | T377: - | U377: 0.002349 | V377: 0.009658 | W377: 0.005873 | X377: -0.003685 | Y377: -0.018082 | Z377: - | AA377: - | AB377: -
A378: MA0000039653 | B378: 3965 | C378: FCP ALPHA OBLIGATAIRE | D378: RED MED ASSET MANAGEMENT | E378: FCP | F378: OMLT | G378: ]1,1 10] | H378: MBI GLOBAL | I378: QUOTIDIENNE | J378: FNPP | K378: CAPITALISANT | L378: 0 | M378: 0 | N378: 0.02 | O378: BCP | P378: RED MED ASSET MANAGEMENT;RED MED SECURITIES | Q378: 1123092.4 | R378: 1123.09 | S378: 0.000472 | T378: - | U378: 0.001034 | V378: 0.002822 | W378: 0.003754 | X378: -0.001245 | Y378: -0.004379 | Z378: 0.080185 | AA378: 0.148577 | AB378: -
A379: MA0000039661 | B379: 3966 | C379: FCP EMERGENCE HARMONY FUND | D379: VALORIS MANAGEMENT | E379: FCP | F379: OMLT | G379: [1,1 10] | H379: MBI MT | I379: QUOTIDIENNE | J379: FNPP | K379: MIXTE | L379: 0 | M379: 0 | N379: 0.02 | O379: CIH BANK | P379: VALORIS MANAGEMENT | Q379: 17650798 | R379: 1356.91 | S379: 0.013792 | T379: - | U379: 0.001011 | V379: 0.002505 | W379: 0.00611 | X379: 0.012204 | Y379: 0.011834 | Z379: 0.10685 | AA379: 0.235037 | AB379: 0.361334
A380: MA0000039679 | B380: 3967 | C380: FCP OPTIMA EQUILIBRE | D380: ALPHAVEST ASSET MANAGEMENT | E380: FCP | F380: DIVERSIFIÉ | G380: - | H380: 60% MBI GLOBAL + 40% MASI | I380: QUOTIDIENNE | J380: FGP | K380: CAPITALISANT | L380: 0.03 | M380: 0.015 | N380: 0.02 | O380: BANQUE CENTRALE POPULAIRE | P380: ALPHAVEST ASSET MANAGEMENT | Q380: 265953800 | R380: 993.06 | S380: -0.008823 | T380: - | U380: 0.007589 | V380: 0.037539 | W380: 0.023636 | X380: -0.009041 | Y380: -0.072522 | Z380: - | AA380: - | AB380: -
A381: MA0000039687 | B381: 3968 | C381: FCP OPTIMA MONETAIRE | D381: ALPHAVEST ASSET MANAGEMENT | E381: FCP | F381: MONÉTAIRE | G381: [0 0,5] | H381: MONIA | I381: QUOTIDIENNE | J381: FGP | K381: CAPITALISANT | L381: 0.03 | M381: 0.015 | N381: 0.02 | O381: BANQUE CENTRALE POPULAIRE | P381: ALPHAVEST ASSET MANAGEMENT | Q381: 9.5307758e+08 | R381: 1030.75 | S381: 0.017201 | T381: - | U381: 0.000573 | V381: 0.002042 | W381: 0.006602 | X381: 0.013411 | Y381: 0.025581 | Z381: - | AA381: - | AB381: -
A382: MA0000039695 | B382: 3969 | C382: FCP OPTIMA OBLIGATAIRE | D382: ALPHAVEST ASSET MANAGEMENT | E382: FCP | F382: OMLT | G382: [4 8] | H382: MBI GLOBAL | I382: QUOTIDIENNE | J382: FGP | K382: CAPITALISANT | L382: 0.03 | M382: 0.015 | N382: 0.02 | O382: BANQUE CENTRALE POPULAIRE | P382: ALPHAVEST ASSET MANAGEMENT | Q382: 5.2560939e+08 | R382: 1010.56 | S382: -0.005217 | T382: - | U382: 0.001377 | V382: 0.006394 | W382: 0.004773 | X382: -0.006127 | Y382: -0.008273 | Z382: - | AA382: - | AB382: -
A383: MA0000039703 | B383: 3970 | C383: FCP OPTIMA SOUVERAIN | D383: ALPHAVEST ASSET MANAGEMENT | E383: FCP | F383: OMLT | G383: [4 8] | H383: MBI GLOBAL | I383: QUOTIDIENNE | J383: FGP | K383: CAPITALISANT | L383: 0.03 | M383: 0.015 | N383: 0.02 | O383: BANK OF AFRICA | P383: ALPHAVEST ASSET MANAGEMENT | Q383: 2.8892556e+08 | R383: 1075.41 | S383: 0.059215 | T383: - | U383: 0.000903 | V383: 0.002984 | W383: -1.9e-05 | X383: -0.004821 | Y383: 0.057766 | Z383: - | AA383: - | AB383: -
A384: MA0000039711 | B384: 3971 | C384: FCP OPTIMA DYNAMIQUE | D384: ALPHAVEST ASSET MANAGEMENT | E384: FCP | F384: OCT | G384: [0,5 1,1] | H384: MBI CT | I384: QUOTIDIENNE | J384: FGP | K384: CAPITALISANT | L384: 0.03 | M384: 0.015 | N384: 0.02 | O384: BANK OF AFRICA | P384: ALPHAVEST ASSET MANAGEMENT | Q384: 9.7925972e+08 | R384: 1033.13 | S384: 0.019047 | T384: - | U384: 0.000746 | V384: 0.002309 | W384: 0.007411 | X384: 0.014882 | Y384: 0.027132 | Z384: - | AA384: - | AB384: -
...

Sheet 31_12_25
A1: Tableau des performances quotidiennes au 31-12-2025
A2: CODE ISIN | B2: Code Maroclear | C2: OPCVM | D2: Société de Gestion | E2: Nature juridique | F2: Classification | G2: Sensibilité | H2: Indice Bentchmark | I2: Périodicité VL | J2: Souscripteurs | K2: Affectation des résultats | L2: Commission de souscription | M2: Commission de rachat | N2: Frais de gestion | O2: Dépositaire | P2: Réseau placeur | Q2: AN | R2: VL | S2: YTD | T2: 1 jour | U2: 1 semaine | V2: 1 mois | W2: 3 mois | X2: 6 mois | Y2: 1 an | Z2: 2 ans | AA2: 3 ans | AB2: 5 ans
A3: MA0000030132 | B3: 3013 | C3: BMCI TRESORERIE | D3: CIH CAPITAL MANAGEMENT | E3: SICAV | F3: MONÉTAIRE | G3: [0 0,5[ | H3: TMJ(jj) | I3: QUOTIDIENNE | J3: FGP | K3: CAPITALISANT | L3: 0.0125 | M3: 0.005 | N3: 0.0195 | O3: BMCI | P3: CIH CAPITAL MANAGEMENT | Q3: 1.5919419e+08 | R3: 122268.97 | S3: 0.016149 | T3: 0.00011 | U3: 0.000386 | V3: 0.001304 | W3: 0.003661 | X3: 0.00739 | Y3: 0.016149 | Z3: 0.038772 | AA3: 0.061869 | AB3: 0.078071
A4: MA0000030280 | B4: 3028 | C4: CDG TAWFIR | D4: CDG CAPITAL GESTION | E4: SICAV | F4: OMLT | G4: [3 7[ | H4: MBI GLOBAL | I4: QUOTIDIENNE | J4: FGP | K4: CAPITALISANT | L4: 0.005 | M4: 0 | N4: 0.02 | O4: CDG CAPITAL | P4: CDG CAPITAL GESTION | Q4: 1.3015908e+09 | R4: 3477.03 | S4: 0.053492 | T4: -0.000354 | U4: -0.002828 | V4: 0.005099 | W4: -0.004153 | X4: 0.008615 | Y4: 0.053492 | Z4: 0.137489 | AA4: 0.147652 | AB4: 0.12209
A5: MA0000030298 | B5: 3029 | C5: SICAV OBLIGATIONS PÉRENNITÉ | D5: CDG CAPITAL GESTION | E5: SICAV | F5: OMLT | G5: [1,1 16[ | H5: MBI MT | I5: QUOTIDIENNE | J5: FNPP | K5: CAPITALISANT | L5: 0.03 | M5: 0.015 | N5: 0.02 | O5: CDG CAPITAL | P5: CDG CAPITAL GESTION | Q5: 6.0010649e+09 | R5: 3313.59 | S5: 0.037095 | T5: -0.00092 | U5: -0.000667 | V5: 0.00441 | W5: -0.000181 | X5: 0.007614 | Y5: 0.037095 | Z5: 0.092905 | AA5: 0.121316 | AB5: 0.139725
A6: MA0000030306 | B6: 3030 | C6: CDG TRESORERIE | D6: CDG CAPITAL GESTION | E6: SICAV | F6: MONÉTAIRE | G6: [0 0,5[ | H6: 50% MBI CT + 50% TMP | I6: QUOTIDIENNE | J6: FGP | K6: CAPITALISANT | L6: 0 | M6: 0 | N6: 0.02 | O6: CDG CAPITAL | P6: CDG CAPITAL GESTION | Q6: 5.1469756e+09 | R6: 2239.01 | S6: 0.027724 | T6: 0.000273 | U6: 0.000724 | V6: 0.002287 | W6: 0.006351 | X6: 0.012788 | Y6: 0.027724 | Z6: 0.062825 | AA6: 0.099316 | AB6: 0.127953
A7: MA0000030371 | B7: 3037 | C7: CIMR TRESO PLUS | D7: SAHAM CAPITAL GESTION | E7: SICAV | F7: OCT | G7: ]0,5 1,1] | H7: MBI CT | I7: QUOTIDIENNE | J7: FNPP | K7: CAPITALISANT | L7: 0 | M7: 0 | N7: 0.02 | O7: SAHAM BANK | P7: SAHAM BANK | Q7: 2.0872146e+08 | R7: 396808.85 | S7: 0.024736 | T7: -0.000112 | U7: 0.000297 | V7: 0.002071 | W7: 0.004259 | X7: 0.009488 | Y7: 0.024736 | Z7: 0.05965 | AA7: 0.09669 | AB7: 0.126277
A8: MA0000030413 | B8: 3041 | C8: BMCI CASH | D8: CIH CAPITAL MANAGEMENT | E8: SICAV | F8: OCT | G8: [0,6 1,1[ | H8: MBI CT | I8: QUOTIDIENNE | J8: FGP | K8: CAPITALISANT | L8: 0 | M8: 0 | N8: 0.0067 | O8: BMCI | P8: CIH CAPITAL MANAGEMENT | Q8: 35914363 | R8: 192.46 | S8: 0.0303 | T8: 0.000104 | U8: 0.000364 | V8: 0.002031 | W8: 0.007117 | X8: 0.016156 | Y8: 0.0303 | Z8: 0.061614 | AA8: 0.087406 | AB8: 0.100337
A9: MA0000030470 | B9: 3047 | C9: CFG CROISSANCE | D9: CFG GESTION | E9: SICAV | F9: DIVERSIFIÉ | G9: - | H9: 50% CFG 25 FLOTTANT + 50% CFG BONDS CT | I9: QUOTIDIENNE | J9: FGP | K9: CAPITALISANT | L9: 0.002 | M9: 0.002 | N9: 0.015 | O9: CFG BANK | P9: CFG GESTION; CFG BANK | Q9: 1.7378724e+09 | R9: 9863.68 | S9: 0.154377 | T9: 0.00428 | U9: -0.01085 | V9: -0.000502 | W9: -0.01863 | X9: -0.006293 | Y9: 0.154377 | Z9: 0.341818 | AA9: 0.396623 | AB9: 0.377334
A10: MA0000030488 | B10: 3048 | C10: IRAD | D10: BMCE CAPITAL GESTION | E10: SICAV | F10: MONÉTAIRE | G10: <0,5 | H10: Taux Repo au jour le jour | I10: QUOTIDIENNE | J10: FGP | K10: CAPITALISANT | L10: 0 | M10: 0 | N10: 0.015 | O10: BANK OF AFRICA | P10: BMCE CAPITAL GESTION | Q10: 3.2013232e+09 | R10: 2747.19 | S10: 0.028413 | T10: 0.000557 | U10: 0.001046 | V10: 0.002749 | W10: 0.006573 | X10: 0.013248 | Y10: 0.028413 | Z10: 0.064006 | AA10: 0.100708 | AB10: 0.137101
A11: MA0000030512 | B11: 3051 | C11: HORIZON EXPANSION | D11: UPLINE CAPITAL MANAGEMENT | E11: SICAV | F11: DIVERSIFIÉ | G11: - | H11: 40% TMP + 60% MASI | I11: QUOTIDIENNE | J11: FGP | K11: CAPITALISANT | L11: 0.01 | M11: 0.005 | N11: 0.02 | O11: BCP | P11: UPLINE CAPITAL MANAGEMENT | Q11: 4719516.2 | R11: 42904.69 | S11: 0.158641 | T11: 0.004749 | U11: -0.004217 | V11: 0.007959 | W11: -7.6e-05 | X11: 0.011769 | Y11: 0.158641 | Z11: 0.307866 | AA11: 0.405262 | AB11: 0.393502
A12: MA0000030520 | B12: 3052 | C12: ATTIJARI DIVERSIFIE | D12: WAFA GESTION | E12: SICAV | F12: DIVERSIFIÉ | G12: - | H12: 30% MASI + 70% MBI MT | I12: QUOTIDIENNE | J12: FGP | K12: CAPITALISANT | L12: 0.03 | M12: 0.015 | N12: 0.02 | O12: ATTIJARIWAFA BANK | P12: WAFA GESTION | Q12: 3.3487515e+09 | R12: 724.38 | S12: 0.135214 | T12: 0.004813 | U12: -0.006842 | V12: 0.008563 | W12: -0.003919 | X12: 0.008858 | Y12: 0.135214 | Z12: - | AA12: 0.350876 | AB12: -
A13: MA0000030553 | B13: 3055 | C13: ATTIJARI TRESORERIE | D13: WAFA GESTION | E13: SICAV | F13: MONÉTAIRE | G13: [0 0,5[ | H13: TMP | I13: QUOTIDIENNE | J13: FGP | K13: CAPITALISANT | L13: 0 | M13: 0 | N13: 0.02 | O13: ATTIJARIWAFA BANK | P13: WAFA GESTION | Q13: 3.1542925e+09 | R13: 5615.9 | S13: 0.021898 | T13: 0.000285 | U13: 0.000672 | V13: 0.001995 | W13: 0.004996 | X13: 0.00991 | Y13: 0.021898 | Z13: 0.050093 | AA13: 0.078802 | AB13: 0.101498
A14: MA0000030579 | B14: 3057 | C14: CDM OPTIMUM | D14: WAFA GESTION | E14: SICAV | F14: DIVERSIFIÉ | G14: - | H14: 50% MBI MLT + 50% MASI RENTABILITE | I14: QUOTIDIENNE | J14: FGP | K14: CAPITALISANT | L14: 0.03 | M14: 0.015 | N14: 0.02 | O14: CDM | P14: WAFA GESTION | Q14: 5.5396675e+08 | R14: 6930.56 | S14: 0.166832 | T14: 0.005261 | U14: -0.00364 | V14: 0.008426 | W14: -0.000388 | X14: 0.010583 | Y14: 0.166832 | Z14: 0.33098 | AA14: 0.429704 | AB14: 0.38397
A15: MA0000030587 | B15: 3058 | C15: CDM GENERATION | D15: WAFA GESTION | E15: SICAV | F15: OMLT | G15: [3 5[ | H15: 65% MBI MT + 35% MBI MLT | I15: QUOTIDIENNE | J15: FGP | K15: CAPITALISANT | L15: 0.03 | M15: 0.015 | N15: 0.02 | O15: CDM | P15: WAFA GESTION | Q15: 1.1780546e+09 | R15: 3608.93 | S15: 0.039783 | T15: -4.4e-05 | U15: -0.001309 | V15: 0.006251 | W15: -0.003209 | X15: 0.003808 | Y15: 0.039783 | Z15: 0.122511 | AA15: 0.134652 | AB15: 0.128863
A16: MA0000030595 | B16: 3059 | C16: CDM TRESOR PLUS | D16: WAFA GESTION | E16: SICAV | F16: OCT | G16: ]0,5 1,1] | H16: MBI CT | I16: QUOTIDIENNE | J16: FGP | K16: DISTRIBUANT | L16: 0.03 | M16: 0.015 | N16: 0.02 | O16: CDM | P16: WAFA GESTION | Q16: 2.7861986e+08 | R16: 1715.03 | S16: 0.027462 | T16: 0.000216 | U16: 0.000636 | V16: 0.002766 | W16: 0.005417 | X16: 0.011447 | Y16: 0.027462 | Z16: 0.065481 | AA16: 0.105109 | AB16: 0.131212
A17: MA0000030603 | B17: 3060 | C17: CDM CASH | D17: WAFA GESTION | E17: SICAV | F17: MONÉTAIRE | G17: [0 0,5[ | H17: 40% TMP + 60% MBI CT | I17: QUOTIDIENNE | J17: FGP | K17: CAPITALISANT | L17: 0.03 | M17: 0.015 | N17: 0.015 | O17: CDM | P17: WAFA GESTION | Q17: 1.4044824e+09 | R17: 5915.2 | S17: 0.02334 | T17: 0.000203 | U17: 0.000606 | V17: 0.001977 | W17: 0.005226 | X17: 0.010577 | Y17: 0.02334 | Z17: 0.054316 | AA17: 0.085573 | AB17: 0.110373
A18: MA0000030736 | B18: 3073 | C18: BMCI TRESO PLUS | D18: CIH CAPITAL MANAGEMENT | E18: SICAV | F18: MONÉTAIRE | G18: [0,6 1,1[ | H18: MBI CT | I18: QUOTIDIENNE | J18: FGP | K18: CAPITALISANT | L18: 0 | M18: 0 | N18: 0.02 | O18: BMCI | P18: CIH CAPITAL MANAGEMENT | Q18: 1.3306287e+09 | R18: 166.3 | S18: 0.021687 | T18: 0.00018 | U18: 0.000541 | V18: 0.001868 | W18: 0.004773 | X18: 0.009531 | Y18: 0.021687 | Z18: 0.050736 | AA18: 0.081274 | AB18: 0.106748
A19: MA0000030777 | B19: 3077 | C19: HORIZON LIQUIDITE | D19: SAHAM CAPITAL GESTION | E19: SICAV | F19: MONÉTAIRE | G19: [0 0,5[ | H19: MONIA | I19: QUOTIDIENNE | J19: FGP | K19: CAPITALISANT | L19: 0 | M19: 0 | N19: 0.02 | O19: SAHAM BANK | P19: SAHAM BANK | Q19: 3.3170275e+08 | R19: 213.36 | S19: 0.02385 | T19: 0.000422 | U19: 0.000891 | V19: 0.002396 | W19: 0.005656 | X19: 0.011041 | Y19: 0.02385 | Z19: 0.055454 | AA19: 0.087185 | AB19: 0.112418
A20: MA0000035677 | B20: 3567 | C20: CDG HORIZONS | D20: CDG CAPITAL GESTION | E20: FCP | F20: OMLT | G20: ]1,1 5,1] | H20: 50% MBI MLT + 50% MBI MT | I20: QUOTIDIENNE | J20: FGP | K20: CAPITALISANT | L20: 0.03 | M20: 0.015 | N20: 0.02 | O20: CDG CAPITAL | P20: CDG CAPITAL GESTION | Q20: 2.2886154e+08 | R20: 2239.45 | S20: 0.050256 | T20: -0.000946 | U20: -0.00091 | V20: 0.008443 | W20: 0.003005 | X20: 0.013573 | Y20: 0.050256 | Z20: 0.117317 | AA20: 0.1283 | AB20: 0.135848
A21: MA0000035735 | B21: 3573 | C21: STAFF ACTION | D21: CFG GESTION | E21: FCP | F21: ACTIONS | G21: - | H21: CFG 25 FLOTTANT | I21: QUOTIDIENNE | J21: FNPP | K21: CAPITALISANT | L21: 0.003 | M21: 0.003 | N21: 0.02 | O21: CFG BANK | P21: CFG GESTION; CFG BANK | Q21: 50914043 | R21: 4676.16 | S21: 0.294034 | T21: 0.008149 | U21: -0.013273 | V21: 0.005312 | W21: -0.00094 | X21: 0.025982 | Y21: 0.294034 | Z21: 0.661276 | AA21: 0.900276 | AB21: 0.971674
A22: MA0000035743 | B22: 3574 | C22: CFG PERFORMANCE | D22: CFG GESTION | E22: FCP | F22: ACTIONS | G22: - | H22: CFG 25 FLOTTANT | I22: QUOTIDIENNE | J22: FGP | K22: CAPITALISANT | L22: 0.0045 | M22: 0.0045 | N22: 0.02 | O22: CFG BANK | P22: CFG GESTION; CFG BANK | Q22: 1.3457085e+09 | R22: 1223.82 | S22: 0.278622 | T22: 0.010178 | U22: -0.008675 | V22: 0.006621 | W22: -0.003842 | X22: 0.002761 | Y22: 0.278622 | Z22: 0.663251 | AA22: 0.844658 | AB22: 0.762617
A23: MA0000035784 | B23: 3578 | C23: CFG VALEURS | D23: CFG GESTION | E23: FCP | F23: ACTIONS | G23: - | H23: CFG 25 FLOTTANT | I23: QUOTIDIENNE | J23: FGP | K23: CAPITALISANT | L23: 0.003 | M23: 0.003 | N23: 0.02 | O23: CFG BANK | P23: CFG GESTION; CFG BANK | Q23: 91411878 | R23: 725.17 | S23: 0.273658 | T23: 0.011084 | U23: -0.007052 | V23: 0.009171 | W23: -0.002696 | X23: 0.010211 | Y23: 0.273658 | Z23: 0.548946 | AA23: 0.707729 | AB23: 0.655261
A24: MA0000035792 | B24: 3579 | C24: CFG RENDEMENT | D24: CFG GESTION | E24: FCP | F24: OMLT | G24: [2 6[ | H24: CFG BONDS CT | I24: QUOTIDIENNE | J24: FGP | K24: CAPITALISANT | L24: 0 | M24: 0 | N24: 0.01 | O24: CFG BANK | P24: CFG GESTION; CFG BANK | Q24: 32901166 | R24: 350.58 | S24: 0.065463 | T24: 0.000856 | U24: 0.000885 | V24: 0.062686 | W24: 0.05877 | X24: 0.058578 | Y24: 0.065463 | Z24: 0.070506 | AA24: 0.048072 | AB24: -0.008485
... A26: MA0000035834 | B26: 3583 | C26: CFG SECURITE | D26: CFG GESTION | E26: FCP | F26: MONÉTAIRE | G26: ]0 0,5] | H26: TMP INTERBANCAIRE | I26: QUOTIDIENNE | J26: FGP | K26: CAPITALISANT | L26: 0 | M26: 0 | N26: 0.006 | O26: CFG BANK | P26: CFG GESTION; CFG BANK | Q26: 1.7564548e+09 | R26: 2533.61 | S26: 0.026331 | T26: 0.000268 | U26: 0.000675 | V26: 0.00491 | W26: 0.007893 | X26: 0.01301 | Y26: 0.026331 | Z26: 0.055464 | AA26: 0.084798 | AB26: 0.108326
A27: MA0000035842 | B27: 3584 | C27: FCP CAPITAL BALANCE | D27: BMCE CAPITAL GESTION | E27: FCP | F27: DIVERSIFIÉ | G27: - | H27: 50% MASI + 50% MBI Global | I27: QUOTIDIENNE | J27: FGP | K27: CAPITALISANT | L27: 0.02 | M27: 0.02 | N27: 0.02 | O27: BANK OF AFRICA | P27: BMCE CAPITAL GESTION | Q27: 3.4922472e+08 | R27: 5871.79 | S27: 0.178991 | T27: 0.004613 | U27: -0.007743 | V27: 0.004176 | W27: -0.004555 | X27: 0.00277 | Y27: 0.178991 | Z27: - | AA27: 0.434183 | AB27: -
A28: MA0000035867 | B28: 3586 | C28: FCP CAPITAL IMTIYAZ CROISSANCE | D28: BMCE CAPITAL GESTION | E28: FCP | F28: DIVERSIFIÉ | G28: - | H28: 30% MASI + 70% MBI | I28: QUOTIDIENNE | J28: FGP | K28: CAPITALISANT | L28: 0.02 | M28: 0.02 | N28: 0.02 | O28: BANK OF AFRICA | P28: BMCE CAPITAL GESTION | Q28: 1531961 | R28: 66607 | S28: 0.13841 | T28: 0.003767 | U28: -0.002509 | V28: 0.006908 | W28: 0.005082 | X28: 0.016576 | Y28: 0.13841 | Z28: - | AA28: 0.36218 | AB28: -
A29: MA0000035875 | B29: 3587 | C29: FCP CAPITAL PARTICIPATIONS | D29: BMCE CAPITAL GESTION | E29: FCP | F29: ACTIONS | G29: - | H29: MASI | I29: QUOTIDIENNE | J29: FGP | K29: CAPITALISANT | L29: 0.02 | M29: 0.02 | N29: 0.02 | O29: BANK OF AFRICA | P29: BMCE CAPITAL GESTION | Q29: 8.4891571e+08 | R29: 11221.02 | S29: 0.261507 | T29: 0.001626 | U29: -0.012538 | V29: -0.010077 | W29: -0.008818 | X29: - | Y29: 0.261507 | Z29: - | AA29: 1.003049 | AB29: -
A30: MA0000035883 | B30: 3588 | C30: CAPITAL DIVIDENDES PLUS | D30: BMCE CAPITAL GESTION | E30: FCP | F30: ACTIONS | G30: - | H30: MASI | I30: QUOTIDIENNE | J30: FGP | K30: MIXTE | L30: 0.02 | M30: 0.02 | N30: 0.02 | O30: BANK OF AFRICA | P30: BMCE CAPITAL GESTION | Q30: 5572399.5 | R30: 8443.02 | S30: 0.25729 | T30: 0.006978 | U30: -0.009807 | V30: - | W30: - | X30: - | Y30: 0.25729 | Z30: - | AA30: 0.801889 | AB30: -
A31: MA0000035917 | B31: 3591 | C31: CAPITAL TRESOR | D31: BMCE CAPITAL GESTION | E31: FCP | F31: OMLT | G31: [2 6[ | H31: 40% MBI MLT + 60% MBI MT | I31: QUOTIDIENNE | J31: FGP | K31: CAPITALISANT | L31: 0.02 | M31: 0.02 | N31: 0.02 | O31: BANK OF AFRICA | P31: BMCE CAPITAL GESTION | Q31: 5.6758552e+09 | R31: 2872.89 | S31: 0.039155 | T31: 0.001244 | U31: 7.3e-05 | V31: 0.006735 | W31: -0.00456 | X31: 0.001866 | Y31: 0.039155 | Z31: - | AA31: 0.145276 | AB31: -
A32: MA0000035925 | B32: 3592 | C32: FCP CAPITAL DYNAMIQUE | D32: BMCE CAPITAL GESTION | E32: FCP | F32: OCT | G32: ]0,5 1,1] | H32: MBI CT | I32: QUOTIDIENNE | J32: FGP | K32: CAPITALISANT | L32: 0.01 | M32: 0.01 | N32: 0.01 | O32: BANK OF AFRICA | P32: BMCE CAPITAL GESTION | Q32: 54351311 | R32: 2319.03 | S32: 0.051328 | T32: 0.000289 | U32: 0.000578 | V32: 0.04012 | W32: 0.041016 | X32: 0.043391 | Y32: 0.051328 | Z32: 0.06988 | AA32: 0.076971 | AB32: 0.107903
A33: MA0000035933 | B33: 3593 | C33: FCP CAPITAL INSTITUTIONS | D33: BMCE CAPITAL GESTION | E33: FCP | F33: OMLT | G33: ]1,1 5,1] | H33: MBI MT | I33: QUOTIDIENNE | J33: FGP | K33: CAPITALISANT | L33: 0.02 | M33: 0.02 | N33: 0.02 | O33: BANK OF AFRICA | P33: BMCE CAPITAL GESTION | Q33: 1.4145436e+09 | R33: 2643.77 | S33: 0.045973 | T33: 0.000178 | U33: -0.001141 | V33: 0.00625 | W33: -0.001548 | X33: 0.008026 | Y33: 0.045973 | Z33: - | AA33: 0.146912 | AB33: -
A34: MA0000035941 | B34: 3594 | C34: FCP CAPITAL IMTIYAZ SECURITE | D34: BMCE CAPITAL GESTION | E34: FCP | F34: OMLT | G34: ]2 6] | H34: MBI GLOBAL | I34: QUOTIDIENNE | J34: FGP | K34: CAPITALISANT | L34: 0.02 | M34: 0.02 | N34: 0.02 | O34: BANK OF AFRICA | P34: BMCE CAPITAL GESTION | Q34: 1.0710698e+09 | R34: 30175.22 | S34: 0.06028 | T34: 0.001322 | U34: 0.001072 | V34: 0.010591 | W34: 0.002063 | X34: 0.011944 | Y34: 0.06028 | Z34: - | AA34: 0.150488 | AB34: -
A35: MA0000035974 | B35: 3597 | C35: EMERGENCE MONEY MARKET FUND | D35: VALORIS MANAGEMENT | E35: FCP | F35: MONÉTAIRE | G35: [0 0,5[ | H35: MBI CT | I35: QUOTIDIENNE | J35: FGP | K35: CAPITALISANT | L35: 0 | M35: 0 | N35: 0.0065 | O35: BANK OF AFRICA | P35: VALORIS MANAGEMENT | Q35: 5.1829386e+08 | R35: 2069.64 | S35: 0.028285 | T35: 0.000237 | U35: 0.000599 | V35: 0.008444 | W35: 0.011366 | X35: 0.016083 | Y35: 0.028285 | Z35: 0.059154 | AA35: 0.089164 | AB35: 0.114021
A36: MA0000036006 | B36: 3600 | C36: UPLINE TRESORERIE | D36: UPLINE CAPITAL MANAGEMENT | E36: FCP | F36: MONÉTAIRE | G36: ]0 0,5] | H36: 100% TMP | I36: QUOTIDIENNE | J36: FGP | K36: CAPITALISANT | L36: 0 | M36: 0 | N36: 0.02 | O36: BCP | P36: UPLINE CAPITAL MANAGEMENT | Q36: 9.8021561e+08 | R36: 19330.21 | S36: 0.022649 | T36: 4.2e-05 | U36: 0.000419 | V36: 0.00163 | W36: 0.0048 | X36: 0.009812 | Y36: 0.022649 | Z36: 0.051763 | AA36: 0.082093 | AB36: 0.110883
A37: MA0000036014 | B37: 3601 | C37: UPLINE CASH | D37: UPLINE CAPITAL MANAGEMENT | E37: FCP | F37: MONÉTAIRE | G37: ]0 0,5] | H37: MONIA | I37: QUOTIDIENNE | J37: FNPP | K37: CAPITALISANT | L37: 0 | M37: 0 | N37: 0.02 | O37: BCP | P37: UPLINE CAPITAL MANAGEMENT | Q37: 4.9905339e+08 | R37: 23204.23 | S37: 0.023842 | T37: 8.2e-05 | U37: 0.000545 | V37: 0.001947 | W37: 0.005379 | X37: 0.010792 | Y37: 0.023842 | Z37: 0.055292 | AA37: 0.087006 | AB37: 0.111427
A38: MA0000036048 | B38: 3604 | C38: ATTIJARI MONETAIRE PLUS | D38: WAFA GESTION | E38: FCP | F38: OCT | G38: [0,5 1,1[ | H38: MBI CT | I38: QUOTIDIENNE | J38: FGP | K38: CAPITALISANT | L38: 0 | M38: 0 | N38: 0.02 | O38: ATTIJARIWAFA BANK | P38: WAFA GESTION | Q38: 8.8490083e+08 | R38: 228.38 | S38: 0.023896 | T38: 8.8e-05 | U38: 0.000394 | V38: 0.002106 | W38: 0.004398 | X38: 0.010129 | Y38: 0.023896 | Z38: 0.056337 | AA38: 0.088457 | AB38: 0.113071
A39: MA0000036063 | B39: 3606 | C39: ATTIJARI ACTIONS | D39: WAFA GESTION | E39: FCP | F39: ACTIONS | G39: - | H39: MASI | I39: QUOTIDIENNE | J39: FGP | K39: CAPITALISANT | L39: 0.03 | M39: 0.015 | N39: 0.02 | O39: ATTIJARIWAFA BANK | P39: WAFA GESTION | Q39: 6.5847549e+08 | R39: 929.04 | S39: 0.269753 | T39: 0.008949 | U39: -0.007107 | V39: 0.005226 | W39: -0.00482 | X39: 0.005378 | Y39: 0.269753 | Z39: 0.511962 | AA39: 0.659889 | AB39: -
A40: MA0000036147 | B40: 3614 | C40: CDM SECURITE PLUS | D40: WAFA GESTION | E40: FCP | F40: MONÉTAIRE | G40: [0 0,5[ | H40: TMP | I40: QUOTIDIENNE | J40: FGP | K40: CAPITALISANT | L40: 0 | M40: 0 | N40: 0.01 | O40: CDM | P40: WAFA GESTION | Q40: 3.709476e+08 | R40: 2022.05 | S40: 0.01848 | T40: 4.9e-05 | U40: 0.000341 | V40: 0.001411 | W40: 0.004301 | X40: 0.008564 | Y40: 0.01848 | Z40: 0.042622 | AA40: 0.068003 | AB40: 0.090248
A41: MA0000036154 | B41: 3615 | C41: FCP CDM LIQUIDITES | D41: WAFA GESTION | E41: FCP | F41: OCT | G41: [0 1,1[ | H41: 80% MBI CT + 20% MBI MT | I41: QUOTIDIENNE | J41: FGP | K41: CAPITALISANT | L41: 0.03 | M41: 0.015 | N41: 0.02 | O41: CDM | P41: WAFA GESTION | Q41: 4.8055412e+08 | R41: 39669.32 | S41: 0.022081 | T41: 8e-05 | U41: 0.000405 | V41: 0.00219 | W41: 0.003913 | X41: 0.008638 | Y41: 0.022081 | Z41: 0.053053 | AA41: 0.083313 | AB41: 0.09703
A42: MA0000036196 | B42: 3619 | C42: FCP CAM LIQUIDITE | D42: MAROGEST | E42: FCP | F42: MONÉTAIRE | G42: ]0 0,5] | H42: TMP INTERBANCAIRE | I42: QUOTIDIENNE | J42: FGP | K42: CAPITALISANT | L42: 0 | M42: 0 | N42: 0.0065 | O42: CIH BANK | P42: MAROGEST | Q42: 2.136308e+08 | R42: 1914.6 | S42: 0.029388 | T42: 0.000413 | U42: 0.000962 | V42: 0.002729 | W42: 0.006778 | X42: 0.013643 | Y42: 0.029388 | Z42: 0.064134 | AA42: 0.099934 | AB42: 0.134537
A43: MA0000036220 | B43: 3622 | C43: FCP CAPITAL PROTECTION | D43: BMCE CAPITAL GESTION | E43: FCP | F43: ACTIONS | G43: - | H43: MASI | I43: QUOTIDIENNE | J43: FNPP | K43: CAPITALISANT | L43: 0.02 | M43: 0.02 | N43: 0.02 | O43: BANK OF AFRICA | P43: BMCE CAPITAL GESTION | Q43: 1.0784622e+09 | R43: 3995.91 | S43: 0.26422 | T43: 0.006869 | U43: -0.015007 | V43: -0.000498 | W43: -0.008058 | X43: -0.00284 | Y43: 0.26422 | Z43: 0.599308 | AA43: 0.812909 | AB43: 0.839259
A44: MA0000036238 | B44: 3623 | C44: FCP CAPITAL MONETAIRE | D44: BMCE CAPITAL GESTION | E44: FCP | F44: MONÉTAIRE | G44: [0 0,25[ | H44: MONIA | I44: QUOTIDIENNE | J44: FGP | K44: CAPITALISANT | L44: 0.01 | M44: 0.01 | N44: 0.01 | O44: BANK OF AFRICA | P44: BMCE CAPITAL GESTION | Q44: 5.1254495e+08 | R44: 1636.71 | S44: 0.019471 | T44: 4.9e-05 | U44: 0.000373 | V44: 0.001438 | W44: 0.004505 | X44: 0.009162 | Y44: 0.019471 | Z44: 0.044813 | AA44: 0.071875 | AB44: 0.096586
A45: MA0000036246 | B45: 3624 | C45: CDG MONETAIRE PLUS | D45: CDG CAPITAL GESTION | E45: FCP | F45: OCT | G45: [0,5 1,1[ | H45: 85% MBI CT + 15% MBI MT | I45: QUOTIDIENNE | J45: FGP | K45: CAPITALISANT | L45: 0.005 | M45: 0 | N45: 0.01 | O45: CDG CAPITAL | P45: CDG CAPITAL GESTION | Q45: 5.8743661e+08 | R45: 2272.64 | S45: 0.033521 | T45: 0.00026 | U45: 0.000744 | V45: 0.003116 | W45: 0.008892 | X45: 0.015478 | Y45: 0.033521 | Z45: 0.07843 | AA45: 0.114028 | AB45: 0.138991
A46: MA0000036261 | B46: 3626 | C46: CAPITAL IMTIYAZ LIQUIDITE | D46: BMCE CAPITAL GESTION | E46: FCP | F46: OCT | G46: ]0,5 1,1] | H46: MBI CT | I46: QUOTIDIENNE | J46: FGP | K46: CAPITALISANT | L46: 0.01 | M46: 0.005 | N46: 0.008 | O46: BANK OF AFRICA | P46: BMCE CAPITAL GESTION | Q46: 1.0146006e+10 | R46: 19018.81 | S46: 0.033044 | T46: -1.5e-05 | U46: 0.000448 | V46: 0.002846 | W46: 0.006257 | X46: 0.013718 | Y46: 0.033044 | Z46: 0.075183 | AA46: 0.11684 | AB46: 0.158459
A47: MA0000036287 | B47: 3628 | C47: EMERGENCE BOND FUND | D47: VALORIS MANAGEMENT | E47: FCP | F47: OCT | G47: ]0.5 1.1] | H47: MBI CT | I47: QUOTIDIENNE | J47: FGP | K47: CAPITALISANT | L47: 0 | M47: 0 | N47: 0.008 | O47: BANK OF AFRICA | P47: VALORIS MANAGEMENT | Q47: 6.8167279e+08 | R47: 2384.4 | S47: 0.025778 | T47: 5.5e-05 | U47: 0.000407 | V47: 0.005308 | W47: 0.007147 | X47: 0.011934 | Y47: 0.025778 | Z47: 0.057618 | AA47: 0.088146 | AB47: 0.125891
A48: MA0000036303 | B48: 3630 | C48: FCP CAPITAL ACTIONS | D48: BMCE CAPITAL GESTION | E48: FCP | F48: ACTIONS | G48: - | H48: MASI | I48: QUOTIDIENNE | J48: FGP | K48: CAPITALISANT | L48: 0.02 | M48: 0.02 | N48: 0.02 | O48: BANK OF AFRICA | P48: BMCE CAPITAL GESTION | Q48: 1.7666664e+08 | R48: 272.66 | S48: 0.287468 | T48: 0.007724 | U48: -0.01346 | V48: 0.000697 | W48: -0.007896 | X48: -0.002925 | Y48: 0.287468 | Z48: 0.624523 | AA48: 0.81495 | AB48: 0.720035
A49: MA0000036311 | B49: 3631 | C49: FCP CAPITAL SELECTION | D49: BMCE CAPITAL GESTION | E49: FCP | F49: ACTIONS | G49: - | H49: MADEX | I49: QUOTIDIENNE | J49: FGP | K49: CAPITALISANT | L49: 0.02 | M49: 0.02 | N49: 0.02 | O49: BANK OF AFRICA | P49: BMCE CAPITAL GESTION | Q49: 3159148.1 | R49: 331.7 | S49: 0.226293 | T49: 0.005944 | U49: -0.009644 | V49: 0.005944 | W49: -0.006351 | X49: 0.011589 | Y49: 0.226293 | Z49: 0.574276 | AA49: 0.786792 | AB49: 0.724281
A50: MA0000036329 | B50: 3632 | C50: FCP CAPITAL TERME | D50: BMCE CAPITAL GESTION | E50: FCP | F50: DIVERSIFIÉ | G50: - | H50: 80% MBI GLOBAL + 20% MASI | I50: QUOTIDIENNE | J50: FGP | K50: CAPITALISANT | L50: 0.02 | M50: 0.02 | N50: 0.02 | O50: BANK OF AFRICA | P50: BMCE CAPITAL GESTION | Q50: 80472594 | R50: 243.86 | S50: 0.10785 | T50: 0.002096 | U50: -0.002291 | V50: 0.005111 | W50: -0.000246 | X50: 0.007353 | Y50: 0.10785 | Z50: 0.241586 | AA50: 0.282461 | AB50: 0.283744
A51: MA0000036345 | B51: 3634 | C51: CFG INSTIBONDS | D51: CFG GESTION | E51: FCP | F51: OMLT | G51: ]1,5 5,5] | H51: MBI GLOBAL | I51: QUOTIDIENNE | J51: FGP | K51: CAPITALISANT | L51: 0.03 | M51: 0.015 | N51: 0.02 | O51: CFG BANK | P51: CFG GESTION; CFG BANK | Q51: 5.512719e+08 | R51: 34.08 | S51: -0.77149 | T51: 0 | U51: 0 | V51: 0.002648 | W51: -0.778759 | X51: -0.779317 | Y51: -0.77149 | Z51: -0.759322 | AA51: -0.752954 | AB51: -
A52: MA0000036352 | B52: 3635 | C52: FCP CAM TRESO PLUS | D52: MAROGEST | E52: FCP | F52: OCT | G52: ]0,5 1,1] | H52: 85% MBI CT + 15 % MBI MT | I52: QUOTIDIENNE | J52: FGP | K52: CAPITALISANT | L52: 0.03 | M52: 0.015 | N52: 0.02 | O52: CIH BANK | P52: CIH | Q52: 3.3168863e+08 | R52: 171.61 | S52: 0.031186 | T52: 0.000233 | U52: 0.0007 | V52: 0.002863 | W52: 0.005743 | X52: 0.012628 | Y52: 0.031186 | Z52: 0.071692 | AA52: 0.111392 | AB52: 0.146206
A53: MA0000036402 | B53: 3640 | C53: UPLINE EQUILIBRE | D53: UPLINE CAPITAL MANAGEMENT | E53: FCP | F53: DIVERSIFIÉ | G53: - | H53: 75% MBI GLOBAL + 25% MASI 20 | I53: QUOTIDIENNE | J53: FNPP | K53: MIXTE | L53: 0 | M53: 0 | N53: 0.02 | O53: BCP | P53: UPLINE CAPITAL MANAGEMENT | Q53: 5.881028e+08 | R53: 128.78 | S53: 0.157907 | T53: 0.004054 | U53: -0.003791 | V53: 0.007432 | W53: -0.003559 | X53: 0.003663 | Y53: 0.157907 | Z53: - | AA53: -0.067393 | AB53: -
A54: MA0000036493 | B54: 3649 | C54: FCP CAPITAL MAGHREB | D54: BMCE CAPITAL GESTION | E54: FCP | F54: ACTIONS | G54: - | H54: MASI | I54: QUOTIDIENNE | J54: FGP | K54: CAPITALISANT | L54: 0.02 | M54: 0.02 | N54: 0.02 | O54: BANK OF AFRICA | P54: BMCE CAPITAL GESTION | Q54: 1.7502702e+09 | R54: 1804.25 | S54: 0.288373 | T54: 0.007516 | U54: -0.015319 | V54: 0.000139 | W54: -0.008392 | X54: -0.005665 | Y54: 0.288373 | Z54: - | AA54: 0.87882 | AB54: -
A55: MA0000036501 | B55: 3650 | C55: FCP CAPITAL MULTI-GESTION | D55: BMCE CAPITAL GESTION | E55: FCP | F55: DIVERSIFIÉ | G55: - | H55: 80% MBI GLOBAL + 20% MASI | I55: QUOTIDIENNE | J55: FGP | K55: CAPITALISANT | L55: 0.02 | M55: 0.02 | N55: 0.02 | O55: BANK OF AFRICA | P55: BMCE CAPITAL GESTION | Q55: 1.6944088e+09 | R55: 556.79 | S55: 0.118367 | T55: 0.003406 | U55: -0.005288 | V55: 0.004565 | W55: -0.005501 | X55: 0.001998 | Y55: 0.118367 | Z55: - | AA55: 0.29474 | AB55: -
A56: MA0000036576 | B56: 3657 | C56: UPLINE VALEURS PLUS | D56: UPLINE CAPITAL MANAGEMENT | E56: FCP | F56: ACTIONS | G56: - | H56: MASI | I56: QUOTIDIENNE | J56: FGP | K56: MIXTE | L56: 0 | M56: 0 | N56: 0.02 | O56: BCP | P56: UPLINE CAPITAL MANAGEMENT | Q56: 15571750 | R56: 4499.21 | S56: 0.301655 | T56: 0.008991 | U56: -0.007975 | V56: 0.008258 | W56: -0.005693 | X56: 0.003634 | Y56: 0.301655 | Z56: 0.614651 | AA56: 0.834151 | AB56: 0.793772
A57: MA0000036584 | B57: 3658 | C57: HORIZON NOVA | D57: SAHAM CAPITAL GESTION | E57: FCP | F57: MONÉTAIRE | G57: [0 0,5[ | H57: TMP INTERBANCAIRE | I57: QUOTIDIENNE | J57: FNPP | K57: CAPITALISANT | L57: 0.03 | M57: 0.015 | N57: 0.02 | O57: SAHAM BANK | P57: SAHAM BANK | Q57: 1502656.9 | R57: 1502.65 | S57: 0.017187 | T57: 0.000166 | U57: 0.000466 | V57: 0.001533 | W57: 0.003747 | X57: 0.007408 | Y57: 0.017187 | Z57: 0.041345 | AA57: 0.067526 | AB57: 0.085432
A58: MA0000036592 | B58: 3659 | C58: FCP CAPITAL IMMOBILIER | D58: BMCE CAPITAL GESTION | E58: FCP | F58: ACTIONS | G58: - | H58: 10% Indice Sectoriel Immobilier + 10 % Indice Sectoriel Batiments et Matériaux de Construction + 80% MASI | I58: QUOTIDIENNE | J58: FGP | K58: CAPITALISANT | L58: 0.02 | M58: 0.02 | N58: 0.02 | O58: BANK OF AFRICA | P58: BMCE CAPITAL GESTION | Q58: 1303442.2 | R58: 1977.9 | S58: 0.309972 | T58: 0.005521 | U58: -0.008571 | V58: 0.005997 | W58: -0.002899 | X58: 0.012636 | Y58: 0.309972 | Z58: - | AA58: 0.965947 | AB58: -
A59: MA0000036600 | B59: 3660 | C59: ALIF I | D59: UPLINE CAPITAL MANAGEMENT | E59: FCP | F59: OMLT | G59: ]3,1 7,1] | H59: 50% MBI MT + 50% MBI MLT | I59: QUOTIDIENNE | J59: FNPP | K59: CAPITALISANT | L59: 0 | M59: 0 | N59: 0.02 | O59: BCP | P59: UPLINE CAPITAL MANAGEMENT | Q59: 2.5536471e+09 | R59: 1850.69 | S59: 0.04677 | T59: -0.001279 | U59: -0.001112 | V59: 0.004914 | W59: -0.002485 | X59: 0.005121 | Y59: 0.04677 | Z59: 0.138095 | AA59: 0.175691 | AB59: 0.196936
A60: MA0000036618 | B60: 3661 | C60: UPLINE PERENNITE | D60: UPLINE CAPITAL MANAGEMENT | E60: FCP | F60: MONÉTAIRE | G60: ]0 0,5] | H60: MBI CT | I60: QUOTIDIENNE | J60: FGP | K60: MIXTE | L60: 0 | M60: 0 | N60: 0.02 | O60: BCP | P60: UPLINE CAPITAL MANAGEMENT | Q60: 4.7938131e+09 | R60: 1758.98 | S60: 0.026434 | T60: 0.000341 | U60: 0.000808 | V60: 0.002496 | W60: 0.005959 | X60: 0.012124 | Y60: 0.026434 | Z60: 0.061686 | AA60: 0.096457 | AB60: 0.132393
A61: MA0000036659 | B61: 3665 | C61: ATTIJARI LIQUIDITE | D61: WAFA GESTION | E61: FCP | F61: MONÉTAIRE | G61: [0 0,5[ | H61: TMP | I61: QUOTIDIENNE | J61: FGP | K61: CAPITALISANT | L61: 0.02 | M61: 0.02 | N61: 0.02 | O61: ATTIJARIWAFA BANK | P61: WAFA GESTION | Q61: 3.6181447e+09 | R61: 1571.22 | S61: 0.020379 | T61: 6.4e-05 | U61: 0.000369 | V61: 0.001492 | W61: 0.004565 | X61: 0.009314 | Y61: 0.020379 | Z61: 0.046336 | AA61: 0.072937 | AB61: 0.100926
A62: MA0000036774 | B62: 3677 | C62: AFRICAPITAL LIQUIDITY | D62: AFRICAPITAL MANAGEMENT | E62: FCP | F62: MONÉTAIRE | G62: ]0 0,5] | H62: Repo jj capitalisé | I62: QUOTIDIENNE | J62: FGP | K62: CAPITALISANT | L62: 0.03 | M62: 0.03 | N62: 0.02 | O62: ATTIJARIWAFA BANK | P62: AFRICAPITAL MANAGEMENT | Q62: 1461905333 | R62: 1565.47 | S62: 0.025119 | T62: 7e-05 | U62: 0.000473 | V62: 0.002177 | W62: 0.005647 | X62: 0.011436 | Y62: 0.025119 | Z62: 0.057786 | AA62: 0.092725 | AB62: 0.120658
A63: MA0000036873 | B63: 3687 | C63: AFRICAPITAL CASH | D63: AFRICAPITAL MANAGEMENT | E63: FCP | F63: OCT | G63: ]0.5 1.1] | H63: MBI CT | I63: QUOTIDIENNE | J63: FGP | K63: CAPITALISANT | L63: 0.02 | M63: 0.02 | N63: 0.02 | O63: ATTIJARIWAFA BANK | P63: AFRICAPITAL MANAGEMENT | Q63: 1.0933114e+09 | R63: 1576.83 | S63: 0.02843 | T63: -0.00014 | U63: 0.000266 | V63: 0.002346 | W63: 0.005067 | X63: 0.010873 | Y63: 0.02843 | Z63: 0.069509 | AA63: 0.109288 | AB63: 0.140391
A64: MA0000036907 | B64: 3690 | C64: FCP IRGAM MONETAIRE | D64: IRG ASSET MANAGEMENT | E64: FCP | F64: MONÉTAIRE | G64: ]0 0,5] | H64: 80% MONIA + 20% MBI CT | I64: QUOTIDIENNE | J64: FGP | K64: CAPITALISANT | L64: 0.03 | M64: 0.015 | N64: 0.02 | O64: ATTIJARIWAFA BANK | P64: IRG ASSET MANAGEMENT | Q64: 1.7708001e+08 | R64: 155.08 | S64: 0.017452 | T64: 0.000129 | U64: 0.000323 | V64: 0.006033 | W64: 0.007798 | X64: 0.010359 | Y64: 0.017452 | Z64: 0.037324 | AA64: 0.070108 | AB64: 0.100873
A65: MA0000036915 | B65: 3691 | C65: FCP IRGAM OBLIGATAIRE | D65: IRG ASSET MANAGEMENT | E65: FCP | F65: OMLT | G65: [3,5 7,5] | H65: MBI MLT | I65: QUOTIDIENNE | J65: FGP | K65: CAPITALISANT | L65: 0.03 | M65: 0.015 | N65: 0.02 | O65: ATTIJARIWAFA BANK | P65: IRG ASSET MANAGEMENT | Q65: 2.1292308e+09 | R65: 167.21 | S65: 0.049918 | T65: 0.000239 | U65: -0.000299 | V65: 0.005291 | W65: -0.005768 | X65: 0.003059 | Y65: 0.049918 | Z65: 0.142535 | AA65: 0.059565 | AB65: 0.028225
A66: MA0000036923 | B66: 3692 | C66: FCP IRGAM ACTIONS | D66: IRG ASSET MANAGEMENT | E66: FCP | F66: ACTIONS | G66: - | H66: MASI FLOTTANT | I66: QUOTIDIENNE | J66: FGP | K66: CAPITALISANT | L66: 0.03 | M66: 0.015 | N66: 0.02 | O66: ATTIJARIWAFA BANK | P66: IRG ASSET MANAGEMENT | Q66: 1.5185503e+09 | R66: 266.55 | S66: 0.24877 | T66: 0.007255 | U66: -0.013545 | V66: -0.003887 | W66: -0.019135 | X66: 0.002558 | Y66: 0.24877 | Z66: 0.614085 | AA66: 0.752465 | AB66: 0.661887
A67: MA0000036972 | B67: 3697 | C67: CFG PREVOYANCE | D67: CFG GESTION | E67: FCP | F67: OMLT | G67: ]1.1 8] | H67: MBI GLOBAL | I67: QUOTIDIENNE | J67: FGP | K67: CAPITALISANT | L67: 0.03 | M67: 0.015 | N67: 0.02 | O67: CFG BANK | P67: CFG GESTION | Q67: 6.4805447e+08 | R67: 169.21 | S67: 0.056034 | T67: 0.000414 | U67: -0.0023 | V67: 0.002904 | W67: -0.006517 | X67: 0.002726 | Y67: 0.056034 | Z67: 0.14926 | AA67: 0.173124 | AB67: 0.184431
A68: MA0000037046 | B68: 3704 | C68: AXA MONETAIRE | D68: CIH CAPITAL MANAGEMENT | E68: FCP | F68: MONÉTAIRE | G68: <=0,5 | H68: TMI(jj) | I68: QUOTIDIENNE | J68: FNPP | K68: CAPITALISANT | L68: 0 | M68: 0 | N68: 0.02 | O68: BMCI | P68: CIH CAPITAL MANAGEMENT | Q68: 6.7992155e+08 | R68: 157681.25 | S68: 0.02368 | T68: 0.000205 | U68: 0.000601 | V68: 0.002061 | W68: 0.005244 | X68: 0.010527 | Y68: 0.02368 | Z68: 0.054672 | AA68: 0.087091 | AB68: 0.115583
A69: MA0000037061 | B69: 3706 | C69: FCP CAPITAL PLUS | D69: BMCE CAPITAL GESTION | E69: FCP | F69: OMLT | G69: ]1,1 5,1] | H69: MBI MT | I69: QUOTIDIENNE | J69: FGP | K69: CAPITALISANT | L69: 0.02 | M69: 0.02 | N69: 0.02 | O69: BANK OF AFRICA | P69: BMCE CAPITAL GESTION | Q69: 2.6345742e+09 | R69: 1668.71 | S69: 0.042156 | T69: 0.00268 | U69: 1.8e-05 | V69: 0.005677 | W69: -0.004201 | X69: -0.000725 | Y69: 0.042156 | Z69: - | AA69: 0.164837 | AB69: -
A70: MA0000037095 | B70: 3709 | C70: AD CASH | D70: AD CAPITAL ASSET MANAGEMENT | E70: FCP | F70: MONÉTAIRE | G70: [0 0.5[ | H70: MBI CT | I70: QUOTIDIENNE | J70: FGP | K70: CAPITALISANT | L70: 0.03 | M70: 0.03 | N70: 0.02 | O70: ATTIJARIWAFA BANK | P70: AD CAPITAL ASSET MANAGEMENT; AD CAPITAL GROUP | Q70: 6.4484291e+08 | R70: 1565.11 | S70: 0.029048 | T70: 0.000396 | U70: 0.000902 | V70: 0.002896 | W70: 0.006715 | X70: 0.012892 | Y70: 0.029048 | Z70: 0.065926 | AA70: 0.103667 | AB70: 0.141816
A71: MA0000037186 | B71: 3718 | C71: FCP ALIF II | D71: WAFA GESTION | E71: SICAV | F71: OMLT | G71: ]1,1 10] | H71: 50% MBI MLT + 50% MBI MT | I71: QUOTIDIENNE | J71: FNPP | K71: CAPITALISANT | L71: 0.03 | M71: 0.015 | N71: 0.02 | O71: ATTIJARIWAFA BANK | P71: WAFA GESTION | Q71: 2.9414971e+09 | R71: 1834.77 | S71: 0.048296 | T71: -0.001823 | U71: -0.001589 | V71: 0.004368 | W71: -0.001219 | X71: 0.006904 | Y71: 0.048296 | Z71: 0.136946 | AA71: 0.18286 | AB71: 0.204494
A72: MA0000037202 | B72: 3720 | C72: ATLAS EQUILIBRE | D72: ATLAS CAPITAL MANAGEMENT | E72: FCP | F72: OCT | G72: ]0.5 1.1] | H72: MBI CT | I72: QUOTIDIENNE | J72: FGP | K72: CAPITALISANT | L72: 0.005 | M72: 0.005 | N72: 0.0075 | O72: ATTIJARIWAFA BANK | P72: ATLAS CAPITAL MANAGEMENT | Q72: 2.0915413e+08 | R72: 144 | S72: 0.030411 | T72: 0.000139 | U72: 0.000625 | V72: 0.002786 | W72: 0.006008 | X72: 0.012943 | Y72: 0.030411 | Z72: 0.06936 | AA72: 0.108545 | AB72: 0.143947
A73: MA0000037251 | B73: 3725 | C73: FCP MAROGEST CASH | D73: MAROGEST | E73: FCP | F73: MONÉTAIRE | G73: ]0 0,5] | H73: TMP INTERBANCAIRE | I73: QUOTIDIENNE | J73: FGP | K73: CAPITALISANT | L73: 0 | M73: 0 | N73: 0.02 | O73: ATTIJARIWAFA BANK | P73: MAROGEST | Q73: 79353866 | R73: 134.87 | S73: 0.026955 | T73: 0.000297 | U73: 0.000742 | V73: 0.0029 | W73: 0.006718 | X73: 0.012766 | Y73: 0.026955 | Z73: 0.060716 | AA73: 0.094191 | AB73: 0.127393
A74: MA0000037327 | B74: 3732 | C74: CAPITAL TRUST MONÉTAIRE | D74: CAPITAL TRUST GESTION | E74: FCP | F74: MONÉTAIRE | G74: <= 0,5 | H74: Taux Repo au jour le jour | I74: QUOTIDIENNE | J74: FGP | K74: CAPITALISANT | L74: 0 | M74: 0 | N74: 0.02 | O74: BMCI | P74: CAPITAL TRUST GESTION | Q74: 25320385 | R74: 1431.82 | S74: 0.028281 | T74: 0.00014 | U74: 0.000433 | V74: 0.01314 | W74: 0.015274 | X74: 0.019009 | Y74: 0.028281 | Z74: 0.051765 | AA74: 0.080195 | AB74: 0.108812
A75: MA0000037335 | B75: 3733 | C75: CMR ACTIONS | D75: WAFA GESTION | E75: FCP | F75: ACTIONS | G75: - | H75: MASI | I75: QUOTIDIENNE | J75: FNPP | K75: MIXTE | L75: 0.03 | M75: 0.015 | N75: 0.02 | O75: ATTIJARIWAFA BANK | P75: WAFA GESTION | Q75: 1.6258302e+09 | R75: 290846.19 | S75: 0.276702 | T75: 0.009989 | U75: -0.005392 | V75: 0.006626 | W75: -0.003145 | X75: 0.008147 | Y75: 0.276702 | Z75: 0.576537 | AA75: 0.794297 | AB75: 0.836225
A76: MA0000037350 | B76: 3735 | C76: UPLINE CAPITAL GARANTI | D76: UPLINE CAPITAL MANAGEMENT | E76: FCP | F76: CONTRACTUEL | G76: - | H76: TMP INTERBANCAIRE | I76: QUOTIDIENNE | J76: FGP | K76: CAPITALISANT | L76: 0 | M76: 0 | N76: 0.02 | O76: BCP | P76: UPLINE CAPITAL MANAGEMENT | Q76: 1.5310476e+09 | R76: 13063.77 | S76: 0.020989 | T76: 5.5e-05 | U76: 0.000384 | V76: 0.001597 | W76: 0.004966 | X76: 0.010104 | Y76: 0.020989 | Z76: 0.048098 | AA76: 0.075385 | AB76: 0.10184
A77: MA0000037368 | B77: 3736 | C77: UPLINE HORIZON | D77: UPLINE CAPITAL MANAGEMENT | E77: FCP | F77: OMLT | G77: ]1,1 5,1] | H77: MBI GLOBAL | I77: QUOTIDIENNE | J77: FNPP | K77: CAPITALISANT | L77: 0 | M77: 0 | N77: 0.02 | O77: BCP | P77: UPLINE CAPITAL MANAGEMENT | Q77: 1.092846e+10 | R77: 16192.76 | S77: 0.042068 | T77: -0.000356 | U77: -0.000214 | V77: 0.004921 | W77: 0.000592 | X77: 0.007507 | Y77: 0.042068 | Z77: 0.106019 | AA77: 0.14273 | AB77: 0.148908
A78: MA0000037376 | B78: 3737 | C78: UPLINE OBLIG PLUS | D78: UPLINE CAPITAL MANAGEMENT | E78: FCP | F78: OMLT | G78: ]1,2 5,2] | H78: 50% MBI CT + 50% MBI MLT | I78: QUOTIDIENNE | J78: FNPP | K78: CAPITALISANT | L78: 0 | M78: 0 | N78: 0.02 | O78: BCP | P78: UPLINE CAPITAL MANAGEMENT | Q78: 2.8040088e+09 | R78: 1784.26 | S78: 0.049176 | T78: -0.000527 | U78: -0.000325 | V78: 0.004153 | W78: 0.000942 | X78: 0.008495 | Y78: 0.049176 | Z78: 0.141598 | AA78: 0.1653 | AB78: 0.189697
A79: MA0000037384 | B79: 3738 | C79: UPLINE OPPORTUNITES | D79: UPLINE CAPITAL MANAGEMENT | E79: FCP | F79: DIVERSIFIÉ | G79: - | H79: 80% MBI + 20% MASI | I79: QUOTIDIENNE | J79: FNPP | K79: CAPITALISANT | L79: 0 | M79: 0 | N79: 0.02 | O79: BCP | P79: UPLINE CAPITAL MANAGEMENT | Q79: 2.2071874e+09 | R79: 19941.34 | S79: 0.135045 | T79: 0.002947 | U79: -0.001442 | V79: 0.009215 | W79: 0.000378 | X79: 0.010134 | Y79: 0.135045 | Z79: 0.28015 | AA79: 0.319506 | AB79: 0.319174
A80: MA0000037392 | B80: 3739 | C80: FCP CAPITAL OBLIGATIONS BANQUES | D80: BMCE CAPITAL GESTION | E80: FCP | F80: OCT | G80: ]0,5 1,1] | H80: 90% MBI CT + 10% MBI MT | I80: QUOTIDIENNE | J80: FGP | K80: CAPITALISANT | L80: 0.01 | M80: 0.01 | N80: 0.01 | O80: BANK OF AFRICA | P80: BMCE CAPITAL GESTION | Q80: 1.2465137e+09 | R80: 1490.97 | S80: 0.029434 | T80: 0.000215 | U80: 0.000423 | V80: 0.002656 | W80: 0.005415 | X80: 0.011753 | Y80: 0.029434 | Z80: 0.070061 | AA80: 0.108882 | AB80: 0.141683
A81: MA0000037400 | B81: 3740 | C81: CFG TRADER | D81: CFG GESTION | E81: FCP | F81: ACTIONS | G81: - | H81: - | I81: QUOTIDIENNE | J81: FGP | K81: CAPITALISANT | L81: 0.002 | M81: 0.002 | N81: 0.02 | O81: CFG BANK | P81: CFG GESTION; CFG BANK | Q81: 29238571 | R81: 255.03 | S81: 0.271336 | T81: 0.008941 | U81: -0.008167 | V81: 0.005797 | W81: 0.011703 | X81: 0.018409 | Y81: 0.271336 | Z81: 0.649399 | AA81: 0.875772 | AB81: 0.928977
... A92: MA0000037715 | B92: 3771 | C92: CAPITAL RENDEMENT | D92: BMCE CAPITAL GESTION | E92: FCP | F92: OCT | G92: ]0,5 1,1] | H92: MBI CT | I92: QUOTIDIENNE | J92: FGP | K92: CAPITALISANT | L92: 0.03 | M92: 0.015 | N92: 0.01 | O92: BANK OF AFRICA | P92: BMCE CAPITAL GESTION | Q92: 4.9388772e+09 | R92: 2536.47 | S92: 0.033223 | T92: 0.00013 | U92: 0.000422 | V92: 0.002724 | W92: 0.005598 | X92: 0.012458 | Y92: 0.033223 | Z92: 0.074876 | AA92: 0.109431 | AB92: 0.146215
A93: MA0000037723 | B93: 3772 | C93: FCP CAPITAL COMBO | D93: BMCE CAPITAL GESTION | E93: FCP | F93: OMLT | G93: ]1,1 5,1] | H93: 50% MBI CT + 50% MBI MT | I93: QUOTIDIENNE | J93: FGP | K93: CAPITALISANT | L93: 0.01 | M93: 0.005 | N93: 0.01 | O93: BANK OF AFRICA | P93: BMCE CAPITAL GESTION | Q93: 8.7757287e+08 | R93: 151724.21 | S93: 0.06621 | T93: 0.000929 | U93: -0.001019 | V93: 0.006108 | W93: 0.000132 | X93: - | Y93: 0.06621 | Z93: - | AA93: 0.19502 | AB93: -
A94: MA0000037749 | B94: 3774 | C94: FCP CAPITAL GLOBAL MACRO | D94: BMCE CAPITAL GESTION | E94: FCP | F94: DIVERSIFIÉ | G94: - | H94: 80% MBI GLOBAL + 20% MASI | I94: QUOTIDIENNE | J94: FGP | K94: CAPITALISANT | L94: 0.01 | M94: 0.005 | N94: 0.02 | O94: BANK OF AFRICA | P94: BMCE CAPITAL GESTION | Q94: 30232246 | R94: 163417.54 | S94: 0.096355 | T94: 0.001868 | U94: -0.002971 | V94: 0.005618 | W94: -0.004823 | X94: - | Y94: 0.096355 | Z94: - | AA94: 0.247636 | AB94: -
A95: MA0000037756 | B95: 3775 | C95: FCP CAPITAL AFRIQUE | D95: BMCE CAPITAL GESTION | E95: FCP | F95: ACTIONS | G95: - | H95: MASI | I95: QUOTIDIENNE | J95: FGP | K95: CAPITALISANT | L95: 0.02 | M95: 0.01 | N95: 0.02 | O95: BANK OF AFRICA | P95: BMCE CAPITAL GESTION | Q95: 4546204.3 | R95: 2151.54 | S95: 0.278593 | T95: 0.008153 | U95: -0.013037 | V95: -0.002231 | W95: 0.001401 | X95: 0.023315 | Y95: 0.278593 | Z95: - | AA95: 0.953796 | AB95: -
A96: MA0000037798 | B96: 3779 | C96: CDM OBLIG PLUS | D96: WAFA GESTION | E96: FCP | F96: OCT | G96: ]0,5 1,1] | H96: MBI CT | I96: QUOTIDIENNE | J96: FGP | K96: CAPITALISANT | L96: 0.03 | M96: 0.015 | N96: 0.02 | O96: CDM | P96: Wafa Gestion | Q96: 2.1755664e+09 | R96: 2745.2 | S96: 0.028685 | T96: 5.5e-05 | U96: 0.000485 | V96: 0.002622 | W96: 0.005538 | X96: 0.01216 | Y96: 0.028685 | Z96: 0.067835 | AA96: 0.107883 | AB96: 0.140711
A97: MA0000037814 | B97: 3781 | C97: CFG CASH SECURE | D97: CFG GESTION | E97: FCP | F97: MONÉTAIRE | G97: ]0 0,5] | H97: CFG BONDS MONETAIRE | I97: QUOTIDIENNE | J97: FGP | K97: CAPITALISANT | L97: 0.005 | M97: 0.005 | N97: 0.006 | O97: CFG BANK | P97: CFG GESTION; CFG BANK | Q97: 62644690 | R97: 1238.82 | S97: 0.023488 | T97: 0.000113 | U97: 0.000533 | V97: 0.001949 | W97: 0.005177 | X97: 0.009921 | Y97: 0.023488 | Z97: 0.054234 | AA97: 0.087581 | AB97: 0.113296
A98: MA0000037889 | B98: 3788 | C98: FCP IRGAM OBLIBANQUES | D98: IRG ASSET MANAGEMENT | E98: FCP | F98: OCT | G98: ]0,5 1,1] | H98: MBI CT | I98: QUOTIDIENNE | J98: FGP | K98: CAPITALISANT | L98: 0.03 | M98: 0.015 | N98: 0.02 | O98: BANK OF AFRICA | P98: IRG ASSET MANAGEMENT | Q98: 9.6229951e+08 | R98: 130.61 | S98: 0.033062 | T98: 0.000383 | U98: 0.001073 | V98: 0.003843 | W98: 0.006939 | X98: 0.014132 | Y98: 0.033062 | Z98: 0.074449 | AA98: 0.109497 | AB98: 0.141895
A99: MA0000037954 | B99: 3795 | C99: CAPITAL TRUST TRÉSORERIE | D99: CAPITAL TRUST GESTION | E99: FCP | F99: MONÉTAIRE | G99: [0 0,5] | H99: Taux Repo | I99: QUOTIDIENNE | J99: FGP | K99: CAPITALISANT | L99: 0.02 | M99: 0.015 | N99: 0.02 | O99: ATTIJARIWAFA BANK | P99: CAPITAL TRUST GESTION | Q99: 1.1948174e+09 | R99: 1264.51 | S99: 0.028341 | T99: 0.000356 | U99: 0.000847 | V99: 0.002656 | W99: 0.006487 | X99: 0.012345 | Y99: 0.028341 | Z99: 0.063731 | AA99: 0.110447 | AB99: 0.13804
A100: MA0000037962 | B100: 3796 | C100: CAPITAL TRUST CASH PLUS | D100: CAPITAL TRUST GESTION | E100: FCP | F100: OCT | G100: ]0,5 1,1] | H100: MBI CT | I100: QUOTIDIENNE | J100: FGP | K100: CAPITALISANT | L100: 0.02 | M100: 0.015 | N100: 0.02 | O100: ATTIJARIWAFA BANK | P100: CAPITAL TRUST GESTION | Q100: 2.9405315e+09 | R100: 1283.88 | S100: 0.032963 | T100: 0.000156 | U100: 0.000655 | V100: 0.003023 | W100: 0.006089 | X100: 0.013219 | Y100: 0.032963 | Z100: 0.07561 | AA100: 0.105173 | AB100: 0.136871
A101: MA0000038002 | B101: 3800 | C101: CFG LIQUID BONDS | D101: CFG GESTION | E101: FCP | F101: OCT | G101: [0,5 1,1[ | H101: CFG BONDS CT | I101: QUOTIDIENNE | J101: FGP | K101: CAPITALISANT | L101: 0 | M101: 0 | N101: 0.01 | O101: CFG BANK | P101: CFG GESTION | Q101: 1.6034025e+09 | R101: 1268514.7 | S101: 0.033608 | T101: 0.000206 | U101: 0.001425 | V101: 0.003657 | W101: 0.006422 | X101: 0.013686 | Y101: 0.033608 | Z101: 0.079418 | AA101: 0.117319 | AB101: 0.153994
A102: MA0000038051 | B102: 3805 | C102: CAPITAL TRUST OBLIG PLUS | D102: CAPITAL TRUST GESTION | E102: FCP | F102: OMLT | G102: ]2 6] | H102: 70% MBI MT + 30% MBI MLT | I102: QUOTIDIENNE | J102: FGP | K102: CAPITALISANT | L102: 0.03 | M102: 0.015 | N102: 0.02 | O102: ATTIJARIWAFA BANK | P102: Capital Trust Gestion | Q102: 7.0694884e+08 | R102: 1304.14 | S102: 0.045822 | T102: -0.000399 | U102: 0.00076 | V102: 0.006941 | W102: 0.005195 | X102: 0.011895 | Y102: 0.045822 | Z102: 0.180046 | AA102: 0.196283 | AB102: 0.182926
A103: MA0000038077 | B103: 3807 | C103: CAPITAL TRUST ÉQUILIBRE | D103: CAPITAL TRUST GESTION | E103: FCP | F103: DIVERSIFIÉ | G103: - | H103: 70% MBI Global + 30% MASI | I103: QUOTIDIENNE | J103: FGP | K103: CAPITALISANT | L103: 0.03 | M103: 0.015 | N103: 0.02 | O103: ATTIJARIWAFA BANK | P103: CAPITAL TRUST GESTION | Q103: 1.384102e+09 | R103: 1280.96 | S103: 0.129913 | T103: 0.004139 | U103: -0.007615 | V103: 0.000242 | W103: -0.016213 | X103: -0.005126 | Y103: 0.129913 | Z103: 0.310673 | AA103: 0.340688 | AB103: 0.267073
A104: MA0000038101 | B104: 3810 | C104: FCP ALIF IV | D104: VALORIS MANAGEMENT | E104: FCP | F104: OMLT | G104: ]1,1 10] | H104: 50 % MBI MT + 50% MBI MLT | I104: QUOTIDIENNE | J104: FNPP | K104: CAPITALISANT | L104: 0.03 | M104: 0.015 | N104: 0.02 | O104: CDG CAPITAL | P104: VALORIS MANAGEMENT | Q104: 3.2124185e+09 | R104: 1363.12 | S104: 0.048973 | T104: -0.001999 | U104: -0.001955 | V104: 0.004591 | W104: -0.002422 | X104: 0.00652 | Y104: 0.048973 | Z104: 0.140095 | AA104: 0.179088 | AB104: 0.200215
A105: MA0000038119 | B105: 3811 | C105: FCP EMERGENCE TRESOR PLUS | D105: VALORIS MANAGEMENT | E105: FCP | F105: OCT | G105: ]0,5 1,1] | H105: MBI CT | I105: QUOTIDIENNE | J105: FGP | K105: CAPITALISANT | L105: 0.03 | M105: 0.015 | N105: 0.02 | O105: BCP | P105: VALORIS MANAGEMENT | Q105: 91173686 | R105: 1197.95 | S105: 0.025309 | T105: 0.000743 | U105: 0.00117 | V105: 0.002905 | W105: 0.005127 | X105: 0.009906 | Y105: 0.025309 | Z105: 0.056049 | AA105: 0.089323 | AB105: 0.112292
A106: MA0000038127 | B106: 3812 | C106: FCP EMERGENCE TRESOR | D106: VALORIS MANAGEMENT | E106: FCP | F106: MONÉTAIRE | G106: [0 0,5] | H106: TMP au jour le jour | I106: QUOTIDIENNE | J106: FGP | K106: CAPITALISANT | L106: 0 | M106: 0 | N106: 0.02 | O106: BCP | P106: VALORIS MANAGEMENT | Q106: 3.5854069e+08 | R106: 1162.9 | S106: 0.022078 | T106: 0.000396 | U106: 0.000628 | V106: 0.001878 | W106: 0.005065 | X106: 0.010313 | Y106: 0.022078 | Z106: 0.050934 | AA106: 0.081084 | AB106: 0.106955
A107: MA0000038143 | B107: 3814 | C107: CFG Profil Equilibré | D107: CFG GESTION | E107: FCP | F107: DIVERSIFIÉ | G107: - | H107: 25% CFG 25 FLOTTANT + 75% MBI MT | I107: QUOTIDIENNE | J107: FGP | K107: CAPITALISANT | L107: 0.002 | M107: 0.001 | N107: 0.02 | O107: CFG BANK | P107: CFG GESTION; CFG BANK | Q107: 39475864 | R107: 1388.14 | S107: 0.103055 | T107: 0.00234 | U107: -0.002006 | V107: 0.005476 | W107: 0.004428 | X107: 0.012384 | Y107: 0.103055 | Z107: 0.208402 | AA107: 0.278908 | AB107: 0.319161
... A121: MA0000038358 | B121: 3835 | C121: IRGAM BALANCE | D121: IRG ASSET MANAGEMENT | E121: FCP | F121: DIVERSIFIÉ | G121: - | H121: 50% MASI + 50% MBI GLOBAL | I121: QUOTIDIENNE | J121: FGP | K121: CAPITALISANT | L121: 0.03 | M121: 0.015 | N121: 0.02 | O121: ATTIJARIWAFA BANK | P121: IRG ASSET MANAGEMENT | Q121: 2.5005142e+09 | R121: 127.23 | S121: 0.151507 | T121: 0.003945 | U121: -0.008494 | V121: -0.000236 | W121: -0.017681 | X121: -0.003056 | Y121: 0.151507 | Z121: 0.34992 | AA121: 0.372492 | AB121: 0.25908
A122: MA0000038374 | B122: 3837 | C122: FCP CAPITAL OPPORTUNITE | D122: BMCE CAPITAL GESTION | E122: FCP | F122: DIVERSIFIÉ | G122: - | H122: 75% MBI + 25% MASI. | I122: QUOTIDIENNE | J122: FGP | K122: CAPITALISANT | L122: 0.03 | M122: 0.03 | N122: 0.02 | O122: BANK OF AFRICA | P122: BMCE CAPITAL GESTION; BANK OF AFRICA | Q122: 1319774 | R122: 1337.15 | S122: 0.101133 | T122: 0.000906 | U122: -0.000135 | V122: 0.001063 | W122: -0.001695 | X122: 0.004522 | Y122: 0.101133 | Z122: - | AA122: 0.315277 | AB122: -
A123: MA0000038382 | B123: 3838 | C123: FCP CAPITAL OBLIGATIONS BANQUES PLUS | D123: BMCE CAPITAL GESTION | E123: FCP | F123: OCT | G123: ]0,5 1,1] | H123: 90% MBI CT + 10% MBI MT | I123: QUOTIDIENNE | J123: FGP | K123: CAPITALISANT | L123: 0.01 | M123: 0.01 | N123: 0.01 | O123: BANK OF AFRICA | P123: BMCE CAPITAL GESTION; BANK OF AFRICA | Q123: 1.4375369e+09 | R123: 1214.2 | S123: 0.035282 | T123: 0.000544 | U123: 0.000849 | V123: 0.003106 | W123: 0.006516 | X123: 0.014141 | Y123: 0.035282 | Z123: 0.074304 | AA123: 0.11848 | AB123: 0.165483
A124: MA0000038390 | B124: 3839 | C124: FCP CAPITAL DIVERSIFIES | D124: BMCE CAPITAL GESTION | E124: FCP | F124: DIVERSIFIÉ | G124: - | H124: 75% MBI + 25% MASI. | I124: QUOTIDIENNE | J124: FGP | K124: CAPITALISANT | L124: 0.03 | M124: 0.03 | N124: 0.02 | O124: BANK OF AFRICA | P124: BMCE CAPITAL GESTION; BANK OF AFRICA | Q124: 1142649.3 | R124: 1142.64 | S124: 0.052756 | T124: 0.001815 | U124: 0.001165 | V124: 0.000981 | W124: -0.001948 | X124: -0.00132 | Y124: 0.052756 | Z124: 0.109607 | AA124: 0.135949 | AB124: 0.126897
...

Sheet Data_Analysis_2
A1: Code | B1: Intitulé | C1: 46017 | D1: 46387 | E1: 46024 | F1: 46031 | G1: 46038 | H1: 46045 | I1: 46052 | J1: 46059 | K1: 46066 | L1: 46073 | M1: 46080 | N1: 46087 | O1: 46094 | P1: 46105 | Q1: 46108 | R1: 46115 | S1: 46122 | T1: 46129 | U1: 46136 | V1: 46146 | W1: 46150 | X1: 46157 | Y1: 46164 | Z1: 46174 | AA1: 46178 | AB1: 46185 | AC1: 46192 | AD1: 46199 | AE1: 46206 | AF1: 46213 | AG1: 46220 | AH1: 46227 | AI1: 46234 | AJ1: 46241 | AK1: 46251 | AL1: =+AK1+7 -> 46258 | AM1: 45166 | AN1: =+AM1+7 -> 45173
A2: 3707 | B2: AD MOROCCAN EQUITY FUND | D2: =+_xlfn.XLOOKUP(A2,'31_12_25'!$B$3:$B$292,'31_12_25'!$R$3:$R$292,"non trouvé",1) -> 1565.11 | E2: 2460 | F2: 2483.45 | G2: 2436.31 | H2: 2352.91 | I2: 2341.56 | J2: 2304.68 | K2: 2327.56 | L2: 2347.75 | M2: 2262.37 | N2: 2114.92 | O2: 2053.86 | P2: 2113.55 | Q2: 2113.19 | R2: 2140.82 | S2: 2224.31 | T2: 2321.14 | U2: 2247.03 | V2: 2227.1 | W2: 2279.13 | X2: 2207.1 | Y2: 2183.36 | Z2: 2203.1 | AA2: 2183.2 | AB2: 2148.28 | AC2: 2203.27 | AD2: 2190.36 | AE2: 2225.14 | AF2: 2186.22 | AG2: 2152.04 | AH2: 2171.1 | AI2: 2179.9 | AJ2: 2265.42 | AK2: 2255.47 | AL2: =+_xlfn.XLOOKUP(A2,'24_08'!B2:B629,'24_08'!R2:R629,"non trouvé",0) -> 2271.62 | AM2: =+_xlfn.XLOOKUP(A2,'28_08'!B3:B629,'28_08'!R3:R629,"non trouvé",0) -> 2255.05 | AO2: =+B2 -> AD MOROCCAN EQUITY FUND
A3: 3899 | B3: AFG DYNAMIC FUND | D3: =+_xlfn.XLOOKUP(A3,'31_12_25'!$B$3:$B$292,'31_12_25'!$R$3:$R$292,"non trouvé",1) -> 8666.23 | E3: 8856.09 | F3: 8971.55 | G3: 8798.35 | H3: 8501.04 | I3: 8492.08 | J3: 8312.24 | K3: 8436.74 | L3: 8479.46 | M3: 8208.87 | N3: 7665.33 | O3: 7535.75 | P3: 7740.9 | Q3: 7774.55 | R3: 7926.18 | S3: 8378.96 | T3: 8799.63 | U3: 8585.5 | V3: 8483.86 | W3: 8619.27 | X3: 8344.84 | Y3: 8309.33 | Z3: 8526.75 | AA3: 8340.24 | AB3: 8109.41 | AC3: 8337.65 | AD3: 8176.86 | AE3: 8385.8 | AF3: 8220.91 | AG3: 8046.51 | AH3: 8138.16 | AI3: 8163.32 | AJ3: 8667.56 | AK3: 8632.29 | AL3: =+_xlfn.XLOOKUP(A3,'24_08'!B3:B630,'24_08'!R3:R630,"non trouvé",0) -> 8743.67 | AM3: =+_xlfn.XLOOKUP(A3,'28_08'!B4:B630,'28_08'!R4:R630,"non trouvé",0) -> 8656.53 | AO3: =+B3 -> AFG DYNAMIC FUND
A4: 3679 | B4: AFRICAPITAL EQUITY | D4: =+_xlfn.XLOOKUP(A4,'31_12_25'!$B$3:$B$292,'31_12_25'!$R$3:$R$292,"non trouvé",1) -> 1576.83 | E4: 3074.6 | F4: 3112.31 | G4: 3050.25 | H4: 2950.52 | I4: 2946.72 | J4: 2886.93 | K4: 2921.65 | L4: 2934.75 | M4: 2829.67 | N4: 2666.19 | O4: 2611.68 | P4: 2676.74 | Q4: 2671.61 | R4: 2710.38 | S4: 2847.52 | T4: 2981.78 | U4: 2899.7 | V4: 2868.97 | W4: 2914.18 | X4: 2822.91 | Y4: 2816.39 | Z4: 2887.34 | AA4: 2838.9 | AB4: 2764.09 | AC4: 2838.43 | AD4: 2793.4 | AE4: 2865.27 | AF4: 2805.77 | AG4: 2754.23 | AH4: 2782.76 | AI4: 2800.7 | AJ4: 2969.53 | AK4: 2962.24 | AL4: =+_xlfn.XLOOKUP(A4,'24_08'!B4:B631,'24_08'!R4:R631,"non trouvé",0) -> 3008.6 | AM4: =+_xlfn.XLOOKUP(A4,'28_08'!B5:B631,'28_08'!R5:R631,"non trouvé",0) -> 2976.25 | AO4: =+B4 -> AFRICAPITAL EQUITY
A5: 3587 | B5: FCP CAPITAL PARTICIPATIONS | D5: =+_xlfn.XLOOKUP(A5,'31_12_25'!$B$3:$B$292,'31_12_25'!$R$3:$R$292,"non trouvé",1) -> 11221.02 | E5: 11430 | F5: 11617.75 | G5: 11334.3 | H5: 10980.79 | I5: 10881.05 | J5: 10598.01 | K5: 10669.58 | L5: 10761.88 | M5: 10327.42 | N5: 9548.96 | O5: 9344.9 | P5: 9598.56 | Q5: 9611.07 | R5: 9641.88 | S5: 10091.65 | T5: 10516.17 | U5: 10215.72 | V5: 10101.74 | W5: 10287.18 | X5: 9913.1 | Y5: 9763.58 | Z5: 9769.46 | AA5: 9643.95 | AB5: 9592.48 | AC5: 9879.9 | AD5: 9812.04 | AE5: 9871.81 | AF5: 9675.59 | AG5: 9488.4 | AH5: 9535.24 | AI5: 9582.11 | AJ5: 10063.81 | AK5: 9990.71 | AL5: =+_xlfn.XLOOKUP(A5,'24_08'!B5:B632,'24_08'!R5:R632,"non trouvé",0) -> 9988.12 | AM5: =+_xlfn.XLOOKUP(A5,'28_08'!B6:B632,'28_08'!R6:R632,"non trouvé",0) -> 9927.86 | AO5: =+B5 -> FCP CAPITAL PARTICIPATIONS
A6: 3909 | B6: FCP Capital Trust Equity | D6: =+_xlfn.XLOOKUP(A6,'31_12_25'!$B$3:$B$292,'31_12_25'!$R$3:$R$292,"non trouvé",1) -> 1532.76 | E6: 1566.8 | F6: 1583.91 | G6: 1557.74 | H6: 1512.09 | I6: 1510.73 | J6: 1473.77 | K6: 1494.53 | L6: 1503.38 | M6: 1449.73 | N6: 1352.23 | O6: 1330.78 | P6: 1361.3 | Q6: 1360.11 | R6: 1374.17 | S6: 1432.61 | T6: 1483.89 | U6: 1447.99 | V6: 1436.32 | W6: 1456.64 | X6: 1406 | Y6: 1402.25 | Z6: 1446.35 | AA6: 1416.49 | AB6: 1375.87 | AC6: 1416.45 | AD6: 1388.35 | AE6: 1420.13 | AF6: 1394.03 | AG6: 1363.66 | AH6: 1379.48 | AI6: 1386.11 | AJ6: 1465.25 | AK6: 1461.35 | AL6: =+_xlfn.XLOOKUP(A6,'24_08'!B6:B633,'24_08'!R6:R633,"non trouvé",0) -> 1482.37 | AM6: =+_xlfn.XLOOKUP(A6,'28_08'!B7:B633,'28_08'!R7:R633,"non trouvé",0) -> 1467.89 | AO6: =+B6 -> FCP Capital Trust Equity
A7: 3574 | B7: FCP CFG PERFORMANCE | D7: =+_xlfn.XLOOKUP(A7,'31_12_25'!$B$3:$B$292,'31_12_25'!$R$3:$R$292,"non trouvé",1) -> 1223.82 | E7: 1251.26 | F7: 1264.24 | G7: 1248.05 | H7: 1210.64 | I7: 1210.93 | J7: 1181.48 | K7: 1204.65 | L7: 1211.16 | M7: 1172.99 | N7: 1091.06 | O7: 1069 | P7: 1092.38 | Q7: 1094.36 | R7: 1117.51 | S7: 1185.29 | T7: 1240.61 | U7: 1208.94 | V7: 1197.38 | W7: 1217.96 | X7: 1177.33 | Y7: 1167.1 | Z7: 1202.96 | AA7: 1173.7 | AB7: 1136.36 | AC7: 1166.33 | AD7: 1143.03 | AE7: 1173.2 | AF7: 1148.53 | AG7: 1121.94 | AH7: 1133.79 | AI7: 1137.63 | AJ7: 1204.26 | AK7: 1201 | AL7: =+_xlfn.XLOOKUP(A7,'24_08'!B7:B634,'24_08'!R7:R634,"non trouvé",0) -> 1216.49 | AM7: =+_xlfn.XLOOKUP(A7,'28_08'!B8:B634,'28_08'!R8:R634,"non trouvé",0) -> 1204.06 | AO7: =+B7 -> FCP CFG PERFORMANCE
A8: 3692 | B8: FCP IRGAM ACTIONS | D8: =+_xlfn.XLOOKUP(A8,'31_12_25'!$B$3:$B$292,'31_12_25'!$R$3:$R$292,"non trouvé",1) -> 266.55 | E8: 273.25 | F8: 276.58 | G8: 271.36 | H8: 262.14 | I8: 261.45 | J8: 256.5 | K8: 259.93 | L8: 261.53 | M8: 252.83 | N8: 237.86 | O8: 233.41 | P8: 238.99 | Q8: 238.87 | R8: 242.67 | S8: 254.78 | T8: 266.04 | U8: 259.27 | V8: 256.79 | W8: 260.68 | X8: 256.79 | Y8: 251.79 | Z8: 258.31 | AA8: 253.36 | AB8: 246.69 | AC8: 252.95 | AD8: 248.67 | AE8: 255.05 | AF8: 249.88 | AG8: 244.86 | AH8: 247.44 | AI8: 248.64 | AJ8: 262.91 | AK8: 262.24 | AL8: =+_xlfn.XLOOKUP(A8,'24_08'!B8:B635,'24_08'!R8:R635,"non trouvé",0) -> 266.1 | AM8: =+_xlfn.XLOOKUP(A8,'28_08'!B9:B635,'28_08'!R9:R635,"non trouvé",0) -> 263.42 | AO8: =+B8 -> FCP IRGAM ACTIONS
A9: 4100 | B9: ALPHA DYNAMIC FUND | D9: =+_xlfn.XLOOKUP(A9,'31_12_25'!$B$3:$B$292,'31_12_25'!$R$3:$R$292,"non trouvé",1) -> 151.98 | E9: 294.38 | F9: 297.58 | G9: 291.5 | H9: 281.92 | I9: 281.77 | J9: 276.57 | K9: 279.99 | L9: 281.84 | M9: 271.75 | N9: 254.98 | O9: 250.5 | P9: 256.85 | Q9: 255.58 | R9: 259.11 | S9: 270.99 | T9: 282.24 | U9: 274.54 | V9: 272.08 | W9: 275.62 | X9: 266.4 | Y9: 264.9 | Z9: 271.48 | AA9: 266.01 | AB9: 259.58 | AC9: 265.75 | AD9: 261.77 | AE9: 267.89 | AF9: 262.84 | AG9: 258.1 | AH9: 261.36 | AI9: 262.1 | AJ9: 275.66 | AK9: 275.27 | AL9: =+_xlfn.XLOOKUP(A9,'24_08'!B9:B636,'24_08'!R9:R636,"non trouvé",0) -> 278.88 | AM9: =+_xlfn.XLOOKUP(A9,'28_08'!B10:B636,'28_08'!R10:R636,"non trouvé",0) -> 276.18 | AO9: =+B9 -> ALPHA DYNAMIC FUND
A10: 4170 | B10: HORIZON EPARGNE | D10: =+_xlfn.XLOOKUP(A10,'31_12_25'!$B$3:$B$292,'31_12_25'!$R$3:$R$292,"non trouvé",1) -> 1512.86 | E10: 268.03 | F10: 271.39 | G10: 266.44 | H10: 257.62 | I10: 257.83 | J10: 252.6 | K10: 256.09 | L10: 257.61 | M10: 248.54 | N10: 232.68 | O10: 228.38 | P10: 233.65 | Q10: 233.75 | R10: 237.85 | S10: 251.51 | T10: 263.56 | U10: 257.13 | V10: 254.68 | W10: 258.85 | X10: 251.37 | Y10: 250.44 | Z10: 257.42 | AA10: 251.49 | AB10: 243.77 | AC10: 249.67 | AD10: 244.82 | AE10: 251.35 | AF10: 246.1 | AG10: 240.99 | AH10: 243.65 | AI10: 245.07 | AJ10: 259.35 | AK10: 258.61 | AL10: =+_xlfn.XLOOKUP(A10,'24_08'!B10:B637,'24_08'!R10:R637,"non trouvé",0) -> 262.6 | AM10: =+_xlfn.XLOOKUP(A10,'28_08'!B11:B637,'28_08'!R11:R637,"non trouvé",0) -> 259.75 | AO10: =+B10 -> HORIZON EPARGNE
A11: 4008 | B11: FCP KENZ ACTIONS | D11: =+_xlfn.XLOOKUP(A11,'31_12_25'!$B$3:$B$292,'31_12_25'!$R$3:$R$292,"non trouvé",1) -> 3213.82 | E11: 1236.79 | F11: 1251.92 | G11: 1232.91 | H11: 1193.77 | I11: 1197.32 | J11: 1170.2 | K11: 1188.25 | L11: 1195.73 | M11: 1156.3 | N11: 1081.76 | O11: 1062.34 | P11: 1085.63 | Q11: 1084.15 | R11: 1105.24 | S11: 1167.89 | T11: 1217.77 | U11: 1186.88 | V11: 1179.45 | W11: 1198.42 | X11: 1162.44 | Y11: 1155.07 | Z11: 1192.62 | AA11: 1166.16 | AB11: 1131.51 | AC11: 1161.06 | AD11: 1140.65 | AE11: 1170.01 | AF11: 1147.1 | AG11: 1126.61 | AH11: 1137.08 | AI11: 1144.63 | AJ11: 1206.57 | AK11: 1203.87 | AL11: =+_xlfn.XLOOKUP(A11,'24_08'!B11:B638,'24_08'!R11:R638,"non trouvé",0) -> 1219.33 | AM11: =+_xlfn.XLOOKUP(A11,'28_08'!B12:B638,'28_08'!R12:R638,"non trouvé",0) -> 1207.72 | AO11: =+B11 -> FCP KENZ ACTIONS
A12: 3972 | B12: FCP OPTIMA PERFORMANCE | D12: =+_xlfn.XLOOKUP(A12,'31_12_25'!$B$3:$B$292,'31_12_25'!$R$3:$R$292,"non trouvé",1) -> 991.78 | E12: 1011.42 | F12: 1026.34 | G12: 1008.99 | H12: 976.17 | I12: 975.43 | J12: 952.99 | K12: 966.41 | L12: 974.31 | M12: 943.06 | N12: 882.03 | O12: 867.17 | P12: 887.15 | Q12: 887.42 | R12: 903.71 | S12: 955.47 | T12: 1002.67 | U12: 979.5 | V12: 969.03 | W12: 986.21 | X12: 955.33 | Y12: 949.99 | Z12: 975.34 | AA12: 954.16 | AB12: 926.09 | AC12: 952.66 | AD12: 935.77 | AE12: 958.81 | AF12: 938.68 | AG12: 920.18 | AH12: 930.31 | AI12: 934.4 | AJ12: 990.37 | AK12: 988.25 | AL12: =+_xlfn.XLOOKUP(A12,'24_08'!B12:B639,'24_08'!R12:R639,"non trouvé",0) -> 1003.74 | AM12: =+_xlfn.XLOOKUP(A12,'28_08'!B13:B639,'28_08'!R13:R639,"non trouvé",0) -> 992.99 | AO12: =+B12 -> FCP OPTIMA PERFORMANCE
A13: 3516 | B13: FCP CAM INVESTISSEMENT | D13: =+_xlfn.XLOOKUP(A13,'31_12_25'!$B$3:$B$292,'31_12_25'!$R$3:$R$292,"non trouvé",1) -> 2239.45 | E13: 5280.46 | F13: 5387.19 | G13: 5287.34 | H13: 5132.82 | I13: 5109.86 | J13: 5077.26 | K13: 5129.03 | L13: 5164.29 | M13: 4951.62 | N13: 4635.76 | O13: 4502.45 | P13: 4631.12 | Q13: 4622.93 | R13: 4656.17 | S13: 4851.49 | T13: 5078.29 | U13: 4893.4 | V13: 4836.09 | W13: 4914.9 | X13: 4746.02 | Y13: 4685.25 | Z13: 4700.43 | AA13: 4651.8 | AB13: 4607.28 | AC13: 4732.86 | AD13: 4695 | AE13: 4774.23 | AF13: 4693.1 | AG13: 4594.6 | AH13: 4640.21 | AI13: 4651.83 | AJ13: 4888.87 | AK13: 4857.02 | AL13: =+_xlfn.XLOOKUP(A13,'24_08'!B13:B640,'24_08'!R13:R640,"non trouvé",0) -> 4891.8 | AM13: =+_xlfn.XLOOKUP(A13,'28_08'!B14:B640,'28_08'!R14:R640,"non trouvé",0) -> 4857.36 | AO13: =+B13 -> FCP CAM INVESTISSEMENT
